Workbook
Name DstStart: 'League Config'!$B$17
Name GateSize: 'League Config'!$B$19
Name KStart: 'League Config'!$B$18
Name NDst: 'League Config'!$B$22
Name NSkill: 'League Config'!$B$21

Sheet Draft Board
A1: Draft Board: go in order, mark every pick in the Pick column. Marked rows cross out. | P1: Freeze adjustments once the draft starts: picks attach to board slots, so do not edit Manual Adjustments mid-draft.
A2: Overall | B2: Pos | C2: Pos Rank | D2: Player / Defense | E2: Adj Rating | F2: Tier | G2: Draft Score | H2: Market ADP | I2: Draft Edge | J2: Pick | K2: Avail Rank | L2: 2026 Expectation | M2: Src | N2: Bye
A3: 1 | B3: =INDEX('Draft Engine'!$A$3:$A$232,$M3) -> WR | C3: =INDEX('Draft Engine'!$F$3:$F$232,$M3) -> 1 | D3: =INDEX('Draft Engine'!$B$3:$B$232,$M3) -> Puka Nacua | E3: =INDEX('Draft Engine'!$E$3:$E$232,$M3) -> 98.4859 | F3: =IF($E3>=95,"ELITE",IF($E3>=90,"TIER 1",IF($E3>=85,"TIER 2",IF($E3>=80,"TIER 3",IF($E3>=75,"TIER 4",IF($E3>=70,"TIER 5",IF($E3>=65,"TIER 6","TIER 7"))))))) -> ELITE | G3: =INDEX('Draft Engine'!$N$3:$N$232,$M3) -> 99.167245 | H3: =INDEX('Draft Engine'!$R$3:$R$232,$M3) -> 2.9 | I3: =INDEX('Draft Engine'!$S$3:$S$232,$M3) -> 1.9 | K3: =INDEX('Draft Engine'!$Z$3:$Z$232,$M3) -> 1 | L3: =INDEX('LIVE SOURCE'!$H$3:$H$232,$M3) -> Elite WR1 and first-round caliber target with overall WR1 upside. | M3: =MATCH($A3,'Draft Engine'!$Q$3:$Q$232,0) -> 86 | N3: =INDEX('LIVE SOURCE'!$L$3:$L$232,$M3) -> 11
A4: 2 | B4: =INDEX('Draft Engine'!$A$3:$A$232,$M4) -> RB | C4: =INDEX('Draft Engine'!$F$3:$F$232,$M4) -> 1 | D4: =INDEX('Draft Engine'!$B$3:$B$232,$M4) -> Bijan Robinson | E4: =INDEX('Draft Engine'!$E$3:$E$232,$M4) -> 97.3673 | F4: =IF($E4>=95,"ELITE",IF($E4>=90,"TIER 1",IF($E4>=85,"TIER 2",IF($E4>=80,"TIER 3",IF($E4>=75,"TIER 4",IF($E4>=70,"TIER 5",IF($E4>=65,"TIER 6","TIER 7"))))))) -> ELITE | G4: =INDEX('Draft Engine'!$N$3:$N$232,$M4) -> 98.552015 | H4: =INDEX('Draft Engine'!$R$3:$R$232,$M4) -> 1.8 | I4: =INDEX('Draft Engine'!$S$3:$S$232,$M4) -> -0.2 | K4: =INDEX('Draft Engine'!$Z$3:$Z$232,$M4) -> 2 | L4: =INDEX('LIVE SOURCE'!$H$3:$H$232,$M4) -> Elite RB1 and first-round roster anchor with league-winning ceiling. | M4: =MATCH($A4,'Draft Engine'!$Q$3:$Q$232,0) -> 33 | N4: =INDEX('LIVE SOURCE'!$L$3:$L$232,$M4) -> 11
A5: 3 | B5: =INDEX('Draft Engine'!$A$3:$A$232,$M5) -> WR | C5: =INDEX('Draft Engine'!$F$3:$F$232,$M5) -> 2 | D5: =INDEX('Draft Engine'!$B$3:$B$232,$M5) -> Ja'Marr Chase | E5: =INDEX('Draft Engine'!$E$3:$E$232,$M5) -> 96.7323 | F5: =IF($E5>=95,"ELITE",IF($E5>=90,"TIER 1",IF($E5>=85,"TIER 2",IF($E5>=80,"TIER 3",IF($E5>=75,"TIER 4",IF($E5>=70,"TIER 5",IF($E5>=65,"TIER 6","TIER 7"))))))) -> ELITE | G5: =INDEX('Draft Engine'!$N$3:$N$232,$M5) -> 98.202765 | H5: =INDEX('Draft Engine'!$R$3:$R$232,$M5) -> 3.9 | I5: =INDEX('Draft Engine'!$S$3:$S$232,$M5) -> 0.9 | K5: =INDEX('Draft Engine'!$Z$3:$Z$232,$M5) -> 3 | L5: =INDEX('LIVE SOURCE'!$H$3:$H$232,$M5) -> Elite WR1 and first-round caliber target with overall WR1 upside. | M5: =MATCH($A5,'Draft Engine'!$Q$3:$Q$232,0) -> 85 | N5: =INDEX('LIVE SOURCE'!$L$3:$L$232,$M5) -> 6
A6: 4 | B6: =INDEX('Draft Engine'!$A$3:$A$232,$M6) -> RB | C6: =INDEX('Draft Engine'!$F$3:$F$232,$M6) -> 2 | D6: =INDEX('Draft Engine'!$B$3:$B$232,$M6) -> Jahmyr Gibbs | E6: =INDEX('Draft Engine'!$E$3:$E$232,$M6) -> 96.3323 | F6: =IF($E6>=95,"ELITE",IF($E6>=90,"TIER 1",IF($E6>=85,"TIER 2",IF($E6>=80,"TIER 3",IF($E6>=75,"TIER 4",IF($E6>=70,"TIER 5",IF($E6>=65,"TIER 6","TIER 7"))))))) -> ELITE | G6: =INDEX('Draft Engine'!$N$3:$N$232,$M6) -> 97.982765 | H6: =INDEX('Draft Engine'!$R$3:$R$232,$M6) -> 1.8 | I6: =INDEX('Draft Engine'!$S$3:$S$232,$M6) -> -2.2 | K6: =INDEX('Draft Engine'!$Z$3:$Z$232,$M6) -> 4 | L6: =INDEX('LIVE SOURCE'!$H$3:$H$232,$M6) -> Elite RB1 and first-round roster anchor with league-winning ceiling. | M6: =MATCH($A6,'Draft Engine'!$Q$3:$Q$232,0) -> 34 | N6: =INDEX('LIVE SOURCE'!$L$3:$L$232,$M6) -> 6
A7: 5 | B7: =INDEX('Draft Engine'!$A$3:$A$232,$M7) -> RB | C7: =INDEX('Draft Engine'!$F$3:$F$232,$M7) -> 3 | D7: =INDEX('Draft Engine'!$B$3:$B$232,$M7) -> Christian McCaffrey | E7: =INDEX('Draft Engine'!$E$3:$E$232,$M7) -> 94.2447 | F7: =IF($E7>=95,"ELITE",IF($E7>=90,"TIER 1",IF($E7>=85,"TIER 2",IF($E7>=80,"TIER 3",IF($E7>=75,"TIER 4",IF($E7>=70,"TIER 5",IF($E7>=65,"TIER 6","TIER 7"))))))) -> TIER 1 | G7: =INDEX('Draft Engine'!$N$3:$N$232,$M7) -> 96.834585 | H7: =INDEX('Draft Engine'!$R$3:$R$232,$M7) -> 5.8 | I7: =INDEX('Draft Engine'!$S$3:$S$232,$M7) -> 0.8 | K7: =INDEX('Draft Engine'!$Z$3:$Z$232,$M7) -> 5 | L7: =INDEX('LIVE SOURCE'!$H$3:$H$232,$M7) -> Elite RB1 and first-round roster anchor with league-winning ceiling. | M7: =MATCH($A7,'Draft Engine'!$Q$3:$Q$232,0) -> 35 | N7: =INDEX('LIVE SOURCE'!$L$3:$L$232,$M7) -> 8
A8: 6 | B8: =INDEX('Draft Engine'!$A$3:$A$232,$M8) -> WR | C8: =INDEX('Draft Engine'!$F$3:$F$232,$M8) -> 3 | D8: =INDEX('Draft Engine'!$B$3:$B$232,$M8) -> Jaxon Smith-Njigba | E8: =INDEX('Draft Engine'!$E$3:$E$232,$M8) -> 94.0799 | F8: =IF($E8>=95,"ELITE",IF($E8>=90,"TIER 1",IF($E8>=85,"TIER 2",IF($E8>=80,"TIER 3",IF($E8>=75,"TIER 4",IF($E8>=70,"TIER 5",IF($E8>=65,"TIER 6","TIER 7"))))))) -> TIER 1 | G8: =INDEX('Draft Engine'!$N$3:$N$232,$M8) -> 96.743945 | H8: =INDEX('Draft Engine'!$R$3:$R$232,$M8) -> 5.7 | I8: =INDEX('Draft Engine'!$S$3:$S$232,$M8) -> -0.3 | K8: =INDEX('Draft Engine'!$Z$3:$Z$232,$M8) -> 6 | L8: =INDEX('LIVE SOURCE'!$H$3:$H$232,$M8) -> Elite WR1 and first-round caliber target with overall WR1 upside. | M8: =MATCH($A8,'Draft Engine'!$Q$3:$Q$232,0) -> 87 | N8: =INDEX('LIVE SOURCE'!$L$3:$L$232,$M8) -> 11
A9: 7 | B9: =INDEX('Draft Engine'!$A$3:$A$232,$M9) -> WR | C9: =INDEX('Draft Engine'!$F$3:$F$232,$M9) -> 4 | D9: =INDEX('Draft Engine'!$B$3:$B$232,$M9) -> Amon-Ra St. Brown | E9: =INDEX('Draft Engine'!$E$3:$E$232,$M9) -> 93.2639 | F9: =IF($E9>=95,"ELITE",IF($E9>=90,"TIER 1",IF($E9>=85,"TIER 2",IF($E9>=80,"TIER 3",IF($E9>=75,"TIER 4",IF($E9>=70,"TIER 5",IF($E9>=65,"TIER 6","TIER 7"))))))) -> TIER 1 | G9: =INDEX('Draft Engine'!$N$3:$N$232,$M9) -> 96.127145 | H9: =INDEX('Draft Engine'!$R$3:$R$232,$M9) -> 7 | I9: =INDEX('Draft Engine'!$S$3:$S$232,$M9) -> 0 | K9: =INDEX('Draft Engine'!$Z$3:$Z$232,$M9) -> 7 | L9: =INDEX('LIVE SOURCE'!$H$3:$H$232,$M9) -> Elite WR1 and first-round caliber target with overall WR1 upside. | M9: =MATCH($A9,'Draft Engine'!$Q$3:$Q$232,0) -> 88 | N9: =INDEX('LIVE SOURCE'!$L$3:$L$232,$M9) -> 6
A10: 8 | B10: =INDEX('Draft Engine'!$A$3:$A$232,$M10) -> RB | C10: =INDEX('Draft Engine'!$F$3:$F$232,$M10) -> 4 | D10: =INDEX('Draft Engine'!$B$3:$B$232,$M10) -> Jonathan Taylor | E10: =INDEX('Draft Engine'!$E$3:$E$232,$M10) -> 92.147 | F10: =IF($E10>=95,"ELITE",IF($E10>=90,"TIER 1",IF($E10>=85,"TIER 2",IF($E10>=80,"TIER 3",IF($E10>=75,"TIER 4",IF($E10>=70,"TIER 5",IF($E10>=65,"TIER 6","TIER 7"))))))) -> TIER 1 | G10: =INDEX('Draft Engine'!$N$3:$N$232,$M10) -> 94.72085 | H10: =INDEX('Draft Engine'!$R$3:$R$232,$M10) -> 7.4 | I10: =INDEX('Draft Engine'!$S$3:$S$232,$M10) -> -0.6 | K10: =INDEX('Draft Engine'!$Z$3:$Z$232,$M10) -> 8 | L10: =INDEX('LIVE SOURCE'!$H$3:$H$232,$M10) -> Elite RB1 and first-round roster anchor with league-winning ceiling. | M10: =MATCH($A10,'Draft Engine'!$Q$3:$Q$232,0) -> 36 | N10: =INDEX('LIVE SOURCE'!$L$3:$L$232,$M10) -> 13
A11: 9 | B11: =INDEX('Draft Engine'!$A$3:$A$232,$M11) -> WR | C11: =INDEX('Draft Engine'!$F$3:$F$232,$M11) -> 5 | D11: =INDEX('Draft Engine'!$B$3:$B$232,$M11) -> Nico Collins | E11: =INDEX('Draft Engine'!$E$3:$E$232,$M11) -> 91.4925 | F11: =IF($E11>=95,"ELITE",IF($E11>=90,"TIER 1",IF($E11>=85,"TIER 2",IF($E11>=80,"TIER 3",IF($E11>=75,"TIER 4",IF($E11>=70,"TIER 5",IF($E11>=65,"TIER 6","TIER 7"))))))) -> TIER 1 | G11: =INDEX('Draft Engine'!$N$3:$N$232,$M11) -> 93.820875 | H11: =INDEX('Draft Engine'!$R$3:$R$232,$M11) -> 23.8 | I11: =INDEX('Draft Engine'!$S$3:$S$232,$M11) -> 14.8 | K11: =INDEX('Draft Engine'!$Z$3:$Z$232,$M11) -> 9 | L11: =INDEX('LIVE SOURCE'!$H$3:$H$232,$M11) -> Elite WR1 and first-round caliber target with overall WR1 upside. | M11: =MATCH($A11,'Draft Engine'!$Q$3:$Q$232,0) -> 94 | N11: =INDEX('LIVE SOURCE'!$L$3:$L$232,$M11) -> 8
A12: 10 | B12: =INDEX('Draft Engine'!$A$3:$A$232,$M12) -> TE | C12: =INDEX('Draft Engine'!$F$3:$F$232,$M12) -> 1 | D12: =INDEX('Draft Engine'!$B$3:$B$232,$M12) -> Trey McBride | E12: =INDEX('Draft Engine'!$E$3:$E$232,$M12) -> 97.7371 | F12: =IF($E12>=95,"ELITE",IF($E12>=90,"TIER 1",IF($E12>=85,"TIER 2",IF($E12>=80,"TIER 3",IF($E12>=75,"TIER 4",IF($E12>=70,"TIER 5",IF($E12>=65,"TIER 6","TIER 7"))))))) -> ELITE | G12: =INDEX('Draft Engine'!$N$3:$N$232,$M12) -> 93.487405 | H12: =INDEX('Draft Engine'!$R$3:$R$232,$M12) -> 35.7 | I12: =INDEX('Draft Engine'!$S$3:$S$232,$M12) -> 25.7 | K12: =INDEX('Draft Engine'!$Z$3:$Z$232,$M12) -> 10 | L12: =INDEX('LIVE SOURCE'!$H$3:$H$232,$M12) -> Elite difference-making TE; positional advantage is the expectation. | M12: =MATCH($A12,'Draft Engine'!$Q$3:$Q$232,0) -> 159 | N12: =INDEX('LIVE SOURCE'!$L$3:$L$232,$M12) -> 14
A13: 11 | B13: =INDEX('Draft Engine'!$A$3:$A$232,$M13) -> RB | C13: =INDEX('Draft Engine'!$F$3:$F$232,$M13) -> 5 | D13: =INDEX('Draft Engine'!$B$3:$B$232,$M13) -> Jeremiyah Love | E13: =INDEX('Draft Engine'!$E$3:$E$232,$M13) -> 90.8659 | F13: =IF($E13>=95,"ELITE",IF($E13>=90,"TIER 1",IF($E13>=85,"TIER 2",IF($E13>=80,"TIER 3",IF($E13>=75,"TIER 4",IF($E13>=70,"TIER 5",IF($E13>=65,"TIER 6","TIER 7"))))))) -> TIER 1 | G13: =INDEX('Draft Engine'!$N$3:$N$232,$M13) -> 93.044245 | H13: =INDEX('Draft Engine'!$R$3:$R$232,$M13) -> 26.2 | I13: =INDEX('Draft Engine'!$S$3:$S$232,$M13) -> 15.2 | K13: =INDEX('Draft Engine'!$Z$3:$Z$232,$M13) -> 11 | L13: =INDEX('LIVE SOURCE'!$H$3:$H$232,$M13) -> Elite RB1 and first-round roster anchor with league-winning ceiling. | M13: =MATCH($A13,'Draft Engine'!$Q$3:$Q$232,0) -> 37 | N13: =INDEX('LIVE SOURCE'!$L$3:$L$232,$M13) -> 14
A14: 12 | B14: =INDEX('Draft Engine'!$A$3:$A$232,$M14) -> QB | C14: =INDEX('Draft Engine'!$F$3:$F$232,$M14) -> 1 | D14: =INDEX('Draft Engine'!$B$3:$B$232,$M14) -> Josh Allen | E14: =INDEX('Draft Engine'!$E$3:$E$232,$M14) -> 97.3099 | F14: =IF($E14>=95,"ELITE",IF($E14>=90,"TIER 1",IF($E14>=85,"TIER 2",IF($E14>=80,"TIER 3",IF($E14>=75,"TIER 4",IF($E14>=70,"TIER 5",IF($E14>=65,"TIER 6","TIER 7"))))))) -> ELITE | G14: =INDEX('Draft Engine'!$N$3:$N$232,$M14) -> 90.744445 | H14: =INDEX('Draft Engine'!$R$3:$R$232,$M14) -> 26.6 | I14: =INDEX('Draft Engine'!$S$3:$S$232,$M14) -> 14.6 | K14: =INDEX('Draft Engine'!$Z$3:$Z$232,$M14) -> 12 | L14: =INDEX('LIVE SOURCE'!$H$3:$H$232,$M14) -> Elite QB1; weekly top-5 expectation with overall QB1 upside. | M14: =MATCH($A14,'Draft Engine'!$Q$3:$Q$232,0) -> 1 | N14: =INDEX('LIVE SOURCE'!$L$3:$L$232,$M14) -> 7
... A232: 230 | B232: =INDEX('Draft Engine'!$A$3:$A$232,$M232) -> K | C232: =INDEX('Draft Engine'!$F$3:$F$232,$M232) -> 12 | D232: =INDEX('Draft Engine'!$B$3:$B$232,$M232) -> Evan McPherson | E232: =INDEX('Draft Engine'!$E$3:$E$232,$M232) -> 69.8 | F232: =IF($E232>=95,"ELITE",IF($E232>=90,"TIER 1",IF($E232>=85,"TIER 2",IF($E232>=80,"TIER 3",IF($E232>=75,"TIER 4",IF($E232>=70,"TIER 5",IF($E232>=65,"TIER 6","TIER 7"))))))) -> TIER 6 | G232: =INDEX('Draft Engine'!$N$3:$N$232,$M232) -> 36.006 | H232: =INDEX('Draft Engine'!$R$3:$R$232,$M232) -> 210 | I232: =INDEX('Draft Engine'!$S$3:$S$232,$M232) -> -20 | K232: =INDEX('Draft Engine'!$Z$3:$Z$232,$M232) -> 230 | L232: =INDEX('LIVE SOURCE'!$H$3:$H$232,$M232) -> Late-round kicker; treat as replaceable unless scoring strongly rewards distance. | M232: =MATCH($A232,'Draft Engine'!$Q$3:$Q$232,0) -> 198 | N232: =INDEX('LIVE SOURCE'!$L$3:$L$232,$M232) -> 6

Sheet League Config
A1: League Configuration (Editable)
A2: Blue cells are yours to edit. Everything downstream recalculates automatically.
A3: League Setting | B3: Value | C3: Notes | E3: Position | F3: Calc Repl Rank | G3: Override | H3: Effective Rank | I3: Replacement Points | J3: Scarcity Mult | K3: Pts Slope | L3: Pts Intercept
A4: Teams | B4: 10 | C4: League size. | E4: QB | F4: =ROUND($B$4*$B$6+$B$4*0.3,0) -> 13 | H4: =IF($G4="",$F4,$G4) -> 13 | I4: =ROUND(_xlfn.AGGREGATE(14,6,'Draft Engine'!$G$3:$G$232/('Draft Engine'!$A$3:$A$232=$E4),MIN($H4,COUNTIF('Draft Engine'!$A$3:$A$232,$E4))),1) -> 351.1 | J4: 1 | K4: 4.5 | L4: -30
A5: Scoring | B5: PPR | C5: Player model is PPR. | E5: RB | F5: =ROUND($B$4*$B$7+$B$4*$B$10*0.55+$B$4*0.6,0) -> 32 | H5: =IF($G5="",$F5,$G5) -> 32 | I5: =ROUND(_xlfn.AGGREGATE(14,6,'Draft Engine'!$G$3:$G$232/('Draft Engine'!$A$3:$A$232=$E5),MIN($H5,COUNTIF('Draft Engine'!$A$3:$A$232,$E5))),1) -> 239 | J5: 1.15 | K5: 4.2 | L5: -70
A6: Starting QB | B6: 1 | C6: Per team. | E6: WR | F6: =ROUND($B$4*$B$8+$B$4*$B$10*0.45+$B$4*0.8,0) -> 33 | H6: =IF($G6="",$F6,$G6) -> 33 | I6: =ROUND(_xlfn.AGGREGATE(14,6,'Draft Engine'!$G$3:$G$232/('Draft Engine'!$A$3:$A$232=$E6),MIN($H6,COUNTIF('Draft Engine'!$A$3:$A$232,$E6))),1) -> 239.3 | J6: 1.1 | K6: 4.2 | L6: -70
A7: Starting RB | B7: 2 | C7: Per team. | E7: TE | F7: =ROUND($B$4*$B$9+$B$4*0.3,0) -> 13 | H7: =IF($G7="",$F7,$G7) -> 13 | I7: =ROUND(_xlfn.AGGREGATE(14,6,'Draft Engine'!$G$3:$G$232/('Draft Engine'!$A$3:$A$232=$E7),MIN($H7,COUNTIF('Draft Engine'!$A$3:$A$232,$E7))),1) -> 179.7 | J7: 0.9 | K7: 3.5 | L7: -100
A8: Starting WR | B8: 2 | C8: Per team. | E8: K | F8: =ROUND($B$4*$B$11,0) -> 10 | H8: =IF($G8="",$F8,$G8) -> 10 | I8: =ROUND(_xlfn.AGGREGATE(14,6,'Draft Engine'!$G$3:$G$232/('Draft Engine'!$A$3:$A$232=$E8),MIN($H8,COUNTIF('Draft Engine'!$A$3:$A$232,$E8))),1) -> 108.4 | J8: 0.55 | K8: 2 | L8: -40
A9: Starting TE | B9: 1 | C9: Per team. | E9: DST | F9: =ROUND($B$4*$B$12,0) -> 10 | H9: =IF($G9="",$F9,$G9) -> 10 | I9: =ROUND(_xlfn.AGGREGATE(14,6,'Draft Engine'!$G$3:$G$232/('Draft Engine'!$A$3:$A$232=$E9),MIN($H9,COUNTIF('Draft Engine'!$A$3:$A$232,$E9))),1) -> 99.6 | J9: 0.5 | K9: 1.8 | L9: -50
A10: Starting FLEX | B10: 1 | C10: RB/WR/TE.
A11: Starting K | B11: 1 | C11: Per team. | E11: Projected points = Pts Slope x Adjusted Rating + Pts Intercept (per position). Tune the curve here.
A12: Starting DST | B12: 1 | C12: Per team.
A13: Bench | B13: 6 | C13: Per team.
A14: K Draft Penalty | B14: 18 | C14: Higher = drafts later.
A15: DST Draft Penalty | B15: 20 | C15: Higher = drafts later.
A16: QB 1QB Penalty | B16: 3 | C16: Set lower in Superflex.
A17: DST Gate Start | B17: 131 | C17: Top DSTs locked to overall 131-140.
A18: K Gate Start | B18: 141 | C18: Top Ks locked to overall 141-150. Keep = DST gate + gate size.
A19: Gate Size | B19: 10 | C19: How many DST/K get gated slots.
A21: Skill players (calc) | B21: =COUNTIF('LIVE SOURCE'!$A$3:$A$232,"QB")+COUNTIF('LIVE SOURCE'!$A$3:$A$232,"RB")+COUNTIF('LIVE SOURCE'!$A$3:$A$232,"WR")+COUNTIF('LIVE SOURCE'!$A$3:$A$232,"TE") -> 186
A22: DST count (calc) | B22: =COUNTIF('LIVE SOURCE'!$A$3:$A$232,"DST") -> 32

Sheet Manual Adjustments
A1: Manual Injury / Role Adjustments (the only place you tweak players)
A2: Pos | B2: Player | C2: Base Rating | D2: Injury Adj | E2: Role Adj | F2: Other Adj | G2: Total Adj | H2: News / Reason | I2: Last Updated | J2: Source
A3: ='LIVE SOURCE'!A3 -> QB | B3: ='LIVE SOURCE'!B3 -> Josh Allen | C3: ='LIVE SOURCE'!D3 -> 97.3099 | G3: =SUM(D3:F3) -> 0 | I3: 2026-08-12
A4: ='LIVE SOURCE'!A4 -> QB | B4: ='LIVE SOURCE'!B4 -> Caleb Williams | C4: ='LIVE SOURCE'!D4 -> 92.1927 | G4: =SUM(D4:F4) -> 0 | I4: 2026-08-12
A5: ='LIVE SOURCE'!A5 -> QB | B5: ='LIVE SOURCE'!B5 -> Drake Maye | C5: ='LIVE SOURCE'!D5 -> 91.043 | G5: =SUM(D5:F5) -> 0 | I5: 2026-08-12
A6: ='LIVE SOURCE'!A6 -> QB | B6: ='LIVE SOURCE'!B6 -> Justin Herbert | C6: ='LIVE SOURCE'!D6 -> 90.1169 | G6: =SUM(D6:F6) -> 0 | I6: 2026-08-12
A7: ='LIVE SOURCE'!A7 -> QB | B7: ='LIVE SOURCE'!B7 -> Lamar Jackson | C7: ='LIVE SOURCE'!D7 -> 88.7112 | G7: =SUM(D7:F7) -> 0 | I7: 2026-08-12
A8: ='LIVE SOURCE'!A8 -> QB | B8: ='LIVE SOURCE'!B8 -> Jalen Hurts | C8: ='LIVE SOURCE'!D8 -> 88.4499 | G8: =SUM(D8:F8) -> 0 | I8: 2026-08-12
A9: ='LIVE SOURCE'!A9 -> QB | B9: ='LIVE SOURCE'!B9 -> Patrick Mahomes II | C9: ='LIVE SOURCE'!D9 -> 87.0063 | G9: =SUM(D9:F9) -> 0 | I9: 2026-08-12
A10: ='LIVE SOURCE'!A10 -> QB | B10: ='LIVE SOURCE'!B10 -> Jayden Daniels | C10: ='LIVE SOURCE'!D10 -> 86.7003 | G10: =SUM(D10:F10) -> 0 | I10: 2026-08-12
A11: ='LIVE SOURCE'!A11 -> QB | B11: ='LIVE SOURCE'!B11 -> Joe Burrow | C11: ='LIVE SOURCE'!D11 -> 85.5913 | G11: =SUM(D11:F11) -> 0 | I11: 2026-08-12
A12: ='LIVE SOURCE'!A12 -> QB | B12: ='LIVE SOURCE'!B12 -> Matthew Stafford | C12: ='LIVE SOURCE'!D12 -> 85.4197 | G12: =SUM(D12:F12) -> 0 | I12: 2026-08-12
A13: ='LIVE SOURCE'!A13 -> QB | B13: ='LIVE SOURCE'!B13 -> Bo Nix | C13: ='LIVE SOURCE'!D13 -> 85.2485 | G13: =SUM(D13:F13) -> 0 | I13: 2026-08-12
A14: ='LIVE SOURCE'!A14 -> QB | B14: ='LIVE SOURCE'!B14 -> Dak Prescott | C14: ='LIVE SOURCE'!D14 -> 85.1156 | G14: =SUM(D14:F14) -> 0 | I14: 2026-08-12
... A78: ='LIVE SOURCE'!A78 -> RB | B78: ='LIVE SOURCE'!B78 -> Tyler Allgeier | C78: ='LIVE SOURCE'!D78 -> 63.0322 | G78: =SUM(D78:F78) -> 0 | I78: 2026-08-12
A79: ='LIVE SOURCE'!A79 -> RB | B79: ='LIVE SOURCE'!B79 -> Zach Charbonnet | C79: ='LIVE SOURCE'!D79 -> 62.5498 | D79: -25 | G79: =SUM(D79:F79) -> -25 | H79: Jan 2026 playoff ACL; opens on PUP, return may be as late as December (ESPN). Not draftable in a 10-team league. | I79: 2026-08-12
A80: ='LIVE SOURCE'!A80 -> RB | B80: ='LIVE SOURCE'!B80 -> Jonathon Brooks | C80: ='LIVE SOURCE'!D80 -> 62.2 | G80: =SUM(D80:F80) -> 0 | I80: 2026-08-12
A81: ='LIVE SOURCE'!A81 -> RB | B81: ='LIVE SOURCE'!B81 -> Emanuel Wilson | C81: ='LIVE SOURCE'!D81 -> 61.9821 | G81: =SUM(D81:F81) -> 0 | I81: 2026-08-12
A82: ='LIVE SOURCE'!A82 -> RB | B82: ='LIVE SOURCE'!B82 -> Isiah Pacheco | C82: ='LIVE SOURCE'!D82 -> 60.0092 | G82: =SUM(D82:F82) -> 0 | I82: 2026-08-12
A83: ='LIVE SOURCE'!A83 -> RB | B83: ='LIVE SOURCE'!B83 -> Alvin Kamara | C83: ='LIVE SOURCE'!D83 -> 59.15 | G83: =SUM(D83:F83) -> 0 | I83: 2026-08-12
A84: ='LIVE SOURCE'!A84 -> RB | B84: ='LIVE SOURCE'!B84 -> Justice Hill | C84: ='LIVE SOURCE'!D84 -> 54.88 | G84: =SUM(D84:F84) -> 0 | I84: 2026-08-12
A85: ='LIVE SOURCE'!A85 -> RB | B85: ='LIVE SOURCE'!B85 -> Tyjae Spears | C85: ='LIVE SOURCE'!D85 -> 63.4 | G85: =SUM(D85:F85) -> 0 | I85: 2026-08-12
A86: ='LIVE SOURCE'!A86 -> RB | B86: ='LIVE SOURCE'!B86 -> Keaton Mitchell | C86: ='LIVE SOURCE'!D86 -> 59 | G86: =SUM(D86:F86) -> 0 | I86: 2026-08-12
A87: ='LIVE SOURCE'!A87 -> WR | B87: ='LIVE SOURCE'!B87 -> Ja'Marr Chase | C87: ='LIVE SOURCE'!D87 -> 96.7323 | G87: =SUM(D87:F87) -> 0 | I87: 2026-08-12
A88: ='LIVE SOURCE'!A88 -> WR | B88: ='LIVE SOURCE'!B88 -> Puka Nacua | C88: ='LIVE SOURCE'!D88 -> 98.4859 | G88: =SUM(D88:F88) -> 0 | I88: 2026-08-12
A89: ='LIVE SOURCE'!A89 -> WR | B89: ='LIVE SOURCE'!B89 -> Jaxon Smith-Njigba | C89: ='LIVE SOURCE'!D89 -> 94.0799 | G89: =SUM(D89:F89) -> 0 | I89: 2026-08-12
A90: ='LIVE SOURCE'!A90 -> WR | B90: ='LIVE SOURCE'!B90 -> Amon-Ra St. Brown | C90: ='LIVE SOURCE'!D90 -> 93.2639 | G90: =SUM(D90:F90) -> 0 | I90: 2026-08-12
A91: ='LIVE SOURCE'!A91 -> WR | B91: ='LIVE SOURCE'!B91 -> A.J. Brown | C91: ='LIVE SOURCE'!D91 -> 83.2357 | G91: =SUM(D91:F91) -> 0 | I91: 2026-08-12
... A126: ='LIVE SOURCE'!A126 -> WR | B126: ='LIVE SOURCE'!B126 -> Brian Thomas Jr. | C126: ='LIVE SOURCE'!D126 -> 66.9675 | G126: =SUM(D126:F126) -> 0 | I126: 2026-08-12
A127: ='LIVE SOURCE'!A127 -> WR | B127: ='LIVE SOURCE'!B127 -> Makai Lemon | C127: ='LIVE SOURCE'!D127 -> 72.2 | D127: -3 | G127: =SUM(D127:F127) -> -3 | H127: Camp hamstring issue / missed practice time; temporary downgrade. | I127: 2026-08-12
A128: ='LIVE SOURCE'!A128 -> WR | B128: ='LIVE SOURCE'!B128 -> Parker Washington | C128: ='LIVE SOURCE'!D128 -> 71.53 | G128: =SUM(D128:F128) -> 0 | I128: 2026-08-12
A129: ='LIVE SOURCE'!A129 -> WR | B129: ='LIVE SOURCE'!B129 -> Chris Godwin Jr. | C129: ='LIVE SOURCE'!D129 -> 70.86 | G129: =SUM(D129:F129) -> 0 | I129: 2026-08-12
A130: ='LIVE SOURCE'!A130 -> WR | B130: ='LIVE SOURCE'!B130 -> Quentin Johnston | C130: ='LIVE SOURCE'!D130 -> 70.19 | G130: =SUM(D130:F130) -> 0 | I130: 2026-08-12
A131: ='LIVE SOURCE'!A131 -> WR | B131: ='LIVE SOURCE'!B131 -> Ricky Pearsall | C131: ='LIVE SOURCE'!D131 -> 69.52 | D131: -60 | G131: =SUM(D131:F131) -> -60 | H131: Season-ending PCL surgery announced 8/1/2026; out for the year (NFL.com). | I131: 2026-08-12
A132: ='LIVE SOURCE'!A132 -> WR | B132: ='LIVE SOURCE'!B132 -> Michael Wilson | C132: ='LIVE SOURCE'!D132 -> 68.85 | G132: =SUM(D132:F132) -> 0 | I132: 2026-08-12
A133: ='LIVE SOURCE'!A133 -> WR | B133: ='LIVE SOURCE'!B133 -> Xavier Worthy | C133: ='LIVE SOURCE'!D133 -> 68.18 | G133: =SUM(D133:F133) -> 0 | I133: 2026-08-12
A134: ='LIVE SOURCE'!A134 -> WR | B134: ='LIVE SOURCE'!B134 -> Matthew Golden | C134: ='LIVE SOURCE'!D134 -> 67.51 | G134: =SUM(D134:F134) -> 0 | I134: 2026-08-12
A135: ='LIVE SOURCE'!A135 -> WR | B135: ='LIVE SOURCE'!B135 -> Josh Downs | C135: ='LIVE SOURCE'!D135 -> 66.84 | G135: =SUM(D135:F135) -> 0 | I135: 2026-08-12
A136: ='LIVE SOURCE'!A136 -> WR | B136: ='LIVE SOURCE'!B136 -> Jayden Reed | C136: ='LIVE SOURCE'!D136 -> 66.17 | G136: =SUM(D136:F136) -> 0 | I136: 2026-08-12
A137: ='LIVE SOURCE'!A137 -> WR | B137: ='LIVE SOURCE'!B137 -> Khalil Shakir | C137: ='LIVE SOURCE'!D137 -> 65.5 | G137: =SUM(D137:F137) -> 0 | I137: 2026-08-12
A138: ='LIVE SOURCE'!A138 -> WR | B138: ='LIVE SOURCE'!B138 -> Jalin Hyatt | C138: ='LIVE SOURCE'!D138 -> 64.83 | G138: =SUM(D138:F138) -> 0 | I138: 2026-08-12
A139: ='LIVE SOURCE'!A139 -> WR | B139: ='LIVE SOURCE'!B139 -> Romeo Doubs | C139: ='LIVE SOURCE'!D139 -> 64.16 | G139: =SUM(D139:F139) -> 0 | I139: 2026-08-12
A140: ='LIVE SOURCE'!A140 -> WR | B140: ='LIVE SOURCE'!B140 -> Jalen Coker | C140: ='LIVE SOURCE'!D140 -> 63.49 | G140: =SUM(D140:F140) -> 0 | I140: 2026-08-12
A141: ='LIVE SOURCE'!A141 -> WR | B141: ='LIVE SOURCE'!B141 -> KC Concepcion | C141: ='LIVE SOURCE'!D141 -> 62.82 | G141: =SUM(D141:F141) -> 0 | I141: 2026-08-12
A142: ='LIVE SOURCE'!A142 -> WR | B142: ='LIVE SOURCE'!B142 -> Rashid Shaheed | C142: ='LIVE SOURCE'!D142 -> 62.15 | G142: =SUM(D142:F142) -> 0 | I142: 2026-08-12
A143: ='LIVE SOURCE'!A143 -> WR | B143: ='LIVE SOURCE'!B143 -> Calvin Ridley | C143: ='LIVE SOURCE'!D143 -> 61.48 | G143: =SUM(D143:F143) -> 0 | I143: 2026-08-12
... A232: ='LIVE SOURCE'!A232 -> DST | B232: ='LIVE SOURCE'!B232 -> Las Vegas Raiders | C232: ='LIVE SOURCE'!D232 -> 58.9 | G232: =SUM(D232:F232) -> 0 | I232: 2026-08-12

Sheet LIVE SOURCE
A1: LIVE SOURCE: the one canonical table. Every other tab reads from here.
A2: Pos | B2: Player | C2: Team | D2: Base Rating | E2: Market ADP | F2: Confidence | G2: Model Path | H2: 2026 Expectation | I2: Why | J2: Main Risk | K2: Source | L2: Bye
A3: QB | B3: Josh Allen | C3: BUF | D3: 97.3099 | E3: 26.6 | F3: A | G3: RATE-ADJUSTED VETERAN | H3: Elite QB1; weekly top-5 expectation with overall QB1 upside. | I3: He produced 22.0 PPR/FP points per game across 17 games. The workload/efficiency profile gives the model a rate-based reason to keep him here. Market price is favorable around ADP 23 versus model overall rank 10. | J3: Passing-TD efficiency, rushing volume and supporting-cast health are the main swing factors. | K3: https://www.fantasypros.com/nfl/adp/ppr-overall.php | L3: 7
A4: QB | B4: Caleb Williams | C4: CHI | D4: 92.1927 | E4: 107.5 | F4: A | G4: RATE-ADJUSTED VETERAN | H4: Elite QB1; weekly top-5 expectation with overall QB1 upside. | I4: He produced 19.0 PPR/FP points per game across 17 games. The workload/efficiency profile gives the model a rate-based reason to keep him here. | J4: Passing-TD efficiency, rushing volume and supporting-cast health are the main swing factors. | K4: ADP proxy — editable; based on positional draft cost | L4: 10
A5: QB | B5: Drake Maye | C5: NE | D5: 91.043 | E5: 49.8 | F5: A | G5: RATE-ADJUSTED VETERAN | H5: Elite QB1; weekly top-5 expectation with overall QB1 upside. | I5: He produced 21.1 PPR/FP points per game across 17 games. The workload/efficiency profile gives the model a rate-based reason to keep him here. | J5: Passing-TD efficiency, rushing volume and supporting-cast health are the main swing factors. | K5: ADP proxy — editable; based on positional draft cost | L5: 11
A6: QB | B6: Justin Herbert | C6: LAC | D6: 90.1169 | E6: 104.2 | F6: A | G6: RATE-ADJUSTED VETERAN | H6: Strong every-week QB1; frequent top-8 finishes expected. | I6: He produced 18.7 PPR/FP points per game across 16 games. The workload/efficiency profile gives the model a rate-based reason to keep him here. | J6: Passing-TD efficiency, rushing volume and supporting-cast health are the main swing factors. | K6: ADP proxy — editable; based on positional draft cost | L6: 7
A7: QB | B7: Lamar Jackson | C7: BAL | D7: 88.7112 | E7: 52.6 | F7: A | G7: RATE-ADJUSTED VETERAN | H7: Strong every-week QB1; frequent top-8 finishes expected. | I7: He produced 17.1 PPR/FP points per game across 13 games. The workload/efficiency profile gives the model a rate-based reason to keep him here. | J7: Passing-TD efficiency, rushing volume and supporting-cast health are the main swing factors. | K7: ADP proxy — editable; based on positional draft cost | L7: 13
A8: QB | B8: Jalen Hurts | C8: PHI | D8: 88.4499 | E8: 73.7 | F8: A | G8: RATE-ADJUSTED VETERAN | H8: Strong every-week QB1; frequent top-8 finishes expected. | I8: He produced 19.1 PPR/FP points per game across 16 games. The workload/efficiency profile gives the model a rate-based reason to keep him here. | J8: Passing-TD efficiency, rushing volume and supporting-cast health are the main swing factors. | K8: ADP proxy — editable; based on positional draft cost | L8: 10
A9: QB | B9: Patrick Mahomes II | C9: KC | D9: 87.0063 | E9: 97.4 | F9: A | G9: RATE-ADJUSTED VETERAN | H9: Strong every-week QB1; frequent top-8 finishes expected. | I9: He produced 21.1 PPR/FP points per game across 14 games. The workload/efficiency profile gives the model a rate-based reason to keep him here. | J9: Passing-TD efficiency, rushing volume and supporting-cast health are the main swing factors. | K9: ADP proxy — editable; based on positional draft cost | L9: 5
A10: QB | B10: Jayden Daniels | C10: WAS | D10: 86.7003 | E10: 67 | F10: B | G10: RATE-ADJUSTED VETERAN | H10: Strong every-week QB1; frequent top-8 finishes expected. | I10: He produced 16.7 PPR/FP points per game across 7 games. The workload/efficiency profile gives the model a rate-based reason to keep him here. Market price is favorable around ADP 78 versus model overall rank 64. | J10: Availability/sample risk is elevated after only 7 games; talent is not being punished as heavily as durability. | K10: ADP proxy — editable; based on positional draft cost | L10: 7
A11: QB | B11: Joe Burrow | C11: CIN | D11: 85.5913 | E11: 57.3 | F11: B | G11: RATE-ADJUSTED VETERAN | H11: Low-end QB1/high-end QB2 in a 10-team league; startable most weeks. | I11: He produced 17.4 PPR/FP points per game across 8 games. The workload/efficiency profile gives the model a rate-based reason to keep him here. Market price is favorable around ADP 86 versus model overall rank 70. | J11: Availability/sample risk is elevated after only 8 games; talent is not being punished as heavily as durability. | K11: ADP proxy — editable; based on positional draft cost | L11: 6
A12: QB | B12: Matthew Stafford | C12: LAR | D12: 85.4197 | E12: 83.7 | F12: A | G12: RATE-ADJUSTED VETERAN | H12: Low-end QB1/high-end QB2 in a 10-team league; startable most weeks. | I12: He produced 21.1 PPR/FP points per game across 17 games. The workload/efficiency profile gives the model a rate-based reason to keep him here. Market price is favorable around ADP 94 versus model overall rank 77. | J12: Passing-TD efficiency, rushing volume and supporting-cast health are the main swing factors. | K12: ADP proxy — editable; based on positional draft cost | L12: 11
A13: QB | B13: Bo Nix | C13: DEN | D13: 85.2485 | E13: 121.5 | F13: A | G13: RATE-ADJUSTED VETERAN | H13: Low-end QB1/high-end QB2 in a 10-team league; startable most weeks. | I13: He produced 18.6 PPR/FP points per game across 17 games. The workload/efficiency profile gives the model a rate-based reason to keep him here. Market price is favorable around ADP 102 versus model overall rank 79. | J13: Passing-TD efficiency, rushing volume and supporting-cast health are the main swing factors. | K13: ADP proxy — editable; based on positional draft cost | L13: 10
A14: QB | B14: Dak Prescott | C14: DAL | D14: 85.1156 | E14: 65.4 | F14: A | G14: RATE-ADJUSTED VETERAN | H14: Low-end QB1/high-end QB2 in a 10-team league; startable most weeks. | I14: He produced 19.0 PPR/FP points per game across 17 games. The workload/efficiency profile gives the model a rate-based reason to keep him here. Market price is favorable around ADP 110 versus model overall rank 82. | J14: Passing-TD efficiency, rushing volume and supporting-cast health are the main swing factors. | K14: ADP proxy — editable; based on positional draft cost | L14: 14
... A232: DST | B232: Las Vegas Raiders | C232: LV | D232: 58.9 | E232: 284 | F232: B | G232: DST MODEL | H232: Streaming/late-round defense; matchup matters more than preseason rank. | I232: The unit grades well relative to the current DST pool, but the model intentionally keeps defense behind core skill positions. | J232: DST scoring is highly opponent- and turnover-dependent, making season-long rank fragile. | K232: https://www.si.com/fantasy/2026-football-defense-rankings-seasonal-leagues | L232: 13

Sheet FINAL Master
A1: 2026 FINAL Master: every player, live-ranked, K/DST gated to the final rounds.
A2: Overall | B2: Pos | C2: Pos Rank | D2: Player / Defense | E2: Adj Rating | F2: Tier | G2: Proj Points | H2: VORP | I2: Draft Score | J2: Market ADP | K2: Draft Edge | L2: Confidence | M2: Model Path | N2: 2026 Expectation | O2: Main Risk | P2: Src
A3: =1 -> 1 | B3: =INDEX('Draft Engine'!$A$3:$A$232,$P3) -> WR | C3: =INDEX('Draft Engine'!$F$3:$F$232,$P3) -> 1 | D3: =INDEX('Draft Engine'!$B$3:$B$232,$P3) -> Puka Nacua | E3: =INDEX('Draft Engine'!$E$3:$E$232,$P3) -> 98.4859 | F3: =IF($E3>=95,"ELITE",IF($E3>=90,"TIER 1",IF($E3>=85,"TIER 2",IF($E3>=80,"TIER 3",IF($E3>=75,"TIER 4",IF($E3>=70,"TIER 5",IF($E3>=65,"TIER 6","TIER 7"))))))) -> ELITE | G3: =INDEX('Draft Engine'!$G$3:$G$232,$P3) -> 343.6 | H3: =INDEX('Draft Engine'!$J$3:$J$232,$P3) -> 104.3 | I3: =INDEX('Draft Engine'!$N$3:$N$232,$P3) -> 99.167245 | J3: =INDEX('Draft Engine'!$R$3:$R$232,$P3) -> 2.9 | K3: =INDEX('Draft Engine'!$S$3:$S$232,$P3) -> 1.9 | L3: =INDEX('Draft Engine'!$T$3:$T$232,$P3) -> A | M3: =INDEX('Draft Engine'!$X$3:$X$232,$P3) -> HISTORY FALLBACK | N3: =INDEX('LIVE SOURCE'!$H$3:$H$232,$P3) -> Elite WR1 and first-round caliber target with overall WR1 upside. | O3: =INDEX('LIVE SOURCE'!$J$3:$J$232,$P3) -> Target competition, quarterback efficiency and touchdown regression are the main downside paths. | P3: =MATCH($A3,'Draft Engine'!$Q$3:$Q$232,0) -> 86
A4: =2 -> 2 | B4: =INDEX('Draft Engine'!$A$3:$A$232,$P4) -> RB | C4: =INDEX('Draft Engine'!$F$3:$F$232,$P4) -> 1 | D4: =INDEX('Draft Engine'!$B$3:$B$232,$P4) -> Bijan Robinson | E4: =INDEX('Draft Engine'!$E$3:$E$232,$P4) -> 97.3673 | F4: =IF($E4>=95,"ELITE",IF($E4>=90,"TIER 1",IF($E4>=85,"TIER 2",IF($E4>=80,"TIER 3",IF($E4>=75,"TIER 4",IF($E4>=70,"TIER 5",IF($E4>=65,"TIER 6","TIER 7"))))))) -> ELITE | G4: =INDEX('Draft Engine'!$G$3:$G$232,$P4) -> 338.9 | H4: =INDEX('Draft Engine'!$J$3:$J$232,$P4) -> 99.9 | I4: =INDEX('Draft Engine'!$N$3:$N$232,$P4) -> 98.552015 | J4: =INDEX('Draft Engine'!$R$3:$R$232,$P4) -> 1.8 | K4: =INDEX('Draft Engine'!$S$3:$S$232,$P4) -> -0.2 | L4: =INDEX('Draft Engine'!$T$3:$T$232,$P4) -> A | M4: =INDEX('Draft Engine'!$X$3:$X$232,$P4) -> RATE-ADJUSTED VETERAN | N4: =INDEX('LIVE SOURCE'!$H$3:$H$232,$P4) -> Elite RB1 and first-round roster anchor with league-winning ceiling. | O4: =INDEX('LIVE SOURCE'!$J$3:$J$232,$P4) -> Touchdown variance, receiving-role changes and backfield competition are the main downside paths. | P4: =MATCH($A4,'Draft Engine'!$Q$3:$Q$232,0) -> 33
A5: =3 -> 3 | B5: =INDEX('Draft Engine'!$A$3:$A$232,$P5) -> WR | C5: =INDEX('Draft Engine'!$F$3:$F$232,$P5) -> 2 | D5: =INDEX('Draft Engine'!$B$3:$B$232,$P5) -> Ja'Marr Chase | E5: =INDEX('Draft Engine'!$E$3:$E$232,$P5) -> 96.7323 | F5: =IF($E5>=95,"ELITE",IF($E5>=90,"TIER 1",IF($E5>=85,"TIER 2",IF($E5>=80,"TIER 3",IF($E5>=75,"TIER 4",IF($E5>=70,"TIER 5",IF($E5>=65,"TIER 6","TIER 7"))))))) -> ELITE | G5: =INDEX('Draft Engine'!$G$3:$G$232,$P5) -> 336.3 | H5: =INDEX('Draft Engine'!$J$3:$J$232,$P5) -> 97 | I5: =INDEX('Draft Engine'!$N$3:$N$232,$P5) -> 98.202765 | J5: =INDEX('Draft Engine'!$R$3:$R$232,$P5) -> 3.9 | K5: =INDEX('Draft Engine'!$S$3:$S$232,$P5) -> 0.9 | L5: =INDEX('Draft Engine'!$T$3:$T$232,$P5) -> A | M5: =INDEX('Draft Engine'!$X$3:$X$232,$P5) -> HISTORY FALLBACK | N5: =INDEX('LIVE SOURCE'!$H$3:$H$232,$P5) -> Elite WR1 and first-round caliber target with overall WR1 upside. | O5: =INDEX('LIVE SOURCE'!$J$3:$J$232,$P5) -> Target competition, quarterback efficiency and touchdown regression are the main downside paths. | P5: =MATCH($A5,'Draft Engine'!$Q$3:$Q$232,0) -> 85
A6: =4 -> 4 | B6: =INDEX('Draft Engine'!$A$3:$A$232,$P6) -> RB | C6: =INDEX('Draft Engine'!$F$3:$F$232,$P6) -> 2 | D6: =INDEX('Draft Engine'!$B$3:$B$232,$P6) -> Jahmyr Gibbs | E6: =INDEX('Draft Engine'!$E$3:$E$232,$P6) -> 96.3323 | F6: =IF($E6>=95,"ELITE",IF($E6>=90,"TIER 1",IF($E6>=85,"TIER 2",IF($E6>=80,"TIER 3",IF($E6>=75,"TIER 4",IF($E6>=70,"TIER 5",IF($E6>=65,"TIER 6","TIER 7"))))))) -> ELITE | G6: =INDEX('Draft Engine'!$G$3:$G$232,$P6) -> 334.6 | H6: =INDEX('Draft Engine'!$J$3:$J$232,$P6) -> 95.6 | I6: =INDEX('Draft Engine'!$N$3:$N$232,$P6) -> 97.982765 | J6: =INDEX('Draft Engine'!$R$3:$R$232,$P6) -> 1.8 | K6: =INDEX('Draft Engine'!$S$3:$S$232,$P6) -> -2.2 | L6: =INDEX('Draft Engine'!$T$3:$T$232,$P6) -> A | M6: =INDEX('Draft Engine'!$X$3:$X$232,$P6) -> RATE-ADJUSTED VETERAN | N6: =INDEX('LIVE SOURCE'!$H$3:$H$232,$P6) -> Elite RB1 and first-round roster anchor with league-winning ceiling. | O6: =INDEX('LIVE SOURCE'!$J$3:$J$232,$P6) -> Touchdown variance, receiving-role changes and backfield competition are the main downside paths. | P6: =MATCH($A6,'Draft Engine'!$Q$3:$Q$232,0) -> 34
A7: =5 -> 5 | B7: =INDEX('Draft Engine'!$A$3:$A$232,$P7) -> RB | C7: =INDEX('Draft Engine'!$F$3:$F$232,$P7) -> 3 | D7: =INDEX('Draft Engine'!$B$3:$B$232,$P7) -> Christian McCaffrey | E7: =INDEX('Draft Engine'!$E$3:$E$232,$P7) -> 94.2447 | F7: =IF($E7>=95,"ELITE",IF($E7>=90,"TIER 1",IF($E7>=85,"TIER 2",IF($E7>=80,"TIER 3",IF($E7>=75,"TIER 4",IF($E7>=70,"TIER 5",IF($E7>=65,"TIER 6","TIER 7"))))))) -> TIER 1 | G7: =INDEX('Draft Engine'!$G$3:$G$232,$P7) -> 325.8 | H7: =INDEX('Draft Engine'!$J$3:$J$232,$P7) -> 86.8 | I7: =INDEX('Draft Engine'!$N$3:$N$232,$P7) -> 96.834585 | J7: =INDEX('Draft Engine'!$R$3:$R$232,$P7) -> 5.8 | K7: =INDEX('Draft Engine'!$S$3:$S$232,$P7) -> 0.8 | L7: =INDEX('Draft Engine'!$T$3:$T$232,$P7) -> A | M7: =INDEX('Draft Engine'!$X$3:$X$232,$P7) -> RATE-ADJUSTED VETERAN | N7: =INDEX('LIVE SOURCE'!$H$3:$H$232,$P7) -> Elite RB1 and first-round roster anchor with league-winning ceiling. | O7: =INDEX('LIVE SOURCE'!$J$3:$J$232,$P7) -> Touchdown variance, receiving-role changes and backfield competition are the main downside paths. | P7: =MATCH($A7,'Draft Engine'!$Q$3:$Q$232,0) -> 35
A8: =6 -> 6 | B8: =INDEX('Draft Engine'!$A$3:$A$232,$P8) -> WR | C8: =INDEX('Draft Engine'!$F$3:$F$232,$P8) -> 3 | D8: =INDEX('Draft Engine'!$B$3:$B$232,$P8) -> Jaxon Smith-Njigba | E8: =INDEX('Draft Engine'!$E$3:$E$232,$P8) -> 94.0799 | F8: =IF($E8>=95,"ELITE",IF($E8>=90,"TIER 1",IF($E8>=85,"TIER 2",IF($E8>=80,"TIER 3",IF($E8>=75,"TIER 4",IF($E8>=70,"TIER 5",IF($E8>=65,"TIER 6","TIER 7"))))))) -> TIER 1 | G8: =INDEX('Draft Engine'!$G$3:$G$232,$P8) -> 325.1 | H8: =INDEX('Draft Engine'!$J$3:$J$232,$P8) -> 85.8 | I8: =INDEX('Draft Engine'!$N$3:$N$232,$P8) -> 96.743945 | J8: =INDEX('Draft Engine'!$R$3:$R$232,$P8) -> 5.7 | K8: =INDEX('Draft Engine'!$S$3:$S$232,$P8) -> -0.3 | L8: =INDEX('Draft Engine'!$T$3:$T$232,$P8) -> A | M8: =INDEX('Draft Engine'!$X$3:$X$232,$P8) -> HISTORY FALLBACK | N8: =INDEX('LIVE SOURCE'!$H$3:$H$232,$P8) -> Elite WR1 and first-round caliber target with overall WR1 upside. | O8: =INDEX('LIVE SOURCE'!$J$3:$J$232,$P8) -> Target competition, quarterback efficiency and touchdown regression are the main downside paths. | P8: =MATCH($A8,'Draft Engine'!$Q$3:$Q$232,0) -> 87
A9: =7 -> 7 | B9: =INDEX('Draft Engine'!$A$3:$A$232,$P9) -> WR | C9: =INDEX('Draft Engine'!$F$3:$F$232,$P9) -> 4 | D9: =INDEX('Draft Engine'!$B$3:$B$232,$P9) -> Amon-Ra St. Brown | E9: =INDEX('Draft Engine'!$E$3:$E$232,$P9) -> 93.2639 | F9: =IF($E9>=95,"ELITE",IF($E9>=90,"TIER 1",IF($E9>=85,"TIER 2",IF($E9>=80,"TIER 3",IF($E9>=75,"TIER 4",IF($E9>=70,"TIER 5",IF($E9>=65,"TIER 6","TIER 7"))))))) -> TIER 1 | G9: =INDEX('Draft Engine'!$G$3:$G$232,$P9) -> 321.7 | H9: =INDEX('Draft Engine'!$J$3:$J$232,$P9) -> 82.4 | I9: =INDEX('Draft Engine'!$N$3:$N$232,$P9) -> 96.127145 | J9: =INDEX('Draft Engine'!$R$3:$R$232,$P9) -> 7 | K9: =INDEX('Draft Engine'!$S$3:$S$232,$P9) -> 0 | L9: =INDEX('Draft Engine'!$T$3:$T$232,$P9) -> A | M9: =INDEX('Draft Engine'!$X$3:$X$232,$P9) -> HISTORY FALLBACK | N9: =INDEX('LIVE SOURCE'!$H$3:$H$232,$P9) -> Elite WR1 and first-round caliber target with overall WR1 upside. | O9: =INDEX('LIVE SOURCE'!$J$3:$J$232,$P9) -> Target competition, quarterback efficiency and touchdown regression are the main downside paths. | P9: =MATCH($A9,'Draft Engine'!$Q$3:$Q$232,0) -> 88
A10: =8 -> 8 | B10: =INDEX('Draft Engine'!$A$3:$A$232,$P10) -> RB | C10: =INDEX('Draft Engine'!$F$3:$F$232,$P10) -> 4 | D10: =INDEX('Draft Engine'!$B$3:$B$232,$P10) -> Jonathan Taylor | E10: =INDEX('Draft Engine'!$E$3:$E$232,$P10) -> 92.147 | F10: =IF($E10>=95,"ELITE",IF($E10>=90,"TIER 1",IF($E10>=85,"TIER 2",IF($E10>=80,"TIER 3",IF($E10>=75,"TIER 4",IF($E10>=70,"TIER 5",IF($E10>=65,"TIER 6","TIER 7"))))))) -> TIER 1 | G10: =INDEX('Draft Engine'!$G$3:$G$232,$P10) -> 317 | H10: =INDEX('Draft Engine'!$J$3:$J$232,$P10) -> 78 | I10: =INDEX('Draft Engine'!$N$3:$N$232,$P10) -> 94.72085 | J10: =INDEX('Draft Engine'!$R$3:$R$232,$P10) -> 7.4 | K10: =INDEX('Draft Engine'!$S$3:$S$232,$P10) -> -0.6 | L10: =INDEX('Draft Engine'!$T$3:$T$232,$P10) -> A | M10: =INDEX('Draft Engine'!$X$3:$X$232,$P10) -> RATE-ADJUSTED VETERAN | N10: =INDEX('LIVE SOURCE'!$H$3:$H$232,$P10) -> Elite RB1 and first-round roster anchor with league-winning ceiling. | O10: =INDEX('LIVE SOURCE'!$J$3:$J$232,$P10) -> Touchdown variance, receiving-role changes and backfield competition are the main downside paths. | P10: =MATCH($A10,'Draft Engine'!$Q$3:$Q$232,0) -> 36
A11: =9 -> 9 | B11: =INDEX('Draft Engine'!$A$3:$A$232,$P11) -> WR | C11: =INDEX('Draft Engine'!$F$3:$F$232,$P11) -> 5 | D11: =INDEX('Draft Engine'!$B$3:$B$232,$P11) -> Nico Collins | E11: =INDEX('Draft Engine'!$E$3:$E$232,$P11) -> 91.4925 | F11: =IF($E11>=95,"ELITE",IF($E11>=90,"TIER 1",IF($E11>=85,"TIER 2",IF($E11>=80,"TIER 3",IF($E11>=75,"TIER 4",IF($E11>=70,"TIER 5",IF($E11>=65,"TIER 6","TIER 7"))))))) -> TIER 1 | G11: =INDEX('Draft Engine'!$G$3:$G$232,$P11) -> 314.3 | H11: =INDEX('Draft Engine'!$J$3:$J$232,$P11) -> 75 | I11: =INDEX('Draft Engine'!$N$3:$N$232,$P11) -> 93.820875 | J11: =INDEX('Draft Engine'!$R$3:$R$232,$P11) -> 23.8 | K11: =INDEX('Draft Engine'!$S$3:$S$232,$P11) -> 14.8 | L11: =INDEX('Draft Engine'!$T$3:$T$232,$P11) -> B | M11: =INDEX('Draft Engine'!$X$3:$X$232,$P11) -> HISTORY FALLBACK | N11: =INDEX('LIVE SOURCE'!$H$3:$H$232,$P11) -> Elite WR1 and first-round caliber target with overall WR1 upside. | O11: =INDEX('LIVE SOURCE'!$J$3:$J$232,$P11) -> Target competition, quarterback efficiency and touchdown regression are the main downside paths. | P11: =MATCH($A11,'Draft Engine'!$Q$3:$Q$232,0) -> 94
A12: =10 -> 10 | B12: =INDEX('Draft Engine'!$A$3:$A$232,$P12) -> TE | C12: =INDEX('Draft Engine'!$F$3:$F$232,$P12) -> 1 | D12: =INDEX('Draft Engine'!$B$3:$B$232,$P12) -> Trey McBride | E12: =INDEX('Draft Engine'!$E$3:$E$232,$P12) -> 97.7371 | F12: =IF($E12>=95,"ELITE",IF($E12>=90,"TIER 1",IF($E12>=85,"TIER 2",IF($E12>=80,"TIER 3",IF($E12>=75,"TIER 4",IF($E12>=70,"TIER 5",IF($E12>=65,"TIER 6","TIER 7"))))))) -> ELITE | G12: =INDEX('Draft Engine'!$G$3:$G$232,$P12) -> 242.1 | H12: =INDEX('Draft Engine'!$J$3:$J$232,$P12) -> 62.4 | I12: =INDEX('Draft Engine'!$N$3:$N$232,$P12) -> 93.487405 | J12: =INDEX('Draft Engine'!$R$3:$R$232,$P12) -> 35.7 | K12: =INDEX('Draft Engine'!$S$3:$S$232,$P12) -> 25.7 | L12: =INDEX('Draft Engine'!$T$3:$T$232,$P12) -> A | M12: =INDEX('Draft Engine'!$X$3:$X$232,$P12) -> RATE-ADJUSTED VETERAN | N12: =INDEX('LIVE SOURCE'!$H$3:$H$232,$P12) -> Elite difference-making TE; positional advantage is the expectation. | O12: =INDEX('LIVE SOURCE'!$J$3:$J$232,$P12) -> Route share, target volume and touchdown volatility are the main swing factors. | P12: =MATCH($A12,'Draft Engine'!$Q$3:$Q$232,0) -> 159
A13: =11 -> 11 | B13: =INDEX('Draft Engine'!$A$3:$A$232,$P13) -> RB | C13: =INDEX('Draft Engine'!$F$3:$F$232,$P13) -> 5 | D13: =INDEX('Draft Engine'!$B$3:$B$232,$P13) -> Jeremiyah Love | E13: =INDEX('Draft Engine'!$E$3:$E$232,$P13) -> 90.8659 | F13: =IF($E13>=95,"ELITE",IF($E13>=90,"TIER 1",IF($E13>=85,"TIER 2",IF($E13>=80,"TIER 3",IF($E13>=75,"TIER 4",IF($E13>=70,"TIER 5",IF($E13>=65,"TIER 6","TIER 7"))))))) -> TIER 1 | G13: =INDEX('Draft Engine'!$G$3:$G$232,$P13) -> 311.6 | H13: =INDEX('Draft Engine'!$J$3:$J$232,$P13) -> 72.6 | I13: =INDEX('Draft Engine'!$N$3:$N$232,$P13) -> 93.044245 | J13: =INDEX('Draft Engine'!$R$3:$R$232,$P13) -> 26.2 | K13: =INDEX('Draft Engine'!$S$3:$S$232,$P13) -> 15.2 | L13: =INDEX('Draft Engine'!$T$3:$T$232,$P13) -> B | M13: =INDEX('Draft Engine'!$X$3:$X$232,$P13) -> ROOKIE ENGINE | N13: =INDEX('LIVE SOURCE'!$H$3:$H$232,$P13) -> Elite RB1 and first-round roster anchor with league-winning ceiling. | O13: =INDEX('LIVE SOURCE'!$J$3:$J$232,$P13) -> NFL translation and exact weekly role are the main variables; preseason first-team usage can move this rating quickly. | P13: =MATCH($A13,'Draft Engine'!$Q$3:$Q$232,0) -> 37
A14: =12 -> 12 | B14: =INDEX('Draft Engine'!$A$3:$A$232,$P14) -> QB | C14: =INDEX('Draft Engine'!$F$3:$F$232,$P14) -> 1 | D14: =INDEX('Draft Engine'!$B$3:$B$232,$P14) -> Josh Allen | E14: =INDEX('Draft Engine'!$E$3:$E$232,$P14) -> 97.3099 | F14: =IF($E14>=95,"ELITE",IF($E14>=90,"TIER 1",IF($E14>=85,"TIER 2",IF($E14>=80,"TIER 3",IF($E14>=75,"TIER 4",IF($E14>=70,"TIER 5",IF($E14>=65,"TIER 6","TIER 7"))))))) -> ELITE | G14: =INDEX('Draft Engine'!$G$3:$G$232,$P14) -> 407.9 | H14: =INDEX('Draft Engine'!$J$3:$J$232,$P14) -> 56.8 | I14: =INDEX('Draft Engine'!$N$3:$N$232,$P14) -> 90.744445 | J14: =INDEX('Draft Engine'!$R$3:$R$232,$P14) -> 26.6 | K14: =INDEX('Draft Engine'!$S$3:$S$232,$P14) -> 14.6 | L14: =INDEX('Draft Engine'!$T$3:$T$232,$P14) -> A | M14: =INDEX('Draft Engine'!$X$3:$X$232,$P14) -> RATE-ADJUSTED VETERAN | N14: =INDEX('LIVE SOURCE'!$H$3:$H$232,$P14) -> Elite QB1; weekly top-5 expectation with overall QB1 upside. | O14: =INDEX('LIVE SOURCE'!$J$3:$J$232,$P14) -> Passing-TD efficiency, rushing volume and supporting-cast health are the main swing factors. | P14: =MATCH($A14,'Draft Engine'!$Q$3:$Q$232,0) -> 1
A15: =13 -> 13 | B15: =INDEX('Draft Engine'!$A$3:$A$232,$P15) -> WR | C15: =INDEX('Draft Engine'!$F$3:$F$232,$P15) -> 6 | D15: =INDEX('Draft Engine'!$B$3:$B$232,$P15) -> Chris Olave | E15: =INDEX('Draft Engine'!$E$3:$E$232,$P15) -> 88.9075 | F15: =IF($E15>=95,"ELITE",IF($E15>=90,"TIER 1",IF($E15>=85,"TIER 2",IF($E15>=80,"TIER 3",IF($E15>=75,"TIER 4",IF($E15>=70,"TIER 5",IF($E15>=65,"TIER 6","TIER 7"))))))) -> TIER 2 | G15: =INDEX('Draft Engine'!$G$3:$G$232,$P15) -> 303.4 | H15: =INDEX('Draft Engine'!$J$3:$J$232,$P15) -> 64.1 | I15: =INDEX('Draft Engine'!$N$3:$N$232,$P15) -> 90.270458 | J15: =INDEX('Draft Engine'!$R$3:$R$232,$P15) -> 20.4 | K15: =INDEX('Draft Engine'!$S$3:$S$232,$P15) -> 7.4 | L15: =INDEX('Draft Engine'!$T$3:$T$232,$P15) -> B | M15: =INDEX('Draft Engine'!$X$3:$X$232,$P15) -> HISTORY FALLBACK | N15: =INDEX('LIVE SOURCE'!$H$3:$H$232,$P15) -> Strong WR1; bankable weekly starter with spike-week ceiling. | O15: =INDEX('LIVE SOURCE'!$J$3:$J$232,$P15) -> Target competition, quarterback efficiency and touchdown regression are the main downside paths. | P15: =MATCH($A15,'Draft Engine'!$Q$3:$Q$232,0) -> 96
A16: =14 -> 14 | B16: =INDEX('Draft Engine'!$A$3:$A$232,$P16) -> RB | C16: =INDEX('Draft Engine'!$F$3:$F$232,$P16) -> 6 | D16: =INDEX('Draft Engine'!$B$3:$B$232,$P16) -> Omarion Hampton | E16: =INDEX('Draft Engine'!$E$3:$E$232,$P16) -> 88.6421 | F16: =IF($E16>=95,"ELITE",IF($E16>=90,"TIER 1",IF($E16>=85,"TIER 2",IF($E16>=80,"TIER 3",IF($E16>=75,"TIER 4",IF($E16>=70,"TIER 5",IF($E16>=65,"TIER 6","TIER 7"))))))) -> TIER 2 | G16: =INDEX('Draft Engine'!$G$3:$G$232,$P16) -> 302.3 | H16: =INDEX('Draft Engine'!$J$3:$J$232,$P16) -> 63.3 | I16: =INDEX('Draft Engine'!$N$3:$N$232,$P16) -> 90.147155 | J16: =INDEX('Draft Engine'!$R$3:$R$232,$P16) -> 19.6 | K16: =INDEX('Draft Engine'!$S$3:$S$232,$P16) -> 5.6 | L16: =INDEX('Draft Engine'!$T$3:$T$232,$P16) -> B | M16: =INDEX('Draft Engine'!$X$3:$X$232,$P16) -> RATE-ADJUSTED VETERAN | N16: =INDEX('LIVE SOURCE'!$H$3:$H$232,$P16) -> Strong RB1; weekly top-12 expectation with multi-touchdown ceiling. | O16: =INDEX('LIVE SOURCE'!$J$3:$J$232,$P16) -> Availability/sample risk is elevated after only 9 games; talent is not being punished as heavily as durability. | P16: =MATCH($A16,'Draft Engine'!$Q$3:$Q$232,0) -> 38
A17: =15 -> 15 | B17: =INDEX('Draft Engine'!$A$3:$A$232,$P17) -> TE | C17: =INDEX('Draft Engine'!$F$3:$F$232,$P17) -> 2 | D17: =INDEX('Draft Engine'!$B$3:$B$232,$P17) -> Brock Bowers | E17: =INDEX('Draft Engine'!$E$3:$E$232,$P17) -> 94.8846 | F17: =IF($E17>=95,"ELITE",IF($E17>=90,"TIER 1",IF($E17>=85,"TIER 2",IF($E17>=80,"TIER 3",IF($E17>=75,"TIER 4",IF($E17>=70,"TIER 5",IF($E17>=65,"TIER 6","TIER 7"))))))) -> TIER 1 | G17: =INDEX('Draft Engine'!$G$3:$G$232,$P17) -> 232.1 | H17: =INDEX('Draft Engine'!$J$3:$J$232,$P17) -> 52.4 | I17: =INDEX('Draft Engine'!$N$3:$N$232,$P17) -> 89.426222 | J17: =INDEX('Draft Engine'!$R$3:$R$232,$P17) -> 41.1 | K17: =INDEX('Draft Engine'!$S$3:$S$232,$P17) -> 26.1 | L17: =INDEX('Draft Engine'!$T$3:$T$232,$P17) -> A | M17: =INDEX('Draft Engine'!$X$3:$X$232,$P17) -> RATE-ADJUSTED VETERAN | N17: =INDEX('LIVE SOURCE'!$H$3:$H$232,$P17) -> Elite difference-making TE; positional advantage is the expectation. | O17: =INDEX('LIVE SOURCE'!$J$3:$J$232,$P17) -> Route share, target volume and touchdown volatility are the main swing factors. | P17: =MATCH($A17,'Draft Engine'!$Q$3:$Q$232,0) -> 160
A18: =16 -> 16 | B18: =INDEX('Draft Engine'!$A$3:$A$232,$P18) -> RB | C18: =INDEX('Draft Engine'!$F$3:$F$232,$P18) -> 7 | D18: =INDEX('Draft Engine'!$B$3:$B$232,$P18) -> De'Von Achane | E18: =INDEX('Draft Engine'!$E$3:$E$232,$P18) -> 87.944 | F18: =IF($E18>=95,"ELITE",IF($E18>=90,"TIER 1",IF($E18>=85,"TIER 2",IF($E18>=80,"TIER 3",IF($E18>=75,"TIER 4",IF($E18>=70,"TIER 5",IF($E18>=65,"TIER 6","TIER 7"))))))) -> TIER 2 | G18: =INDEX('Draft Engine'!$G$3:$G$232,$P18) -> 299.4 | H18: =INDEX('Draft Engine'!$J$3:$J$232,$P18) -> 60.4 | I18: =INDEX('Draft Engine'!$N$3:$N$232,$P18) -> 89.2412 | J18: =INDEX('Draft Engine'!$R$3:$R$232,$P18) -> 10.1 | K18: =INDEX('Draft Engine'!$S$3:$S$232,$P18) -> -5.9 | L18: =INDEX('Draft Engine'!$T$3:$T$232,$P18) -> A | M18: =INDEX('Draft Engine'!$X$3:$X$232,$P18) -> RATE-ADJUSTED VETERAN | N18: =INDEX('LIVE SOURCE'!$H$3:$H$232,$P18) -> Strong RB1; weekly top-12 expectation with multi-touchdown ceiling. | O18: =INDEX('LIVE SOURCE'!$J$3:$J$232,$P18) -> Touchdown variance, receiving-role changes and backfield competition are the main downside paths. | P18: =MATCH($A18,'Draft Engine'!$Q$3:$Q$232,0) -> 39
A19: =17 -> 17 | B19: =INDEX('Draft Engine'!$A$3:$A$232,$P19) -> RB | C19: =INDEX('Draft Engine'!$F$3:$F$232,$P19) -> 8 | D19: =INDEX('Draft Engine'!$B$3:$B$232,$P19) -> Kenneth Walker III | E19: =INDEX('Draft Engine'!$E$3:$E$232,$P19) -> 87.2926 | F19: =IF($E19>=95,"ELITE",IF($E19>=90,"TIER 1",IF($E19>=85,"TIER 2",IF($E19>=80,"TIER 3",IF($E19>=75,"TIER 4",IF($E19>=70,"TIER 5",IF($E19>=65,"TIER 6","TIER 7"))))))) -> TIER 2 | G19: =INDEX('Draft Engine'!$G$3:$G$232,$P19) -> 296.6 | H19: =INDEX('Draft Engine'!$J$3:$J$232,$P19) -> 57.6 | I19: =INDEX('Draft Engine'!$N$3:$N$232,$P19) -> 88.113305 | J19: =INDEX('Draft Engine'!$R$3:$R$232,$P19) -> 26.2 | K19: =INDEX('Draft Engine'!$S$3:$S$232,$P19) -> 9.2 | L19: =INDEX('Draft Engine'!$T$3:$T$232,$P19) -> A | M19: =INDEX('Draft Engine'!$X$3:$X$232,$P19) -> RATE-ADJUSTED VETERAN | N19: =INDEX('LIVE SOURCE'!$H$3:$H$232,$P19) -> Strong RB1; weekly top-12 expectation with multi-touchdown ceiling. | O19: =INDEX('LIVE SOURCE'!$J$3:$J$232,$P19) -> Touchdown variance, receiving-role changes and backfield competition are the main downside paths. | P19: =MATCH($A19,'Draft Engine'!$Q$3:$Q$232,0) -> 40
A20: =18 -> 18 | B20: =INDEX('Draft Engine'!$A$3:$A$232,$P20) -> WR | C20: =INDEX('Draft Engine'!$F$3:$F$232,$P20) -> 7 | D20: =INDEX('Draft Engine'!$B$3:$B$232,$P20) -> Drake London | E20: =INDEX('Draft Engine'!$E$3:$E$232,$P20) -> 87.5106 | F20: =IF($E20>=95,"ELITE",IF($E20>=90,"TIER 1",IF($E20>=85,"TIER 2",IF($E20>=80,"TIER 3",IF($E20>=75,"TIER 4",IF($E20>=70,"TIER 5",IF($E20>=65,"TIER 6","TIER 7"))))))) -> TIER 2 | G20: =INDEX('Draft Engine'!$G$3:$G$232,$P20) -> 297.5 | H20: =INDEX('Draft Engine'!$J$3:$J$232,$P20) -> 58.2 | I20: =INDEX('Draft Engine'!$N$3:$N$232,$P20) -> 88.10683 | J20: =INDEX('Draft Engine'!$R$3:$R$232,$P20) -> 10.2 | K20: =INDEX('Draft Engine'!$S$3:$S$232,$P20) -> -7.8 | L20: =INDEX('Draft Engine'!$T$3:$T$232,$P20) -> A | M20: =INDEX('Draft Engine'!$X$3:$X$232,$P20) -> HISTORY FALLBACK | N20: =INDEX('LIVE SOURCE'!$H$3:$H$232,$P20) -> Strong WR1; bankable weekly starter with spike-week ceiling. | O20: =INDEX('LIVE SOURCE'!$J$3:$J$232,$P20) -> Target competition, quarterback efficiency and touchdown regression are the main downside paths. | P20: =MATCH($A20,'Draft Engine'!$Q$3:$Q$232,0) -> 93
A21: =19 -> 19 | B21: =INDEX('Draft Engine'!$A$3:$A$232,$P21) -> WR | C21: =INDEX('Draft Engine'!$F$3:$F$232,$P21) -> 8 | D21: =INDEX('Draft Engine'!$B$3:$B$232,$P21) -> DeVonta Smith | E21: =INDEX('Draft Engine'!$E$3:$E$232,$P21) -> 87.4875 | F21: =IF($E21>=95,"ELITE",IF($E21>=90,"TIER 1",IF($E21>=85,"TIER 2",IF($E21>=80,"TIER 3",IF($E21>=75,"TIER 4",IF($E21>=70,"TIER 5",IF($E21>=65,"TIER 6","TIER 7"))))))) -> TIER 2 | G21: =INDEX('Draft Engine'!$G$3:$G$232,$P21) -> 297.4 | H21: =INDEX('Draft Engine'!$J$3:$J$232,$P21) -> 58.1 | I21: =INDEX('Draft Engine'!$N$3:$N$232,$P21) -> 87.742792 | J21: =INDEX('Draft Engine'!$R$3:$R$232,$P21) -> 29.5 | K21: =INDEX('Draft Engine'!$S$3:$S$232,$P21) -> 10.5 | L21: =INDEX('Draft Engine'!$T$3:$T$232,$P21) -> B | M21: =INDEX('Draft Engine'!$X$3:$X$232,$P21) -> HISTORY FALLBACK | N21: =INDEX('LIVE SOURCE'!$H$3:$H$232,$P21) -> Strong WR1; bankable weekly starter with spike-week ceiling. | O21: =INDEX('LIVE SOURCE'!$J$3:$J$232,$P21) -> Target competition, quarterback efficiency and touchdown regression are the main downside paths. | P21: =MATCH($A21,'Draft Engine'!$Q$3:$Q$232,0) -> 100
A22: =20 -> 20 | B22: =INDEX('Draft Engine'!$A$3:$A$232,$P22) -> RB | C22: =INDEX('Draft Engine'!$F$3:$F$232,$P22) -> 9 | D22: =INDEX('Draft Engine'!$B$3:$B$232,$P22) -> James Cook III | E22: =INDEX('Draft Engine'!$E$3:$E$232,$P22) -> 87.058 | F22: =IF($E22>=95,"ELITE",IF($E22>=90,"TIER 1",IF($E22>=85,"TIER 2",IF($E22>=80,"TIER 3",IF($E22>=75,"TIER 4",IF($E22>=70,"TIER 5",IF($E22>=65,"TIER 6","TIER 7"))))))) -> TIER 2 | G22: =INDEX('Draft Engine'!$G$3:$G$232,$P22) -> 295.6 | H22: =INDEX('Draft Engine'!$J$3:$J$232,$P22) -> 56.6 | I22: =INDEX('Draft Engine'!$N$3:$N$232,$P22) -> 87.4449 | J22: =INDEX('Draft Engine'!$R$3:$R$232,$P22) -> 14.9 | K22: =INDEX('Draft Engine'!$S$3:$S$232,$P22) -> -5.1 | L22: =INDEX('Draft Engine'!$T$3:$T$232,$P22) -> A | M22: =INDEX('Draft Engine'!$X$3:$X$232,$P22) -> RATE-ADJUSTED VETERAN | N22: =INDEX('LIVE SOURCE'!$H$3:$H$232,$P22) -> Strong RB1; weekly top-12 expectation with multi-touchdown ceiling. | O22: =INDEX('LIVE SOURCE'!$J$3:$J$232,$P22) -> Touchdown variance, receiving-role changes and backfield competition are the main downside paths. | P22: =MATCH($A22,'Draft Engine'!$Q$3:$Q$232,0) -> 41
A23: =21 -> 21 | B23: =INDEX('Draft Engine'!$A$3:$A$232,$P23) -> WR | C23: =INDEX('Draft Engine'!$F$3:$F$232,$P23) -> 9 | D23: =INDEX('Draft Engine'!$B$3:$B$232,$P23) -> Zay Flowers | E23: =INDEX('Draft Engine'!$E$3:$E$232,$P23) -> 86.57 | F23: =IF($E23>=95,"ELITE",IF($E23>=90,"TIER 1",IF($E23>=85,"TIER 2",IF($E23>=80,"TIER 3",IF($E23>=75,"TIER 4",IF($E23>=70,"TIER 5",IF($E23>=65,"TIER 6","TIER 7"))))))) -> TIER 2 | G23: =INDEX('Draft Engine'!$G$3:$G$232,$P23) -> 293.6 | H23: =INDEX('Draft Engine'!$J$3:$J$232,$P23) -> 54.3 | I23: =INDEX('Draft Engine'!$N$3:$N$232,$P23) -> 86.220833 | J23: =INDEX('Draft Engine'!$R$3:$R$232,$P23) -> 26.4 | K23: =INDEX('Draft Engine'!$S$3:$S$232,$P23) -> 5.4 | L23: =INDEX('Draft Engine'!$T$3:$T$232,$P23) -> B | M23: =INDEX('Draft Engine'!$X$3:$X$232,$P23) -> HISTORY FALLBACK | N23: =INDEX('LIVE SOURCE'!$H$3:$H$232,$P23) -> Strong WR1; bankable weekly starter with spike-week ceiling. | O23: =INDEX('LIVE SOURCE'!$J$3:$J$232,$P23) -> Target competition, quarterback efficiency and touchdown regression are the main downside paths. | P23: =MATCH($A23,'Draft Engine'!$Q$3:$Q$232,0) -> 101
A24: =22 -> 22 | B24: =INDEX('Draft Engine'!$A$3:$A$232,$P24) -> RB | C24: =INDEX('Draft Engine'!$F$3:$F$232,$P24) -> 10 | D24: =INDEX('Draft Engine'!$B$3:$B$232,$P24) -> Kyren Williams | E24: =INDEX('Draft Engine'!$E$3:$E$232,$P24) -> 85.9486 | F24: =IF($E24>=95,"ELITE",IF($E24>=90,"TIER 1",IF($E24>=85,"TIER 2",IF($E24>=80,"TIER 3",IF($E24>=75,"TIER 4",IF($E24>=70,"TIER 5",IF($E24>=65,"TIER 6","TIER 7"))))))) -> TIER 2 | G24: =INDEX('Draft Engine'!$G$3:$G$232,$P24) -> 291 | H24: =INDEX('Draft Engine'!$J$3:$J$232,$P24) -> 52 | I24: =INDEX('Draft Engine'!$N$3:$N$232,$P24) -> 85.647355 | J24: =INDEX('Draft Engine'!$R$3:$R$232,$P24) -> 33.1 | K24: =INDEX('Draft Engine'!$S$3:$S$232,$P24) -> 11.1 | L24: =INDEX('Draft Engine'!$T$3:$T$232,$P24) -> A | M24: =INDEX('Draft Engine'!$X$3:$X$232,$P24) -> RATE-ADJUSTED VETERAN | N24: =INDEX('LIVE SOURCE'!$H$3:$H$232,$P24) -> Strong RB1; weekly top-12 expectation with multi-touchdown ceiling. | O24: =INDEX('LIVE SOURCE'!$J$3:$J$232,$P24) -> Touchdown variance, receiving-role changes and backfield competition are the main downside paths. | P24: =MATCH($A24,'Draft Engine'!$Q$3:$Q$232,0) -> 42
A25: =23 -> 23 | B25: =INDEX('Draft Engine'!$A$3:$A$232,$P25) -> WR | C25: =INDEX('Draft Engine'!$F$3:$F$232,$P25) -> 10 | D25: =INDEX('Draft Engine'!$B$3:$B$232,$P25) -> Garrett Wilson | E25: =INDEX('Draft Engine'!$E$3:$E$232,$P25) -> 86.155 | F25: =IF($E25>=95,"ELITE",IF($E25>=90,"TIER 1",IF($E25>=85,"TIER 2",IF($E25>=80,"TIER 3",IF($E25>=75,"TIER 4",IF($E25>=70,"TIER 5",IF($E25>=65,"TIER 6","TIER 7"))))))) -> TIER 2 | G25: =INDEX('Draft Engine'!$G$3:$G$232,$P25) -> 291.9 | H25: =INDEX('Draft Engine'!$J$3:$J$232,$P25) -> 52.6 | I25: =INDEX('Draft Engine'!$N$3:$N$232,$P25) -> 85.35325 | J25: =INDEX('Draft Engine'!$R$3:$R$232,$P25) -> 29 | K25: =INDEX('Draft Engine'!$S$3:$S$232,$P25) -> 6 | L25: =INDEX('Draft Engine'!$T$3:$T$232,$P25) -> B | M25: =INDEX('Draft Engine'!$X$3:$X$232,$P25) -> HISTORY FALLBACK | N25: =INDEX('LIVE SOURCE'!$H$3:$H$232,$P25) -> Strong WR1; bankable weekly starter with spike-week ceiling. | O25: =INDEX('LIVE SOURCE'!$J$3:$J$232,$P25) -> Availability/sample risk is elevated after only 7 games; talent is not being punished as heavily as durability. | P25: =MATCH($A25,'Draft Engine'!$Q$3:$Q$232,0) -> 99
A26: =24 -> 24 | B26: =INDEX('Draft Engine'!$A$3:$A$232,$P26) -> RB | C26: =INDEX('Draft Engine'!$F$3:$F$232,$P26) -> 11 | D26: =INDEX('Draft Engine'!$B$3:$B$232,$P26) -> Breece Hall | E26: =INDEX('Draft Engine'!$E$3:$E$232,$P26) -> 85.8952 | F26: =IF($E26>=95,"ELITE",IF($E26>=90,"TIER 1",IF($E26>=85,"TIER 2",IF($E26>=80,"TIER 3",IF($E26>=75,"TIER 4",IF($E26>=70,"TIER 5",IF($E26>=65,"TIER 6","TIER 7"))))))) -> TIER 2 | G26: =INDEX('Draft Engine'!$G$3:$G$232,$P26) -> 290.8 | H26: =INDEX('Draft Engine'!$J$3:$J$232,$P26) -> 51.8 | I26: =INDEX('Draft Engine'!$N$3:$N$232,$P26) -> 85.22261 | J26: =INDEX('Draft Engine'!$R$3:$R$232,$P26) -> 27 | K26: =INDEX('Draft Engine'!$S$3:$S$232,$P26) -> 3 | L26: =INDEX('Draft Engine'!$T$3:$T$232,$P26) -> A | M26: =INDEX('Draft Engine'!$X$3:$X$232,$P26) -> RATE-ADJUSTED VETERAN | N26: =INDEX('LIVE SOURCE'!$H$3:$H$232,$P26) -> Strong RB1; weekly top-12 expectation with multi-touchdown ceiling. | O26: =INDEX('LIVE SOURCE'!$J$3:$J$232,$P26) -> Touchdown variance, receiving-role changes and backfield competition are the main downside paths. | P26: =MATCH($A26,'Draft Engine'!$Q$3:$Q$232,0) -> 43
A27: =25 -> 25 | B27: =INDEX('Draft Engine'!$A$3:$A$232,$P27) -> RB | C27: =INDEX('Draft Engine'!$F$3:$F$232,$P27) -> 12 | D27: =INDEX('Draft Engine'!$B$3:$B$232,$P27) -> Ashton Jeanty | E27: =INDEX('Draft Engine'!$E$3:$E$232,$P27) -> 85.8433 | F27: =IF($E27>=95,"ELITE",IF($E27>=90,"TIER 1",IF($E27>=85,"TIER 2",IF($E27>=80,"TIER 3",IF($E27>=75,"TIER 4",IF($E27>=70,"TIER 5",IF($E27>=65,"TIER 6","TIER 7"))))))) -> TIER 2 | G27: =INDEX('Draft Engine'!$G$3:$G$232,$P27) -> 290.5 | H27: =INDEX('Draft Engine'!$J$3:$J$232,$P27) -> 51.5 | I27: =INDEX('Draft Engine'!$N$3:$N$232,$P27) -> 84.78069 | J27: =INDEX('Draft Engine'!$R$3:$R$232,$P27) -> 13.8 | K27: =INDEX('Draft Engine'!$S$3:$S$232,$P27) -> -11.2 | L27: =INDEX('Draft Engine'!$T$3:$T$232,$P27) -> A | M27: =INDEX('Draft Engine'!$X$3:$X$232,$P27) -> RATE-ADJUSTED VETERAN | N27: =INDEX('LIVE SOURCE'!$H$3:$H$232,$P27) -> Strong RB1; weekly top-12 expectation with multi-touchdown ceiling. | O27: =INDEX('LIVE SOURCE'!$J$3:$J$232,$P27) -> Price is the biggest risk: the market currently asks you to draft him earlier than the model prefers. | P27: =MATCH($A27,'Draft Engine'!$Q$3:$Q$232,0) -> 44
A28: =26 -> 26 | B28: =INDEX('Draft Engine'!$A$3:$A$232,$P28) -> WR | C28: =INDEX('Draft Engine'!$F$3:$F$232,$P28) -> 11 | D28: =INDEX('Draft Engine'!$B$3:$B$232,$P28) -> CeeDee Lamb | E28: =INDEX('Draft Engine'!$E$3:$E$232,$P28) -> 85.7426 | F28: =IF($E28>=95,"ELITE",IF($E28>=90,"TIER 1",IF($E28>=85,"TIER 2",IF($E28>=80,"TIER 3",IF($E28>=75,"TIER 4",IF($E28>=70,"TIER 5",IF($E28>=65,"TIER 6","TIER 7"))))))) -> TIER 2 | G28: =INDEX('Draft Engine'!$G$3:$G$232,$P28) -> 290.1 | H28: =INDEX('Draft Engine'!$J$3:$J$232,$P28) -> 50.8 | I28: =INDEX('Draft Engine'!$N$3:$N$232,$P28) -> 84.469097 | J28: =INDEX('Draft Engine'!$R$3:$R$232,$P28) -> 11.2 | K28: =INDEX('Draft Engine'!$S$3:$S$232,$P28) -> -14.8 | L28: =INDEX('Draft Engine'!$T$3:$T$232,$P28) -> A | M28: =INDEX('Draft Engine'!$X$3:$X$232,$P28) -> HISTORY FALLBACK | N28: =INDEX('LIVE SOURCE'!$H$3:$H$232,$P28) -> Strong WR1; bankable weekly starter with spike-week ceiling. | O28: =INDEX('LIVE SOURCE'!$J$3:$J$232,$P28) -> Price is the biggest risk: the market currently asks you to draft him earlier than the model prefers. | P28: =MATCH($A28,'Draft Engine'!$Q$3:$Q$232,0) -> 90
A29: =27 -> 27 | B29: =INDEX('Draft Engine'!$A$3:$A$232,$P29) -> RB | C29: =INDEX('Draft Engine'!$F$3:$F$232,$P29) -> 13 | D29: =INDEX('Draft Engine'!$B$3:$B$232,$P29) -> Derrick Henry | E29: =INDEX('Draft Engine'!$E$3:$E$232,$P29) -> 85.6674 | F29: =IF($E29>=95,"ELITE",IF($E29>=90,"TIER 1",IF($E29>=85,"TIER 2",IF($E29>=80,"TIER 3",IF($E29>=75,"TIER 4",IF($E29>=70,"TIER 5",IF($E29>=65,"TIER 6","TIER 7"))))))) -> TIER 2 | G29: =INDEX('Draft Engine'!$G$3:$G$232,$P29) -> 289.8 | H29: =INDEX('Draft Engine'!$J$3:$J$232,$P29) -> 50.8 | I29: =INDEX('Draft Engine'!$N$3:$N$232,$P29) -> 84.19857 | J29: =INDEX('Draft Engine'!$R$3:$R$232,$P29) -> 15.4 | K29: =INDEX('Draft Engine'!$S$3:$S$232,$P29) -> -11.6 | L29: =INDEX('Draft Engine'!$T$3:$T$232,$P29) -> A | M29: =INDEX('Draft Engine'!$X$3:$X$232,$P29) -> RATE-ADJUSTED VETERAN | N29: =INDEX('LIVE SOURCE'!$H$3:$H$232,$P29) -> RB2 with RB1 weeks; should be a regular starter. | O29: =INDEX('LIVE SOURCE'!$J$3:$J$232,$P29) -> Touchdown variance, receiving-role changes and backfield competition are the main downside paths. | P29: =MATCH($A29,'Draft Engine'!$Q$3:$Q$232,0) -> 45
A30: =28 -> 28 | B30: =INDEX('Draft Engine'!$A$3:$A$232,$P30) -> WR | C30: =INDEX('Draft Engine'!$F$3:$F$232,$P30) -> 12 | D30: =INDEX('Draft Engine'!$B$3:$B$232,$P30) -> Tetairoa McMillan | E30: =INDEX('Draft Engine'!$E$3:$E$232,$P30) -> 85.74 | F30: =IF($E30>=95,"ELITE",IF($E30>=90,"TIER 1",IF($E30>=85,"TIER 2",IF($E30>=80,"TIER 3",IF($E30>=75,"TIER 4",IF($E30>=70,"TIER 5",IF($E30>=65,"TIER 6","TIER 7"))))))) -> TIER 2 | G30: =INDEX('Draft Engine'!$G$3:$G$232,$P30) -> 290.1 | H30: =INDEX('Draft Engine'!$J$3:$J$232,$P30) -> 50.8 | I30: =INDEX('Draft Engine'!$N$3:$N$232,$P30) -> 84.134333 | J30: =INDEX('Draft Engine'!$R$3:$R$232,$P30) -> 34.4 | K30: =INDEX('Draft Engine'!$S$3:$S$232,$P30) -> 6.4 | L30: =INDEX('Draft Engine'!$T$3:$T$232,$P30) -> B | M30: =INDEX('Draft Engine'!$X$3:$X$232,$P30) -> HISTORY FALLBACK | N30: =INDEX('LIVE SOURCE'!$H$3:$H$232,$P30) -> Strong WR1; bankable weekly starter with spike-week ceiling. | O30: =INDEX('LIVE SOURCE'!$J$3:$J$232,$P30) -> Target competition, quarterback efficiency and touchdown regression are the main downside paths. | P30: =MATCH($A30,'Draft Engine'!$Q$3:$Q$232,0) -> 97
A31: =29 -> 29 | B31: =INDEX('Draft Engine'!$A$3:$A$232,$P31) -> RB | C31: =INDEX('Draft Engine'!$F$3:$F$232,$P31) -> 14 | D31: =INDEX('Draft Engine'!$B$3:$B$232,$P31) -> Chase Brown | E31: =INDEX('Draft Engine'!$E$3:$E$232,$P31) -> 85.6644 | F31: =IF($E31>=95,"ELITE",IF($E31>=90,"TIER 1",IF($E31>=85,"TIER 2",IF($E31>=80,"TIER 3",IF($E31>=75,"TIER 4",IF($E31>=70,"TIER 5",IF($E31>=65,"TIER 6","TIER 7"))))))) -> TIER 2 | G31: =INDEX('Draft Engine'!$G$3:$G$232,$P31) -> 289.8 | H31: =INDEX('Draft Engine'!$J$3:$J$232,$P31) -> 50.8 | I31: =INDEX('Draft Engine'!$N$3:$N$232,$P31) -> 83.837545 | J31: =INDEX('Draft Engine'!$R$3:$R$232,$P31) -> 12.1 | K31: =INDEX('Draft Engine'!$S$3:$S$232,$P31) -> -16.9 | L31: =INDEX('Draft Engine'!$T$3:$T$232,$P31) -> A | M31: =INDEX('Draft Engine'!$X$3:$X$232,$P31) -> RATE-ADJUSTED VETERAN | N31: =INDEX('LIVE SOURCE'!$H$3:$H$232,$P31) -> RB2 with RB1 weeks; should be a regular starter. | O31: =INDEX('LIVE SOURCE'!$J$3:$J$232,$P31) -> Touchdown variance, receiving-role changes and backfield competition are the main downside paths. | P31: =MATCH($A31,'Draft Engine'!$Q$3:$Q$232,0) -> 46
A32: =30 -> 30 | B32: =INDEX('Draft Engine'!$A$3:$A$232,$P32) -> QB | C32: =INDEX('Draft Engine'!$F$3:$F$232,$P32) -> 2 | D32: =INDEX('Draft Engine'!$B$3:$B$232,$P32) -> Caleb Williams | E32: =INDEX('Draft Engine'!$E$3:$E$232,$P32) -> 92.1927 | F32: =IF($E32>=95,"ELITE",IF($E32>=90,"TIER 1",IF($E32>=85,"TIER 2",IF($E32>=80,"TIER 3",IF($E32>=75,"TIER 4",IF($E32>=70,"TIER 5",IF($E32>=65,"TIER 6","TIER 7"))))))) -> TIER 1 | G32: =INDEX('Draft Engine'!$G$3:$G$232,$P32) -> 384.9 | H32: =INDEX('Draft Engine'!$J$3:$J$232,$P32) -> 33.8 | I32: =INDEX('Draft Engine'!$N$3:$N$232,$P32) -> 83.020754 | J32: =INDEX('Draft Engine'!$R$3:$R$232,$P32) -> 107.5 | K32: =INDEX('Draft Engine'!$S$3:$S$232,$P32) -> 77.5 | L32: =INDEX('Draft Engine'!$T$3:$T$232,$P32) -> A | M32: =INDEX('Draft Engine'!$X$3:$X$232,$P32) -> RATE-ADJUSTED VETERAN | N32: =INDEX('LIVE SOURCE'!$H$3:$H$232,$P32) -> Elite QB1; weekly top-5 expectation with overall QB1 upside. | O32: =INDEX('LIVE SOURCE'!$J$3:$J$232,$P32) -> Passing-TD efficiency, rushing volume and supporting-cast health are the main swing factors. | P32: =MATCH($A32,'Draft Engine'!$Q$3:$Q$232,0) -> 2
A33: =31 -> 31 | B33: =INDEX('Draft Engine'!$A$3:$A$232,$P33) -> WR | C33: =INDEX('Draft Engine'!$F$3:$F$232,$P33) -> 13 | D33: =INDEX('Draft Engine'!$B$3:$B$232,$P33) -> Tee Higgins | E33: =INDEX('Draft Engine'!$E$3:$E$232,$P33) -> 84.8225 | F33: =IF($E33>=95,"ELITE",IF($E33>=90,"TIER 1",IF($E33>=85,"TIER 2",IF($E33>=80,"TIER 3",IF($E33>=75,"TIER 4",IF($E33>=70,"TIER 5",IF($E33>=65,"TIER 6","TIER 7"))))))) -> TIER 3 | G33: =INDEX('Draft Engine'!$G$3:$G$232,$P33) -> 286.3 | H33: =INDEX('Draft Engine'!$J$3:$J$232,$P33) -> 47 | I33: =INDEX('Draft Engine'!$N$3:$N$232,$P33) -> 82.612375 | J33: =INDEX('Draft Engine'!$R$3:$R$232,$P33) -> 38.6 | K33: =INDEX('Draft Engine'!$S$3:$S$232,$P33) -> 7.6 | L33: =INDEX('Draft Engine'!$T$3:$T$232,$P33) -> B | M33: =INDEX('Draft Engine'!$X$3:$X$232,$P33) -> HISTORY FALLBACK | N33: =INDEX('LIVE SOURCE'!$H$3:$H$232,$P33) -> Strong WR2 with top-12 weekly upside. | O33: =INDEX('LIVE SOURCE'!$J$3:$J$232,$P33) -> Target competition, quarterback efficiency and touchdown regression are the main downside paths. | P33: =MATCH($A33,'Draft Engine'!$Q$3:$Q$232,0) -> 98
A34: =32 -> 32 | B34: =INDEX('Draft Engine'!$A$3:$A$232,$P34) -> WR | C34: =INDEX('Draft Engine'!$F$3:$F$232,$P34) -> 14 | D34: =INDEX('Draft Engine'!$B$3:$B$232,$P34) -> Justin Jefferson | E34: =INDEX('Draft Engine'!$E$3:$E$232,$P34) -> 84.7936 | F34: =IF($E34>=95,"ELITE",IF($E34>=90,"TIER 1",IF($E34>=85,"TIER 2",IF($E34>=80,"TIER 3",IF($E34>=75,"TIER 4",IF($E34>=70,"TIER 5",IF($E34>=65,"TIER 6","TIER 7"))))))) -> TIER 3 | G34: =INDEX('Draft Engine'!$G$3:$G$232,$P34) -> 286.1 | H34: =INDEX('Draft Engine'!$J$3:$J$232,$P34) -> 46.8 | I34: =INDEX('Draft Engine'!$N$3:$N$232,$P34) -> 82.227147 | J34: =INDEX('Draft Engine'!$R$3:$R$232,$P34) -> 14.6 | K34: =INDEX('Draft Engine'!$S$3:$S$232,$P34) -> -17.4 | L34: =INDEX('Draft Engine'!$T$3:$T$232,$P34) -> A | M34: =INDEX('Draft Engine'!$X$3:$X$232,$P34) -> HISTORY FALLBACK | N34: =INDEX('LIVE SOURCE'!$H$3:$H$232,$P34) -> Strong WR2 with top-12 weekly upside. | O34: =INDEX('LIVE SOURCE'!$J$3:$J$232,$P34) -> Price is the biggest risk: the market currently asks you to draft him earlier than the model prefers. | P34: =MATCH($A34,'Draft Engine'!$Q$3:$Q$232,0) -> 91
A35: =33 -> 33 | B35: =INDEX('Draft Engine'!$A$3:$A$232,$P35) -> RB | C35: =INDEX('Draft Engine'!$F$3:$F$232,$P35) -> 15 | D35: =INDEX('Draft Engine'!$B$3:$B$232,$P35) -> Josh Jacobs | E35: =INDEX('Draft Engine'!$E$3:$E$232,$P35) -> 84.4264 | F35: =IF($E35>=95,"ELITE",IF($E35>=90,"TIER 1",IF($E35>=85,"TIER 2",IF($E35>=80,"TIER 3",IF($E35>=75,"TIER 4",IF($E35>=70,"TIER 5",IF($E35>=65,"TIER 6","TIER 7"))))))) -> TIER 3 | G35: =INDEX('Draft Engine'!$G$3:$G$232,$P35) -> 284.6 | H35: =INDEX('Draft Engine'!$J$3:$J$232,$P35) -> 45.6 | I35: =INDEX('Draft Engine'!$N$3:$N$232,$P35) -> 81.86127 | J35: =INDEX('Draft Engine'!$R$3:$R$232,$P35) -> 24.2 | K35: =INDEX('Draft Engine'!$S$3:$S$232,$P35) -> -8.8 | L35: =INDEX('Draft Engine'!$T$3:$T$232,$P35) -> A | M35: =INDEX('Draft Engine'!$X$3:$X$232,$P35) -> RATE-ADJUSTED VETERAN | N35: =INDEX('LIVE SOURCE'!$H$3:$H$232,$P35) -> RB2 with RB1 weeks; should be a regular starter. | O35: =INDEX('LIVE SOURCE'!$J$3:$J$232,$P35) -> Touchdown variance, receiving-role changes and backfield competition are the main downside paths. | P35: =MATCH($A35,'Draft Engine'!$Q$3:$Q$232,0) -> 47
A36: =34 -> 34 | B36: =INDEX('Draft Engine'!$A$3:$A$232,$P36) -> TE | C36: =INDEX('Draft Engine'!$F$3:$F$232,$P36) -> 3 | D36: =INDEX('Draft Engine'!$B$3:$B$232,$P36) -> Colston Loveland | E36: =INDEX('Draft Engine'!$E$3:$E$232,$P36) -> 88.7531 | F36: =IF($E36>=95,"ELITE",IF($E36>=90,"TIER 1",IF($E36>=85,"TIER 2",IF($E36>=80,"TIER 3",IF($E36>=75,"TIER 4",IF($E36>=70,"TIER 5",IF($E36>=65,"TIER 6","TIER 7"))))))) -> TIER 2 | G36: =INDEX('Draft Engine'!$G$3:$G$232,$P36) -> 210.6 | H36: =INDEX('Draft Engine'!$J$3:$J$232,$P36) -> 30.9 | I36: =INDEX('Draft Engine'!$N$3:$N$232,$P36) -> 81.49159 | J36: =INDEX('Draft Engine'!$R$3:$R$232,$P36) -> 60.8 | K36: =INDEX('Draft Engine'!$S$3:$S$232,$P36) -> 26.8 | L36: =INDEX('Draft Engine'!$T$3:$T$232,$P36) -> A | M36: =INDEX('Draft Engine'!$X$3:$X$232,$P36) -> RATE-ADJUSTED VETERAN | N36: =INDEX('LIVE SOURCE'!$H$3:$H$232,$P36) -> Elite difference-making TE; positional advantage is the expectation. | O36: =INDEX('LIVE SOURCE'!$J$3:$J$232,$P36) -> Route share, target volume and touchdown volatility are the main swing factors. | P36: =MATCH($A36,'Draft Engine'!$Q$3:$Q$232,0) -> 161
A37: =35 -> 35 | B37: =INDEX('Draft Engine'!$A$3:$A$232,$P37) -> WR | C37: =INDEX('Draft Engine'!$F$3:$F$232,$P37) -> 15 | D37: =INDEX('Draft Engine'!$B$3:$B$232,$P37) -> Rashee Rice | E37: =INDEX('Draft Engine'!$E$3:$E$232,$P37) -> 84.0947 | F37: =IF($E37>=95,"ELITE",IF($E37>=90,"TIER 1",IF($E37>=85,"TIER 2",IF($E37>=80,"TIER 3",IF($E37>=75,"TIER 4",IF($E37>=70,"TIER 5",IF($E37>=65,"TIER 6","TIER 7"))))))) -> TIER 3 | G37: =INDEX('Draft Engine'!$G$3:$G$232,$P37) -> 283.2 | H37: =INDEX('Draft Engine'!$J$3:$J$232,$P37) -> 43.9 | I37: =INDEX('Draft Engine'!$N$3:$N$232,$P37) -> 80.987418 | J37: =INDEX('Draft Engine'!$R$3:$R$232,$P37) -> 11.5 | K37: =INDEX('Draft Engine'!$S$3:$S$232,$P37) -> -23.5 | L37: =INDEX('Draft Engine'!$T$3:$T$232,$P37) -> A | M37: =INDEX('Draft Engine'!$X$3:$X$232,$P37) -> HISTORY FALLBACK | N37: =INDEX('LIVE SOURCE'!$H$3:$H$232,$P37) -> Strong WR2 with top-12 weekly upside. | O37: =INDEX('LIVE SOURCE'!$J$3:$J$232,$P37) -> Availability/sample risk is elevated after only 8 games; talent is not being punished as heavily as durability. | P37: =MATCH($A37,'Draft Engine'!$Q$3:$Q$232,0) -> 95
A38: =36 -> 36 | B38: =INDEX('Draft Engine'!$A$3:$A$232,$P38) -> RB | C38: =INDEX('Draft Engine'!$F$3:$F$232,$P38) -> 16 | D38: =INDEX('Draft Engine'!$B$3:$B$232,$P38) -> Saquon Barkley | E38: =INDEX('Draft Engine'!$E$3:$E$232,$P38) -> 84.034 | F38: =IF($E38>=95,"ELITE",IF($E38>=90,"TIER 1",IF($E38>=85,"TIER 2",IF($E38>=80,"TIER 3",IF($E38>=75,"TIER 4",IF($E38>=70,"TIER 5",IF($E38>=65,"TIER 6","TIER 7"))))))) -> TIER 3 | G38: =INDEX('Draft Engine'!$G$3:$G$232,$P38) -> 282.9 | H38: =INDEX('Draft Engine'!$J$3:$J$232,$P38) -> 43.9 | I38: =INDEX('Draft Engine'!$N$3:$N$232,$P38) -> 80.980075 | J38: =INDEX('Draft Engine'!$R$3:$R$232,$P38) -> 19 | K38: =INDEX('Draft Engine'!$S$3:$S$232,$P38) -> -17 | L38: =INDEX('Draft Engine'!$T$3:$T$232,$P38) -> A | M38: =INDEX('Draft Engine'!$X$3:$X$232,$P38) -> RATE-ADJUSTED VETERAN | N38: =INDEX('LIVE SOURCE'!$H$3:$H$232,$P38) -> RB2 with RB1 weeks; should be a regular starter. | O38: =INDEX('LIVE SOURCE'!$J$3:$J$232,$P38) -> Touchdown variance, receiving-role changes and backfield competition are the main downside paths. | P38: =MATCH($A38,'Draft Engine'!$Q$3:$Q$232,0) -> 48
A39: =37 -> 37 | B39: =INDEX('Draft Engine'!$A$3:$A$232,$P39) -> QB | C39: =INDEX('Draft Engine'!$F$3:$F$232,$P39) -> 3 | D39: =INDEX('Draft Engine'!$B$3:$B$232,$P39) -> Drake Maye | E39: =INDEX('Draft Engine'!$E$3:$E$232,$P39) -> 91.043 | F39: =IF($E39>=95,"ELITE",IF($E39>=90,"TIER 1",IF($E39>=85,"TIER 2",IF($E39>=80,"TIER 3",IF($E39>=75,"TIER 4",IF($E39>=70,"TIER 5",IF($E39>=65,"TIER 6","TIER 7"))))))) -> TIER 1 | G39: =INDEX('Draft Engine'!$G$3:$G$232,$P39) -> 379.7 | H39: =INDEX('Draft Engine'!$J$3:$J$232,$P39) -> 28.6 | I39: =INDEX('Draft Engine'!$N$3:$N$232,$P39) -> 80.683188 | J39: =INDEX('Draft Engine'!$R$3:$R$232,$P39) -> 49.8 | K39: =INDEX('Draft Engine'!$S$3:$S$232,$P39) -> 12.8 | L39: =INDEX('Draft Engine'!$T$3:$T$232,$P39) -> A | M39: =INDEX('Draft Engine'!$X$3:$X$232,$P39) -> RATE-ADJUSTED VETERAN | N39: =INDEX('LIVE SOURCE'!$H$3:$H$232,$P39) -> Elite QB1; weekly top-5 expectation with overall QB1 upside. | O39: =INDEX('LIVE SOURCE'!$J$3:$J$232,$P39) -> Passing-TD efficiency, rushing volume and supporting-cast health are the main swing factors. | P39: =MATCH($A39,'Draft Engine'!$Q$3:$Q$232,0) -> 3
A40: =38 -> 38 | B40: =INDEX('Draft Engine'!$A$3:$A$232,$P40) -> RB | C40: =INDEX('Draft Engine'!$F$3:$F$232,$P40) -> 17 | D40: =INDEX('Draft Engine'!$B$3:$B$232,$P40) -> Javonte Williams | E40: =INDEX('Draft Engine'!$E$3:$E$232,$P40) -> 83.8032 | F40: =IF($E40>=95,"ELITE",IF($E40>=90,"TIER 1",IF($E40>=85,"TIER 2",IF($E40>=80,"TIER 3",IF($E40>=75,"TIER 4",IF($E40>=70,"TIER 5",IF($E40>=65,"TIER 6","TIER 7"))))))) -> TIER 3 | G40: =INDEX('Draft Engine'!$G$3:$G$232,$P40) -> 282 | H40: =INDEX('Draft Engine'!$J$3:$J$232,$P40) -> 43 | I40: =INDEX('Draft Engine'!$N$3:$N$232,$P40) -> 80.33176 | J40: =INDEX('Draft Engine'!$R$3:$R$232,$P40) -> 35.8 | K40: =INDEX('Draft Engine'!$S$3:$S$232,$P40) -> -2.2 | L40: =INDEX('Draft Engine'!$T$3:$T$232,$P40) -> A | M40: =INDEX('Draft Engine'!$X$3:$X$232,$P40) -> RATE-ADJUSTED VETERAN | N40: =INDEX('LIVE SOURCE'!$H$3:$H$232,$P40) -> RB2 with RB1 weeks; should be a regular starter. | O40: =INDEX('LIVE SOURCE'!$J$3:$J$232,$P40) -> Touchdown variance, receiving-role changes and backfield competition are the main downside paths. | P40: =MATCH($A40,'Draft Engine'!$Q$3:$Q$232,0) -> 49
A41: =39 -> 39 | B41: =INDEX('Draft Engine'!$A$3:$A$232,$P41) -> WR | C41: =INDEX('Draft Engine'!$F$3:$F$232,$P41) -> 16 | D41: =INDEX('Draft Engine'!$B$3:$B$232,$P41) -> A.J. Brown | E41: =INDEX('Draft Engine'!$E$3:$E$232,$P41) -> 83.2357 | F41: =IF($E41>=95,"ELITE",IF($E41>=90,"TIER 1",IF($E41>=85,"TIER 2",IF($E41>=80,"TIER 3",IF($E41>=75,"TIER 4",IF($E41>=70,"TIER 5",IF($E41>=65,"TIER 6","TIER 7"))))))) -> TIER 3 | G41: =INDEX('Draft Engine'!$G$3:$G$232,$P41) -> 279.6 | H41: =INDEX('Draft Engine'!$J$3:$J$232,$P41) -> 40.3 | I41: =INDEX('Draft Engine'!$N$3:$N$232,$P41) -> 79.533635 | J41: =INDEX('Draft Engine'!$R$3:$R$232,$P41) -> 17.8 | K41: =INDEX('Draft Engine'!$S$3:$S$232,$P41) -> -21.2 | L41: =INDEX('Draft Engine'!$T$3:$T$232,$P41) -> A | M41: =INDEX('Draft Engine'!$X$3:$X$232,$P41) -> HISTORY FALLBACK | N41: =INDEX('LIVE SOURCE'!$H$3:$H$232,$P41) -> Strong WR2 with top-12 weekly upside. | O41: =INDEX('LIVE SOURCE'!$J$3:$J$232,$P41) -> Price is the biggest risk: the market currently asks you to draft him earlier than the model prefers. | P41: =MATCH($A41,'Draft Engine'!$Q$3:$Q$232,0) -> 89
A42: =40 -> 40 | B42: =INDEX('Draft Engine'!$A$3:$A$232,$P42) -> RB | C42: =INDEX('Draft Engine'!$F$3:$F$232,$P42) -> 18 | D42: =INDEX('Draft Engine'!$B$3:$B$232,$P42) -> Travis Etienne Jr. | E42: =INDEX('Draft Engine'!$E$3:$E$232,$P42) -> 83.0436 | F42: =IF($E42>=95,"ELITE",IF($E42>=90,"TIER 1",IF($E42>=85,"TIER 2",IF($E42>=80,"TIER 3",IF($E42>=75,"TIER 4",IF($E42>=70,"TIER 5",IF($E42>=65,"TIER 6","TIER 7"))))))) -> TIER 3 | G42: =INDEX('Draft Engine'!$G$3:$G$232,$P42) -> 278.8 | H42: =INDEX('Draft Engine'!$J$3:$J$232,$P42) -> 39.8 | I42: =INDEX('Draft Engine'!$N$3:$N$232,$P42) -> 78.978605 | J42: =INDEX('Draft Engine'!$R$3:$R$232,$P42) -> 38.4 | K42: =INDEX('Draft Engine'!$S$3:$S$232,$P42) -> -1.6 | L42: =INDEX('Draft Engine'!$T$3:$T$232,$P42) -> A | M42: =INDEX('Draft Engine'!$X$3:$X$232,$P42) -> RATE-ADJUSTED VETERAN | N42: =INDEX('LIVE SOURCE'!$H$3:$H$232,$P42) -> RB2 with RB1 weeks; should be a regular starter. | O42: =INDEX('LIVE SOURCE'!$J$3:$J$232,$P42) -> Touchdown variance, receiving-role changes and backfield competition are the main downside paths. | P42: =MATCH($A42,'Draft Engine'!$Q$3:$Q$232,0) -> 50
A43: =41 -> 41 | B43: =INDEX('Draft Engine'!$A$3:$A$232,$P43) -> TE | C43: =INDEX('Draft Engine'!$F$3:$F$232,$P43) -> 4 | D43: =INDEX('Draft Engine'!$B$3:$B$232,$P43) -> Tyler Warren | E43: =INDEX('Draft Engine'!$E$3:$E$232,$P43) -> 87.2024 | F43: =IF($E43>=95,"ELITE",IF($E43>=90,"TIER 1",IF($E43>=85,"TIER 2",IF($E43>=80,"TIER 3",IF($E43>=75,"TIER 4",IF($E43>=70,"TIER 5",IF($E43>=65,"TIER 6","TIER 7"))))))) -> TIER 2 | G43: =INDEX('Draft Engine'!$G$3:$G$232,$P43) -> 205.2 | H43: =INDEX('Draft Engine'!$J$3:$J$232,$P43) -> 25.5 | I43: =INDEX('Draft Engine'!$N$3:$N$232,$P43) -> 78.974397 | J43: =INDEX('Draft Engine'!$R$3:$R$232,$P43) -> 65.4 | K43: =INDEX('Draft Engine'!$S$3:$S$232,$P43) -> 24.4 | L43: =INDEX('Draft Engine'!$T$3:$T$232,$P43) -> A | M43: =INDEX('Draft Engine'!$X$3:$X$232,$P43) -> RATE-ADJUSTED VETERAN | N43: =INDEX('LIVE SOURCE'!$H$3:$H$232,$P43) -> Every-week TE1 with real top-5 upside. | O43: =INDEX('LIVE SOURCE'!$J$3:$J$232,$P43) -> Route share, target volume and touchdown volatility are the main swing factors. | P43: =MATCH($A43,'Draft Engine'!$Q$3:$Q$232,0) -> 162
A44: =42 -> 42 | B44: =INDEX('Draft Engine'!$A$3:$A$232,$P44) -> QB | C44: =INDEX('Draft Engine'!$F$3:$F$232,$P44) -> 4 | D44: =INDEX('Draft Engine'!$B$3:$B$232,$P44) -> Justin Herbert | E44: =INDEX('Draft Engine'!$E$3:$E$232,$P44) -> 90.1169 | F44: =IF($E44>=95,"ELITE",IF($E44>=90,"TIER 1",IF($E44>=85,"TIER 2",IF($E44>=80,"TIER 3",IF($E44>=75,"TIER 4",IF($E44>=70,"TIER 5",IF($E44>=65,"TIER 6","TIER 7"))))))) -> TIER 1 | G44: =INDEX('Draft Engine'!$G$3:$G$232,$P44) -> 375.5 | H44: =INDEX('Draft Engine'!$J$3:$J$232,$P44) -> 24.4 | I44: =INDEX('Draft Engine'!$N$3:$N$232,$P44) -> 78.648603 | J44: =INDEX('Draft Engine'!$R$3:$R$232,$P44) -> 104.2 | K44: =INDEX('Draft Engine'!$S$3:$S$232,$P44) -> 62.2 | L44: =INDEX('Draft Engine'!$T$3:$T$232,$P44) -> A | M44: =INDEX('Draft Engine'!$X$3:$X$232,$P44) -> RATE-ADJUSTED VETERAN | N44: =INDEX('LIVE SOURCE'!$H$3:$H$232,$P44) -> Strong every-week QB1; frequent top-8 finishes expected. | O44: =INDEX('LIVE SOURCE'!$J$3:$J$232,$P44) -> Passing-TD efficiency, rushing volume and supporting-cast health are the main swing factors. | P44: =MATCH($A44,'Draft Engine'!$Q$3:$Q$232,0) -> 4
A45: =43 -> 43 | B45: =INDEX('Draft Engine'!$A$3:$A$232,$P45) -> WR | C45: =INDEX('Draft Engine'!$F$3:$F$232,$P45) -> 17 | D45: =INDEX('Draft Engine'!$B$3:$B$232,$P45) -> Ladd McConkey | E45: =INDEX('Draft Engine'!$E$3:$E$232,$P45) -> 82.7325 | F45: =IF($E45>=95,"ELITE",IF($E45>=90,"TIER 1",IF($E45>=85,"TIER 2",IF($E45>=80,"TIER 3",IF($E45>=75,"TIER 4",IF($E45>=70,"TIER 5",IF($E45>=65,"TIER 6","TIER 7"))))))) -> TIER 3 | G45: =INDEX('Draft Engine'!$G$3:$G$232,$P45) -> 277.5 | H45: =INDEX('Draft Engine'!$J$3:$J$232,$P45) -> 38.2 | I45: =INDEX('Draft Engine'!$N$3:$N$232,$P45) -> 78.545542 | J45: =INDEX('Draft Engine'!$R$3:$R$232,$P45) -> 44.3 | K45: =INDEX('Draft Engine'!$S$3:$S$232,$P45) -> 1.3 | L45: =INDEX('Draft Engine'!$T$3:$T$232,$P45) -> B | M45: =INDEX('Draft Engine'!$X$3:$X$232,$P45) -> HISTORY FALLBACK | N45: =INDEX('LIVE SOURCE'!$H$3:$H$232,$P45) -> Strong WR2 with top-12 weekly upside. | O45: =INDEX('LIVE SOURCE'!$J$3:$J$232,$P45) -> Target competition, quarterback efficiency and touchdown regression are the main downside paths. | P45: =MATCH($A45,'Draft Engine'!$Q$3:$Q$232,0) -> 106
A46: =44 -> 44 | B46: =INDEX('Draft Engine'!$A$3:$A$232,$P46) -> WR | C46: =INDEX('Draft Engine'!$F$3:$F$232,$P46) -> 18 | D46: =INDEX('Draft Engine'!$B$3:$B$232,$P46) -> Jaylen Waddle | E46: =INDEX('Draft Engine'!$E$3:$E$232,$P46) -> 82.3175 | F46: =IF($E46>=95,"ELITE",IF($E46>=90,"TIER 1",IF($E46>=85,"TIER 2",IF($E46>=80,"TIER 3",IF($E46>=75,"TIER 4",IF($E46>=70,"TIER 5",IF($E46>=65,"TIER 6","TIER 7"))))))) -> TIER 3 | G46: =INDEX('Draft Engine'!$G$3:$G$232,$P46) -> 275.7 | H46: =INDEX('Draft Engine'!$J$3:$J$232,$P46) -> 36.4 | I46: =INDEX('Draft Engine'!$N$3:$N$232,$P46) -> 77.659958 | J46: =INDEX('Draft Engine'!$R$3:$R$232,$P46) -> 48.9 | K46: =INDEX('Draft Engine'!$S$3:$S$232,$P46) -> 4.9 | L46: =INDEX('Draft Engine'!$T$3:$T$232,$P46) -> C | M46: =INDEX('Draft Engine'!$X$3:$X$232,$P46) -> HISTORY FALLBACK | N46: =INDEX('LIVE SOURCE'!$H$3:$H$232,$P46) -> Strong WR2 with top-12 weekly upside. | O46: =INDEX('LIVE SOURCE'!$J$3:$J$232,$P46) -> Target competition, quarterback efficiency and touchdown regression are the main downside paths. | P46: =MATCH($A46,'Draft Engine'!$Q$3:$Q$232,0) -> 104
A47: =45 -> 45 | B47: =INDEX('Draft Engine'!$A$3:$A$232,$P47) -> TE | C47: =INDEX('Draft Engine'!$F$3:$F$232,$P47) -> 5 | D47: =INDEX('Draft Engine'!$B$3:$B$232,$P47) -> George Kittle | E47: =INDEX('Draft Engine'!$E$3:$E$232,$P47) -> 86.2664 | F47: =IF($E47>=95,"ELITE",IF($E47>=90,"TIER 1",IF($E47>=85,"TIER 2",IF($E47>=80,"TIER 3",IF($E47>=75,"TIER 4",IF($E47>=70,"TIER 5",IF($E47>=65,"TIER 6","TIER 7"))))))) -> TIER 2 | G47: =INDEX('Draft Engine'!$G$3:$G$232,$P47) -> 201.9 | H47: =INDEX('Draft Engine'!$J$3:$J$232,$P47) -> 22.2 | I47: =INDEX('Draft Engine'!$N$3:$N$232,$P47) -> 77.173289 | J47: =INDEX('Draft Engine'!$R$3:$R$232,$P47) -> 115.1 | K47: =INDEX('Draft Engine'!$S$3:$S$232,$P47) -> 70.1 | L47: =INDEX('Draft Engine'!$T$3:$T$232,$P47) -> B | M47: =INDEX('Draft Engine'!$X$3:$X$232,$P47) -> RATE-ADJUSTED VETERAN | N47: =INDEX('LIVE SOURCE'!$H$3:$H$232,$P47) -> Every-week TE1 with real top-5 upside. | O47: =INDEX('LIVE SOURCE'!$J$3:$J$232,$P47) -> Route share, target volume and touchdown volatility are the main swing factors. | P47: =MATCH($A47,'Draft Engine'!$Q$3:$Q$232,0) -> 163
A48: =46 -> 46 | B48: =INDEX('Draft Engine'!$A$3:$A$232,$P48) -> RB | C48: =INDEX('Draft Engine'!$F$3:$F$232,$P48) -> 19 | D48: =INDEX('Draft Engine'!$B$3:$B$232,$P48) -> Cam Skattebo | E48: =INDEX('Draft Engine'!$E$3:$E$232,$P48) -> 81.8884 | F48: =IF($E48>=95,"ELITE",IF($E48>=90,"TIER 1",IF($E48>=85,"TIER 2",IF($E48>=80,"TIER 3",IF($E48>=75,"TIER 4",IF($E48>=70,"TIER 5",IF($E48>=65,"TIER 6","TIER 7"))))))) -> TIER 3 | G48: =INDEX('Draft Engine'!$G$3:$G$232,$P48) -> 273.9 | H48: =INDEX('Draft Engine'!$J$3:$J$232,$P48) -> 34.9 | I48: =INDEX('Draft Engine'!$N$3:$N$232,$P48) -> 77.10187 | J48: =INDEX('Draft Engine'!$R$3:$R$232,$P48) -> 30.8 | K48: =INDEX('Draft Engine'!$S$3:$S$232,$P48) -> -15.2 | L48: =INDEX('Draft Engine'!$T$3:$T$232,$P48) -> B | M48: =INDEX('Draft Engine'!$X$3:$X$232,$P48) -> RATE-ADJUSTED VETERAN | N48: =INDEX('LIVE SOURCE'!$H$3:$H$232,$P48) -> RB2 with RB1 weeks; should be a regular starter. | O48: =INDEX('LIVE SOURCE'!$J$3:$J$232,$P48) -> Availability/sample risk is elevated after only 8 games; talent is not being punished as heavily as durability. | P48: =MATCH($A48,'Draft Engine'!$Q$3:$Q$232,0) -> 51
A49: =47 -> 47 | B49: =INDEX('Draft Engine'!$A$3:$A$232,$P49) -> WR | C49: =INDEX('Draft Engine'!$F$3:$F$232,$P49) -> 19 | D49: =INDEX('Draft Engine'!$B$3:$B$232,$P49) -> George Pickens | E49: =INDEX('Draft Engine'!$E$3:$E$232,$P49) -> 81.8366 | F49: =IF($E49>=95,"ELITE",IF($E49>=90,"TIER 1",IF($E49>=85,"TIER 2",IF($E49>=80,"TIER 3",IF($E49>=75,"TIER 4",IF($E49>=70,"TIER 5",IF($E49>=65,"TIER 6","TIER 7"))))))) -> TIER 3 | G49: =INDEX('Draft Engine'!$G$3:$G$232,$P49) -> 273.7 | H49: =INDEX('Draft Engine'!$J$3:$J$232,$P49) -> 34.4 | I49: =INDEX('Draft Engine'!$N$3:$N$232,$P49) -> 76.70213 | J49: =INDEX('Draft Engine'!$R$3:$R$232,$P49) -> 21.1 | K49: =INDEX('Draft Engine'!$S$3:$S$232,$P49) -> -25.9 | L49: =INDEX('Draft Engine'!$T$3:$T$232,$P49) -> A | M49: =INDEX('Draft Engine'!$X$3:$X$232,$P49) -> HISTORY FALLBACK | N49: =INDEX('LIVE SOURCE'!$H$3:$H$232,$P49) -> Strong WR2 with top-12 weekly upside. | O49: =INDEX('LIVE SOURCE'!$J$3:$J$232,$P49) -> Price is the biggest risk: the market currently asks you to draft him earlier than the model prefers. | P49: =MATCH($A49,'Draft Engine'!$Q$3:$Q$232,0) -> 92
A50: =48 -> 48 | B50: =INDEX('Draft Engine'!$A$3:$A$232,$P50) -> WR | C50: =INDEX('Draft Engine'!$F$3:$F$232,$P50) -> 20 | D50: =INDEX('Draft Engine'!$B$3:$B$232,$P50) -> Emeka Egbuka | E50: =INDEX('Draft Engine'!$E$3:$E$232,$P50) -> 81.735 | F50: =IF($E50>=95,"ELITE",IF($E50>=90,"TIER 1",IF($E50>=85,"TIER 2",IF($E50>=80,"TIER 3",IF($E50>=75,"TIER 4",IF($E50>=70,"TIER 5",IF($E50>=65,"TIER 6","TIER 7"))))))) -> TIER 3 | G50: =INDEX('Draft Engine'!$G$3:$G$232,$P50) -> 273.3 | H50: =INDEX('Draft Engine'!$J$3:$J$232,$P50) -> 34 | I50: =INDEX('Draft Engine'!$N$3:$N$232,$P50) -> 76.240917 | J50: =INDEX('Draft Engine'!$R$3:$R$232,$P50) -> 34.4 | K50: =INDEX('Draft Engine'!$S$3:$S$232,$P50) -> -13.6 | L50: =INDEX('Draft Engine'!$T$3:$T$232,$P50) -> C | M50: =INDEX('Draft Engine'!$X$3:$X$232,$P50) -> HISTORY FALLBACK | N50: =INDEX('LIVE SOURCE'!$H$3:$H$232,$P50) -> Strong WR2 with top-12 weekly upside. | O50: =INDEX('LIVE SOURCE'!$J$3:$J$232,$P50) -> Target competition, quarterback efficiency and touchdown regression are the main downside paths. | P50: =MATCH($A50,'Draft Engine'!$Q$3:$Q$232,0) -> 103
A51: =49 -> 49 | B51: =INDEX('Draft Engine'!$A$3:$A$232,$P51) -> QB | C51: =INDEX('Draft Engine'!$F$3:$F$232,$P51) -> 5 | D51: =INDEX('Draft Engine'!$B$3:$B$232,$P51) -> Lamar Jackson | E51: =INDEX('Draft Engine'!$E$3:$E$232,$P51) -> 88.7112 | F51: =IF($E51>=95,"ELITE",IF($E51>=90,"TIER 1",IF($E51>=85,"TIER 2",IF($E51>=80,"TIER 3",IF($E51>=75,"TIER 4",IF($E51>=70,"TIER 5",IF($E51>=65,"TIER 6","TIER 7"))))))) -> TIER 2 | G51: =INDEX('Draft Engine'!$G$3:$G$232,$P51) -> 369.2 | H51: =INDEX('Draft Engine'!$J$3:$J$232,$P51) -> 18.1 | I51: =INDEX('Draft Engine'!$N$3:$N$232,$P51) -> 75.972237 | J51: =INDEX('Draft Engine'!$R$3:$R$232,$P51) -> 52.6 | K51: =INDEX('Draft Engine'!$S$3:$S$232,$P51) -> 3.6 | L51: =INDEX('Draft Engine'!$T$3:$T$232,$P51) -> A | M51: =INDEX('Draft Engine'!$X$3:$X$232,$P51) -> RATE-ADJUSTED VETERAN | N51: =INDEX('LIVE SOURCE'!$H$3:$H$232,$P51) -> Strong every-week QB1; frequent top-8 finishes expected. | O51: =INDEX('LIVE SOURCE'!$J$3:$J$232,$P51) -> Passing-TD efficiency, rushing volume and supporting-cast health are the main swing factors. | P51: =MATCH($A51,'Draft Engine'!$Q$3:$Q$232,0) -> 5
A52: =50 -> 50 | B52: =INDEX('Draft Engine'!$A$3:$A$232,$P52) -> TE | C52: =INDEX('Draft Engine'!$F$3:$F$232,$P52) -> 6 | D52: =INDEX('Draft Engine'!$B$3:$B$232,$P52) -> Kyle Pitts Sr. | E52: =INDEX('Draft Engine'!$E$3:$E$232,$P52) -> 85.3045 | F52: =IF($E52>=95,"ELITE",IF($E52>=90,"TIER 1",IF($E52>=85,"TIER 2",IF($E52>=80,"TIER 3",IF($E52>=75,"TIER 4",IF($E52>=70,"TIER 5",IF($E52>=65,"TIER 6","TIER 7"))))))) -> TIER 2 | G52: =INDEX('Draft Engine'!$G$3:$G$232,$P52) -> 198.6 | H52: =INDEX('Draft Engine'!$J$3:$J$232,$P52) -> 18.9 | I52: =INDEX('Draft Engine'!$N$3:$N$232,$P52) -> 75.357937 | J52: =INDEX('Draft Engine'!$R$3:$R$232,$P52) -> 78.3 | K52: =INDEX('Draft Engine'!$S$3:$S$232,$P52) -> 28.3 | L52: =INDEX('Draft Engine'!$T$3:$T$232,$P52) -> A | M52: =INDEX('Draft Engine'!$X$3:$X$232,$P52) -> RATE-ADJUSTED VETERAN | N52: =INDEX('LIVE SOURCE'!$H$3:$H$232,$P52) -> Every-week TE1 with real top-5 upside. | O52: =INDEX('LIVE SOURCE'!$J$3:$J$232,$P52) -> Route share, target volume and touchdown volatility are the main swing factors. | P52: =MATCH($A52,'Draft Engine'!$Q$3:$Q$232,0) -> 164
A53: =51 -> 51 | B53: =INDEX('Draft Engine'!$A$3:$A$232,$P53) -> WR | C53: =INDEX('Draft Engine'!$F$3:$F$232,$P53) -> 21 | D53: =INDEX('Draft Engine'!$B$3:$B$232,$P53) -> Malik Nabers | E53: =INDEX('Draft Engine'!$E$3:$E$232,$P53) -> 81.1525 | F53: =IF($E53>=95,"ELITE",IF($E53>=90,"TIER 1",IF($E53>=85,"TIER 2",IF($E53>=80,"TIER 3",IF($E53>=75,"TIER 4",IF($E53>=70,"TIER 5",IF($E53>=65,"TIER 6","TIER 7"))))))) -> TIER 3 | G53: =INDEX('Draft Engine'!$G$3:$G$232,$P53) -> 270.8 | H53: =INDEX('Draft Engine'!$J$3:$J$232,$P53) -> 31.5 | I53: =INDEX('Draft Engine'!$N$3:$N$232,$P53) -> 75.137208 | J53: =INDEX('Draft Engine'!$R$3:$R$232,$P53) -> 31.9 | K53: =INDEX('Draft Engine'!$S$3:$S$232,$P53) -> -19.1 | L53: =INDEX('Draft Engine'!$T$3:$T$232,$P53) -> C | M53: =INDEX('Draft Engine'!$X$3:$X$232,$P53) -> HISTORY FALLBACK | N53: =INDEX('LIVE SOURCE'!$H$3:$H$232,$P53) -> Strong WR2 with top-12 weekly upside. | O53: =INDEX('LIVE SOURCE'!$J$3:$J$232,$P53) -> Evidence is thinner than for established veterans, so camp, depth-chart and role news can move the grade materially. | P53: =MATCH($A53,'Draft Engine'!$Q$3:$Q$232,0) -> 102
A54: =52 -> 52 | B54: =INDEX('Draft Engine'!$A$3:$A$232,$P54) -> QB | C54: =INDEX('Draft Engine'!$F$3:$F$232,$P54) -> 6 | D54: =INDEX('Draft Engine'!$B$3:$B$232,$P54) -> Jalen Hurts | E54: =INDEX('Draft Engine'!$E$3:$E$232,$P54) -> 88.4499 | F54: =IF($E54>=95,"ELITE",IF($E54>=90,"TIER 1",IF($E54>=85,"TIER 2",IF($E54>=80,"TIER 3",IF($E54>=75,"TIER 4",IF($E54>=70,"TIER 5",IF($E54>=65,"TIER 6","TIER 7"))))))) -> TIER 2 | G54: =INDEX('Draft Engine'!$G$3:$G$232,$P54) -> 368 | H54: =INDEX('Draft Engine'!$J$3:$J$232,$P54) -> 16.9 | I54: =INDEX('Draft Engine'!$N$3:$N$232,$P54) -> 74.843291 | J54: =INDEX('Draft Engine'!$R$3:$R$232,$P54) -> 73.7 | K54: =INDEX('Draft Engine'!$S$3:$S$232,$P54) -> 21.7 | L54: =INDEX('Draft Engine'!$T$3:$T$232,$P54) -> A | M54: =INDEX('Draft Engine'!$X$3:$X$232,$P54) -> RATE-ADJUSTED VETERAN | N54: =INDEX('LIVE SOURCE'!$H$3:$H$232,$P54) -> Strong every-week QB1; frequent top-8 finishes expected. | O54: =INDEX('LIVE SOURCE'!$J$3:$J$232,$P54) -> Passing-TD efficiency, rushing volume and supporting-cast health are the main swing factors. | P54: =MATCH($A54,'Draft Engine'!$Q$3:$Q$232,0) -> 6
A55: =53 -> 53 | B55: =INDEX('Draft Engine'!$A$3:$A$232,$P55) -> RB | C55: =INDEX('Draft Engine'!$F$3:$F$232,$P55) -> 20 | D55: =INDEX('Draft Engine'!$B$3:$B$232,$P55) -> D'Andre Swift | E55: =INDEX('Draft Engine'!$E$3:$E$232,$P55) -> 79.9856 | F55: =IF($E55>=95,"ELITE",IF($E55>=90,"TIER 1",IF($E55>=85,"TIER 2",IF($E55>=80,"TIER 3",IF($E55>=75,"TIER 4",IF($E55>=70,"TIER 5",IF($E55>=65,"TIER 6","TIER 7"))))))) -> TIER 4 | G55: =INDEX('Draft Engine'!$G$3:$G$232,$P55) -> 265.9 | H55: =INDEX('Draft Engine'!$J$3:$J$232,$P55) -> 26.9 | I55: =INDEX('Draft Engine'!$N$3:$N$232,$P55) -> 74.255955 | J55: =INDEX('Draft Engine'!$R$3:$R$232,$P55) -> 43.9 | K55: =INDEX('Draft Engine'!$S$3:$S$232,$P55) -> -9.1 | L55: =INDEX('Draft Engine'!$T$3:$T$232,$P55) -> A | M55: =INDEX('Draft Engine'!$X$3:$X$232,$P55) -> RATE-ADJUSTED VETERAN | N55: =INDEX('LIVE SOURCE'!$H$3:$H$232,$P55) -> RB2 with RB1 weeks; should be a regular starter. | O55: =INDEX('LIVE SOURCE'!$J$3:$J$232,$P55) -> Touchdown variance, receiving-role changes and backfield competition are the main downside paths. | P55: =MATCH($A55,'Draft Engine'!$Q$3:$Q$232,0) -> 52
A56: =54 -> 54 | B56: =INDEX('Draft Engine'!$A$3:$A$232,$P56) -> RB | C56: =INDEX('Draft Engine'!$F$3:$F$232,$P56) -> 21 | D56: =INDEX('Draft Engine'!$B$3:$B$232,$P56) -> Bucky Irving | E56: =INDEX('Draft Engine'!$E$3:$E$232,$P56) -> 79.9355 | F56: =IF($E56>=95,"ELITE",IF($E56>=90,"TIER 1",IF($E56>=85,"TIER 2",IF($E56>=80,"TIER 3",IF($E56>=75,"TIER 4",IF($E56>=70,"TIER 5",IF($E56>=65,"TIER 6","TIER 7"))))))) -> TIER 4 | G56: =INDEX('Draft Engine'!$G$3:$G$232,$P56) -> 265.7 | H56: =INDEX('Draft Engine'!$J$3:$J$232,$P56) -> 26.7 | I56: =INDEX('Draft Engine'!$N$3:$N$232,$P56) -> 73.833025 | J56: =INDEX('Draft Engine'!$R$3:$R$232,$P56) -> 43 | K56: =INDEX('Draft Engine'!$S$3:$S$232,$P56) -> -11 | L56: =INDEX('Draft Engine'!$T$3:$T$232,$P56) -> B | M56: =INDEX('Draft Engine'!$X$3:$X$232,$P56) -> RATE-ADJUSTED VETERAN | N56: =INDEX('LIVE SOURCE'!$H$3:$H$232,$P56) -> RB2/FLEX; useful weekly but role and receiving volume matter. | O56: =INDEX('LIVE SOURCE'!$J$3:$J$232,$P56) -> Touchdown variance, receiving-role changes and backfield competition are the main downside paths. | P56: =MATCH($A56,'Draft Engine'!$Q$3:$Q$232,0) -> 53
A57: =55 -> 55 | B57: =INDEX('Draft Engine'!$A$3:$A$232,$P57) -> TE | C57: =INDEX('Draft Engine'!$F$3:$F$232,$P57) -> 7 | D57: =INDEX('Draft Engine'!$B$3:$B$232,$P57) -> Harold Fannin Jr. | E57: =INDEX('Draft Engine'!$E$3:$E$232,$P57) -> 84.3777 | F57: =IF($E57>=95,"ELITE",IF($E57>=90,"TIER 1",IF($E57>=85,"TIER 2",IF($E57>=80,"TIER 3",IF($E57>=75,"TIER 4",IF($E57>=70,"TIER 5",IF($E57>=65,"TIER 6","TIER 7"))))))) -> TIER 3 | G57: =INDEX('Draft Engine'!$G$3:$G$232,$P57) -> 195.3 | H57: =INDEX('Draft Engine'!$J$3:$J$232,$P57) -> 15.6 | I57: =INDEX('Draft Engine'!$N$3:$N$232,$P57) -> 73.561889 | J57: =INDEX('Draft Engine'!$R$3:$R$232,$P57) -> 82.8 | K57: =INDEX('Draft Engine'!$S$3:$S$232,$P57) -> 27.8 | L57: =INDEX('Draft Engine'!$T$3:$T$232,$P57) -> A | M57: =INDEX('Draft Engine'!$X$3:$X$232,$P57) -> RATE-ADJUSTED VETERAN | N57: =INDEX('LIVE SOURCE'!$H$3:$H$232,$P57) -> Every-week TE1 with real top-5 upside. | O57: =INDEX('LIVE SOURCE'!$J$3:$J$232,$P57) -> Route share, target volume and touchdown volatility are the main swing factors. | P57: =MATCH($A57,'Draft Engine'!$Q$3:$Q$232,0) -> 165
A58: =56 -> 56 | B58: =INDEX('Draft Engine'!$A$3:$A$232,$P58) -> RB | C58: =INDEX('Draft Engine'!$F$3:$F$232,$P58) -> 22 | D58: =INDEX('Draft Engine'!$B$3:$B$232,$P58) -> Quinshon Judkins | E58: =INDEX('Draft Engine'!$E$3:$E$232,$P58) -> 79.9303 | F58: =IF($E58>=95,"ELITE",IF($E58>=90,"TIER 1",IF($E58>=85,"TIER 2",IF($E58>=80,"TIER 3",IF($E58>=75,"TIER 4",IF($E58>=70,"TIER 5",IF($E58>=65,"TIER 6","TIER 7"))))))) -> TIER 4 | G58: =INDEX('Draft Engine'!$G$3:$G$232,$P58) -> 265.7 | H58: =INDEX('Draft Engine'!$J$3:$J$232,$P58) -> 26.7 | I58: =INDEX('Draft Engine'!$N$3:$N$232,$P58) -> 73.47079 | J58: =INDEX('Draft Engine'!$R$3:$R$232,$P58) -> 49.9 | K58: =INDEX('Draft Engine'!$S$3:$S$232,$P58) -> -6.1 | L58: =INDEX('Draft Engine'!$T$3:$T$232,$P58) -> A | M58: =INDEX('Draft Engine'!$X$3:$X$232,$P58) -> RATE-ADJUSTED VETERAN | N58: =INDEX('LIVE SOURCE'!$H$3:$H$232,$P58) -> RB2/FLEX; useful weekly but role and receiving volume matter. | O58: =INDEX('LIVE SOURCE'!$J$3:$J$232,$P58) -> Touchdown variance, receiving-role changes and backfield competition are the main downside paths. | P58: =MATCH($A58,'Draft Engine'!$Q$3:$Q$232,0) -> 54
A59: =57 -> 57 | B59: =INDEX('Draft Engine'!$A$3:$A$232,$P59) -> WR | C59: =INDEX('Draft Engine'!$F$3:$F$232,$P59) -> 22 | D59: =INDEX('Draft Engine'!$B$3:$B$232,$P59) -> Terry McLaurin | E59: =INDEX('Draft Engine'!$E$3:$E$232,$P59) -> 79.9 | F59: =IF($E59>=95,"ELITE",IF($E59>=90,"TIER 1",IF($E59>=85,"TIER 2",IF($E59>=80,"TIER 3",IF($E59>=75,"TIER 4",IF($E59>=70,"TIER 5",IF($E59>=65,"TIER 6","TIER 7"))))))) -> TIER 4 | G59: =INDEX('Draft Engine'!$G$3:$G$232,$P59) -> 265.6 | H59: =INDEX('Draft Engine'!$J$3:$J$232,$P59) -> 26.3 | I59: =INDEX('Draft Engine'!$N$3:$N$232,$P59) -> 73.179 | J59: =INDEX('Draft Engine'!$R$3:$R$232,$P59) -> 43 | K59: =INDEX('Draft Engine'!$S$3:$S$232,$P59) -> -14 | L59: =INDEX('Draft Engine'!$T$3:$T$232,$P59) -> C | M59: =INDEX('Draft Engine'!$X$3:$X$232,$P59) -> HISTORY FALLBACK | N59: =INDEX('LIVE SOURCE'!$H$3:$H$232,$P59) -> Strong WR2 with top-12 weekly upside. | O59: =INDEX('LIVE SOURCE'!$J$3:$J$232,$P59) -> Target competition, quarterback efficiency and touchdown regression are the main downside paths. | P59: =MATCH($A59,'Draft Engine'!$Q$3:$Q$232,0) -> 105
A60: =58 -> 58 | B60: =INDEX('Draft Engine'!$A$3:$A$232,$P60) -> TE | C60: =INDEX('Draft Engine'!$F$3:$F$232,$P60) -> 8 | D60: =INDEX('Draft Engine'!$B$3:$B$232,$P60) -> Jake Ferguson | E60: =INDEX('Draft Engine'!$E$3:$E$232,$P60) -> 84.073 | F60: =IF($E60>=95,"ELITE",IF($E60>=90,"TIER 1",IF($E60>=85,"TIER 2",IF($E60>=80,"TIER 3",IF($E60>=75,"TIER 4",IF($E60>=70,"TIER 5",IF($E60>=65,"TIER 6","TIER 7"))))))) -> TIER 3 | G60: =INDEX('Draft Engine'!$G$3:$G$232,$P60) -> 194.3 | H60: =INDEX('Draft Engine'!$J$3:$J$232,$P60) -> 14.6 | I60: =INDEX('Draft Engine'!$N$3:$N$232,$P60) -> 72.521996 | J60: =INDEX('Draft Engine'!$R$3:$R$232,$P60) -> 140.8 | K60: =INDEX('Draft Engine'!$S$3:$S$232,$P60) -> 82.8 | L60: =INDEX('Draft Engine'!$T$3:$T$232,$P60) -> A | M60: =INDEX('Draft Engine'!$X$3:$X$232,$P60) -> RATE-ADJUSTED VETERAN | N60: =INDEX('LIVE SOURCE'!$H$3:$H$232,$P60) -> Every-week TE1 with real top-5 upside. | O60: =INDEX('LIVE SOURCE'!$J$3:$J$232,$P60) -> Route share, target volume and touchdown volatility are the main swing factors. | P60: =MATCH($A60,'Draft Engine'!$Q$3:$Q$232,0) -> 166
A61: =59 -> 59 | B61: =INDEX('Draft Engine'!$A$3:$A$232,$P61) -> QB | C61: =INDEX('Draft Engine'!$F$3:$F$232,$P61) -> 7 | D61: =INDEX('Draft Engine'!$B$3:$B$232,$P61) -> Patrick Mahomes II | E61: =INDEX('Draft Engine'!$E$3:$E$232,$P61) -> 87.0063 | F61: =IF($E61>=95,"ELITE",IF($E61>=90,"TIER 1",IF($E61>=85,"TIER 2",IF($E61>=80,"TIER 3",IF($E61>=75,"TIER 4",IF($E61>=70,"TIER 5",IF($E61>=65,"TIER 6","TIER 7"))))))) -> TIER 2 | G61: =INDEX('Draft Engine'!$G$3:$G$232,$P61) -> 361.5 | H61: =INDEX('Draft Engine'!$J$3:$J$232,$P61) -> 10.4 | I61: =INDEX('Draft Engine'!$N$3:$N$232,$P61) -> 72.11008 | J61: =INDEX('Draft Engine'!$R$3:$R$232,$P61) -> 97.4 | K61: =INDEX('Draft Engine'!$S$3:$S$232,$P61) -> 38.4 | L61: =INDEX('Draft Engine'!$T$3:$T$232,$P61) -> A | M61: =INDEX('Draft Engine'!$X$3:$X$232,$P61) -> RATE-ADJUSTED VETERAN | N61: =INDEX('LIVE SOURCE'!$H$3:$H$232,$P61) -> Strong every-week QB1; frequent top-8 finishes expected. | O61: =INDEX('LIVE SOURCE'!$J$3:$J$232,$P61) -> Passing-TD efficiency, rushing volume and supporting-cast health are the main swing factors. | P61: =MATCH($A61,'Draft Engine'!$Q$3:$Q$232,0) -> 7
A62: =60 -> 60 | B62: =INDEX('Draft Engine'!$A$3:$A$232,$P62) -> TE | C62: =INDEX('Draft Engine'!$F$3:$F$232,$P62) -> 9 | D62: =INDEX('Draft Engine'!$B$3:$B$232,$P62) -> Tucker Kraft | E62: =INDEX('Draft Engine'!$E$3:$E$232,$P62) -> 83.8086 | F62: =IF($E62>=95,"ELITE",IF($E62>=90,"TIER 1",IF($E62>=85,"TIER 2",IF($E62>=80,"TIER 3",IF($E62>=75,"TIER 4",IF($E62>=70,"TIER 5",IF($E62>=65,"TIER 6","TIER 7"))))))) -> TIER 3 | G62: =INDEX('Draft Engine'!$G$3:$G$232,$P62) -> 193.3 | H62: =INDEX('Draft Engine'!$J$3:$J$232,$P62) -> 13.6 | I62: =INDEX('Draft Engine'!$N$3:$N$232,$P62) -> 71.504268 | J62: =INDEX('Draft Engine'!$R$3:$R$232,$P62) -> 108.3 | K62: =INDEX('Draft Engine'!$S$3:$S$232,$P62) -> 48.3 | L62: =INDEX('Draft Engine'!$T$3:$T$232,$P62) -> B | M62: =INDEX('Draft Engine'!$X$3:$X$232,$P62) -> RATE-ADJUSTED VETERAN | N62: =INDEX('LIVE SOURCE'!$H$3:$H$232,$P62) -> Low-end TE1; startable but replacement options remain close. | O62: =INDEX('LIVE SOURCE'!$J$3:$J$232,$P62) -> Availability/sample risk is elevated after only 8 games; talent is not being punished as heavily as durability. | P62: =MATCH($A62,'Draft Engine'!$Q$3:$Q$232,0) -> 167
A63: =61 -> 61 | B63: =INDEX('Draft Engine'!$A$3:$A$232,$P63) -> WR | C63: =INDEX('Draft Engine'!$F$3:$F$232,$P63) -> 23 | D63: =INDEX('Draft Engine'!$B$3:$B$232,$P63) -> Luther Burden III | E63: =INDEX('Draft Engine'!$E$3:$E$232,$P63) -> 78.6475 | F63: =IF($E63>=95,"ELITE",IF($E63>=90,"TIER 1",IF($E63>=85,"TIER 2",IF($E63>=80,"TIER 3",IF($E63>=75,"TIER 4",IF($E63>=70,"TIER 5",IF($E63>=65,"TIER 6","TIER 7"))))))) -> TIER 4 | G63: =INDEX('Draft Engine'!$G$3:$G$232,$P63) -> 260.3 | H63: =INDEX('Draft Engine'!$J$3:$J$232,$P63) -> 21 | I63: =INDEX('Draft Engine'!$N$3:$N$232,$P63) -> 71.202792 | J63: =INDEX('Draft Engine'!$R$3:$R$232,$P63) -> 53.1 | K63: =INDEX('Draft Engine'!$S$3:$S$232,$P63) -> -7.9 | L63: =INDEX('Draft Engine'!$T$3:$T$232,$P63) -> C | M63: =INDEX('Draft Engine'!$X$3:$X$232,$P63) -> HISTORY FALLBACK | N63: =INDEX('LIVE SOURCE'!$H$3:$H$232,$P63) -> Strong WR2 with top-12 weekly upside. | O63: =INDEX('LIVE SOURCE'!$J$3:$J$232,$P63) -> Target competition, quarterback efficiency and touchdown regression are the main downside paths. | P63: =MATCH($A63,'Draft Engine'!$Q$3:$Q$232,0) -> 108
A64: =62 -> 62 | B64: =INDEX('Draft Engine'!$A$3:$A$232,$P64) -> QB | C64: =INDEX('Draft Engine'!$F$3:$F$232,$P64) -> 8 | D64: =INDEX('Draft Engine'!$B$3:$B$232,$P64) -> Jayden Daniels | E64: =INDEX('Draft Engine'!$E$3:$E$232,$P64) -> 86.7003 | F64: =IF($E64>=95,"ELITE",IF($E64>=90,"TIER 1",IF($E64>=85,"TIER 2",IF($E64>=80,"TIER 3",IF($E64>=75,"TIER 4",IF($E64>=70,"TIER 5",IF($E64>=65,"TIER 6","TIER 7"))))))) -> TIER 2 | G64: =INDEX('Draft Engine'!$G$3:$G$232,$P64) -> 360.2 | H64: =INDEX('Draft Engine'!$J$3:$J$232,$P64) -> 9.1 | I64: =INDEX('Draft Engine'!$N$3:$N$232,$P64) -> 70.93855 | J64: =INDEX('Draft Engine'!$R$3:$R$232,$P64) -> 67 | K64: =INDEX('Draft Engine'!$S$3:$S$232,$P64) -> 5 | L64: =INDEX('Draft Engine'!$T$3:$T$232,$P64) -> B | M64: =INDEX('Draft Engine'!$X$3:$X$232,$P64) -> RATE-ADJUSTED VETERAN | N64: =INDEX('LIVE SOURCE'!$H$3:$H$232,$P64) -> Strong every-week QB1; frequent top-8 finishes expected. | O64: =INDEX('LIVE SOURCE'!$J$3:$J$232,$P64) -> Availability/sample risk is elevated after only 7 games; talent is not being punished as heavily as durability. | P64: =MATCH($A64,'Draft Engine'!$Q$3:$Q$232,0) -> 8
A65: =63 -> 63 | B65: =INDEX('Draft Engine'!$A$3:$A$232,$P65) -> RB | C65: =INDEX('Draft Engine'!$F$3:$F$232,$P65) -> 23 | D65: =INDEX('Draft Engine'!$B$3:$B$232,$P65) -> David Montgomery | E65: =INDEX('Draft Engine'!$E$3:$E$232,$P65) -> 77.9102 | F65: =IF($E65>=95,"ELITE",IF($E65>=90,"TIER 1",IF($E65>=85,"TIER 2",IF($E65>=80,"TIER 3",IF($E65>=75,"TIER 4",IF($E65>=70,"TIER 5",IF($E65>=65,"TIER 6","TIER 7"))))))) -> TIER 4 | G65: =INDEX('Draft Engine'!$G$3:$G$232,$P65) -> 257.2 | H65: =INDEX('Draft Engine'!$J$3:$J$232,$P65) -> 18.2 | I65: =INDEX('Draft Engine'!$N$3:$N$232,$P65) -> 70.47036 | J65: =INDEX('Draft Engine'!$R$3:$R$232,$P65) -> 66.4 | K65: =INDEX('Draft Engine'!$S$3:$S$232,$P65) -> 3.4 | L65: =INDEX('Draft Engine'!$T$3:$T$232,$P65) -> A | M65: =INDEX('Draft Engine'!$X$3:$X$232,$P65) -> RATE-ADJUSTED VETERAN | N65: =INDEX('LIVE SOURCE'!$H$3:$H$232,$P65) -> RB2/FLEX; useful weekly but role and receiving volume matter. | O65: =INDEX('LIVE SOURCE'!$J$3:$J$232,$P65) -> Touchdown variance, receiving-role changes and backfield competition are the main downside paths. | P65: =MATCH($A65,'Draft Engine'!$Q$3:$Q$232,0) -> 55
A66: =64 -> 64 | B66: =INDEX('Draft Engine'!$A$3:$A$232,$P66) -> WR | C66: =INDEX('Draft Engine'!$F$3:$F$232,$P66) -> 24 | D66: =INDEX('Draft Engine'!$B$3:$B$232,$P66) -> Davante Adams | E66: =INDEX('Draft Engine'!$E$3:$E$232,$P66) -> 78.065 | F66: =IF($E66>=95,"ELITE",IF($E66>=90,"TIER 1",IF($E66>=85,"TIER 2",IF($E66>=80,"TIER 3",IF($E66>=75,"TIER 4",IF($E66>=70,"TIER 5",IF($E66>=65,"TIER 6","TIER 7"))))))) -> TIER 4 | G66: =INDEX('Draft Engine'!$G$3:$G$232,$P66) -> 257.9 | H66: =INDEX('Draft Engine'!$J$3:$J$232,$P66) -> 18.6 | I66: =INDEX('Draft Engine'!$N$3:$N$232,$P66) -> 70.117083 | J66: =INDEX('Draft Engine'!$R$3:$R$232,$P66) -> 41.5 | K66: =INDEX('Draft Engine'!$S$3:$S$232,$P66) -> -22.5 | L66: =INDEX('Draft Engine'!$T$3:$T$232,$P66) -> C | M66: =INDEX('Draft Engine'!$X$3:$X$232,$P66) -> HISTORY FALLBACK | N66: =INDEX('LIVE SOURCE'!$H$3:$H$232,$P66) -> Strong WR2 with top-12 weekly upside. | O66: =INDEX('LIVE SOURCE'!$J$3:$J$232,$P66) -> Target competition, quarterback efficiency and touchdown regression are the main downside paths. | P66: =MATCH($A66,'Draft Engine'!$Q$3:$Q$232,0) -> 107
A67: =65 -> 65 | B67: =INDEX('Draft Engine'!$A$3:$A$232,$P67) -> RB | C67: =INDEX('Draft Engine'!$F$3:$F$232,$P67) -> 24 | D67: =INDEX('Draft Engine'!$B$3:$B$232,$P67) -> TreVeyon Henderson | E67: =INDEX('Draft Engine'!$E$3:$E$232,$P67) -> 77.8325 | F67: =IF($E67>=95,"ELITE",IF($E67>=90,"TIER 1",IF($E67>=85,"TIER 2",IF($E67>=80,"TIER 3",IF($E67>=75,"TIER 4",IF($E67>=70,"TIER 5",IF($E67>=65,"TIER 6","TIER 7"))))))) -> TIER 4 | G67: =INDEX('Draft Engine'!$G$3:$G$232,$P67) -> 256.9 | H67: =INDEX('Draft Engine'!$J$3:$J$232,$P67) -> 17.9 | I67: =INDEX('Draft Engine'!$N$3:$N$232,$P67) -> 70.01425 | J67: =INDEX('Draft Engine'!$R$3:$R$232,$P67) -> 55.4 | K67: =INDEX('Draft Engine'!$S$3:$S$232,$P67) -> -9.6 | L67: =INDEX('Draft Engine'!$T$3:$T$232,$P67) -> A | M67: =INDEX('Draft Engine'!$X$3:$X$232,$P67) -> RATE-ADJUSTED VETERAN | N67: =INDEX('LIVE SOURCE'!$H$3:$H$232,$P67) -> RB2/FLEX; useful weekly but role and receiving volume matter. | O67: =INDEX('LIVE SOURCE'!$J$3:$J$232,$P67) -> Touchdown variance, receiving-role changes and backfield competition are the main downside paths. | P67: =MATCH($A67,'Draft Engine'!$Q$3:$Q$232,0) -> 56
A68: =66 -> 66 | B68: =INDEX('Draft Engine'!$A$3:$A$232,$P68) -> TE | C68: =INDEX('Draft Engine'!$F$3:$F$232,$P68) -> 10 | D68: =INDEX('Draft Engine'!$B$3:$B$232,$P68) -> Sam LaPorta | E68: =INDEX('Draft Engine'!$E$3:$E$232,$P68) -> 82.8653 | F68: =IF($E68>=95,"ELITE",IF($E68>=90,"TIER 1",IF($E68>=85,"TIER 2",IF($E68>=80,"TIER 3",IF($E68>=75,"TIER 4",IF($E68>=70,"TIER 5",IF($E68>=65,"TIER 6","TIER 7"))))))) -> TIER 3 | G68: =INDEX('Draft Engine'!$G$3:$G$232,$P68) -> 190 | H68: =INDEX('Draft Engine'!$J$3:$J$232,$P68) -> 10.3 | I68: =INDEX('Draft Engine'!$N$3:$N$232,$P68) -> 69.699146 | J68: =INDEX('Draft Engine'!$R$3:$R$232,$P68) -> 88.7 | K68: =INDEX('Draft Engine'!$S$3:$S$232,$P68) -> 22.7 | L68: =INDEX('Draft Engine'!$T$3:$T$232,$P68) -> B | M68: =INDEX('Draft Engine'!$X$3:$X$232,$P68) -> RATE-ADJUSTED VETERAN | N68: =INDEX('LIVE SOURCE'!$H$3:$H$232,$P68) -> Low-end TE1; startable but replacement options remain close. | O68: =INDEX('LIVE SOURCE'!$J$3:$J$232,$P68) -> Availability/sample risk is elevated after only 9 games; talent is not being punished as heavily as durability. | P68: =MATCH($A68,'Draft Engine'!$Q$3:$Q$232,0) -> 168
A69: =67 -> 67 | B69: =INDEX('Draft Engine'!$A$3:$A$232,$P69) -> QB | C69: =INDEX('Draft Engine'!$F$3:$F$232,$P69) -> 9 | D69: =INDEX('Draft Engine'!$B$3:$B$232,$P69) -> Joe Burrow | E69: =INDEX('Draft Engine'!$E$3:$E$232,$P69) -> 85.5913 | F69: =IF($E69>=95,"ELITE",IF($E69>=90,"TIER 1",IF($E69>=85,"TIER 2",IF($E69>=80,"TIER 3",IF($E69>=75,"TIER 4",IF($E69>=70,"TIER 5",IF($E69>=65,"TIER 6","TIER 7"))))))) -> TIER 2 | G69: =INDEX('Draft Engine'!$G$3:$G$232,$P69) -> 355.2 | H69: =INDEX('Draft Engine'!$J$3:$J$232,$P69) -> 4.1 | I69: =INDEX('Draft Engine'!$N$3:$N$232,$P69) -> 68.659369 | J69: =INDEX('Draft Engine'!$R$3:$R$232,$P69) -> 57.3 | K69: =INDEX('Draft Engine'!$S$3:$S$232,$P69) -> -9.7 | L69: =INDEX('Draft Engine'!$T$3:$T$232,$P69) -> B | M69: =INDEX('Draft Engine'!$X$3:$X$232,$P69) -> RATE-ADJUSTED VETERAN | N69: =INDEX('LIVE SOURCE'!$H$3:$H$232,$P69) -> Low-end QB1/high-end QB2 in a 10-team league; startable most weeks. | O69: =INDEX('LIVE SOURCE'!$J$3:$J$232,$P69) -> Availability/sample risk is elevated after only 8 games; talent is not being punished as heavily as durability. | P69: =MATCH($A69,'Draft Engine'!$Q$3:$Q$232,0) -> 9
A70: =68 -> 68 | B70: =INDEX('Draft Engine'!$A$3:$A$232,$P70) -> RB | C70: =INDEX('Draft Engine'!$F$3:$F$232,$P70) -> 25 | D70: =INDEX('Draft Engine'!$B$3:$B$232,$P70) -> Jadarian Price | E70: =INDEX('Draft Engine'!$E$3:$E$232,$P70) -> 76.6622 | F70: =IF($E70>=95,"ELITE",IF($E70>=90,"TIER 1",IF($E70>=85,"TIER 2",IF($E70>=80,"TIER 3",IF($E70>=75,"TIER 4",IF($E70>=70,"TIER 5",IF($E70>=65,"TIER 6","TIER 7"))))))) -> TIER 4 | G70: =INDEX('Draft Engine'!$G$3:$G$232,$P70) -> 252 | H70: =INDEX('Draft Engine'!$J$3:$J$232,$P70) -> 13 | I70: =INDEX('Draft Engine'!$N$3:$N$232,$P70) -> 68.12921 | J70: =INDEX('Draft Engine'!$R$3:$R$232,$P70) -> 63 | K70: =INDEX('Draft Engine'!$S$3:$S$232,$P70) -> -5 | L70: =INDEX('Draft Engine'!$T$3:$T$232,$P70) -> B | M70: =INDEX('Draft Engine'!$X$3:$X$232,$P70) -> ROOKIE ENGINE | N70: =INDEX('LIVE SOURCE'!$H$3:$H$232,$P70) -> RB2/FLEX; useful weekly but role and receiving volume matter. | O70: =INDEX('LIVE SOURCE'!$J$3:$J$232,$P70) -> NFL translation and exact weekly role are the main variables; preseason first-team usage can move this rating quickly. | P70: =MATCH($A70,'Draft Engine'!$Q$3:$Q$232,0) -> 57
A71: =69 -> 69 | B71: =INDEX('Draft Engine'!$A$3:$A$232,$P71) -> TE | C71: =INDEX('Draft Engine'!$F$3:$F$232,$P71) -> 11 | D71: =INDEX('Draft Engine'!$B$3:$B$232,$P71) -> Dalton Kincaid | E71: =INDEX('Draft Engine'!$E$3:$E$232,$P71) -> 81.9141 | F71: =IF($E71>=95,"ELITE",IF($E71>=90,"TIER 1",IF($E71>=85,"TIER 2",IF($E71>=80,"TIER 3",IF($E71>=75,"TIER 4",IF($E71>=70,"TIER 5",IF($E71>=65,"TIER 6","TIER 7"))))))) -> TIER 3 | G71: =INDEX('Draft Engine'!$G$3:$G$232,$P71) -> 186.7 | H71: =INDEX('Draft Engine'!$J$3:$J$232,$P71) -> 7 | I71: =INDEX('Draft Engine'!$N$3:$N$232,$P71) -> 67.889678 | J71: =INDEX('Draft Engine'!$R$3:$R$232,$P71) -> 152 | K71: =INDEX('Draft Engine'!$S$3:$S$232,$P71) -> 83 | L71: =INDEX('Draft Engine'!$T$3:$T$232,$P71) -> A | M71: =INDEX('Draft Engine'!$X$3:$X$232,$P71) -> RATE-ADJUSTED VETERAN | N71: =INDEX('LIVE SOURCE'!$H$3:$H$232,$P71) -> Low-end TE1; startable but replacement options remain close. | O71: =INDEX('LIVE SOURCE'!$J$3:$J$232,$P71) -> Route share, target volume and touchdown volatility are the main swing factors. | P71: =MATCH($A71,'Draft Engine'!$Q$3:$Q$232,0) -> 169
A72: =70 -> 70 | B72: =INDEX('Draft Engine'!$A$3:$A$232,$P72) -> WR | C72: =INDEX('Draft Engine'!$F$3:$F$232,$P72) -> 25 | D72: =INDEX('Draft Engine'!$B$3:$B$232,$P72) -> Mike Evans | E72: =INDEX('Draft Engine'!$E$3:$E$232,$P72) -> 76.4775 | F72: =IF($E72>=95,"ELITE",IF($E72>=90,"TIER 1",IF($E72>=85,"TIER 2",IF($E72>=80,"TIER 3",IF($E72>=75,"TIER 4",IF($E72>=70,"TIER 5",IF($E72>=65,"TIER 6","TIER 7"))))))) -> TIER 4 | G72: =INDEX('Draft Engine'!$G$3:$G$232,$P72) -> 251.2 | H72: =INDEX('Draft Engine'!$J$3:$J$232,$P72) -> 11.9 | I72: =INDEX('Draft Engine'!$N$3:$N$232,$P72) -> 67.704625 | J72: =INDEX('Draft Engine'!$R$3:$R$232,$P72) -> 59.4 | K72: =INDEX('Draft Engine'!$S$3:$S$232,$P72) -> -10.6 | L72: =INDEX('Draft Engine'!$T$3:$T$232,$P72) -> C | M72: =INDEX('Draft Engine'!$X$3:$X$232,$P72) -> HISTORY FALLBACK | N72: =INDEX('LIVE SOURCE'!$H$3:$H$232,$P72) -> WR2/FLEX; dependable lineup option with matchup-driven ceiling. | O72: =INDEX('LIVE SOURCE'!$J$3:$J$232,$P72) -> Evidence is thinner than for established veterans, so camp, depth-chart and role news can move the grade materially. | P72: =MATCH($A72,'Draft Engine'!$Q$3:$Q$232,0) -> 112
A73: =71 -> 71 | B73: =INDEX('Draft Engine'!$A$3:$A$232,$P73) -> QB | C73: =INDEX('Draft Engine'!$F$3:$F$232,$P73) -> 10 | D73: =INDEX('Draft Engine'!$B$3:$B$232,$P73) -> Matthew Stafford | E73: =INDEX('Draft Engine'!$E$3:$E$232,$P73) -> 85.4197 | F73: =IF($E73>=95,"ELITE",IF($E73>=90,"TIER 1",IF($E73>=85,"TIER 2",IF($E73>=80,"TIER 3",IF($E73>=75,"TIER 4",IF($E73>=70,"TIER 5",IF($E73>=65,"TIER 6","TIER 7"))))))) -> TIER 2 | G73: =INDEX('Draft Engine'!$G$3:$G$232,$P73) -> 354.4 | H73: =INDEX('Draft Engine'!$J$3:$J$232,$P73) -> 3.3 | I73: =INDEX('Draft Engine'!$N$3:$N$232,$P73) -> 67.651758 | J73: =INDEX('Draft Engine'!$R$3:$R$232,$P73) -> 83.7 | K73: =INDEX('Draft Engine'!$S$3:$S$232,$P73) -> 12.7 | L73: =INDEX('Draft Engine'!$T$3:$T$232,$P73) -> A | M73: =INDEX('Draft Engine'!$X$3:$X$232,$P73) -> RATE-ADJUSTED VETERAN | N73: =INDEX('LIVE SOURCE'!$H$3:$H$232,$P73) -> Low-end QB1/high-end QB2 in a 10-team league; startable most weeks. | O73: =INDEX('LIVE SOURCE'!$J$3:$J$232,$P73) -> Passing-TD efficiency, rushing volume and supporting-cast health are the main swing factors. | P73: =MATCH($A73,'Draft Engine'!$Q$3:$Q$232,0) -> 10
A74: =72 -> 72 | B74: =INDEX('Draft Engine'!$A$3:$A$232,$P74) -> WR | C74: =INDEX('Draft Engine'!$F$3:$F$232,$P74) -> 26 | D74: =INDEX('Draft Engine'!$B$3:$B$232,$P74) -> Jordyn Tyson | E74: =INDEX('Draft Engine'!$E$3:$E$232,$P74) -> 76.22 | F74: =IF($E74>=95,"ELITE",IF($E74>=90,"TIER 1",IF($E74>=85,"TIER 2",IF($E74>=80,"TIER 3",IF($E74>=75,"TIER 4",IF($E74>=70,"TIER 5",IF($E74>=65,"TIER 6","TIER 7"))))))) -> TIER 4 | G74: =INDEX('Draft Engine'!$G$3:$G$232,$P74) -> 250.1 | H74: =INDEX('Draft Engine'!$J$3:$J$232,$P74) -> 10.8 | I74: =INDEX('Draft Engine'!$N$3:$N$232,$P74) -> 67.031667 | J74: =INDEX('Draft Engine'!$R$3:$R$232,$P74) -> 87.1 | K74: =INDEX('Draft Engine'!$S$3:$S$232,$P74) -> 15.1 | L74: =INDEX('Draft Engine'!$T$3:$T$232,$P74) -> C | M74: =INDEX('Draft Engine'!$X$3:$X$232,$P74) -> HISTORY FALLBACK | N74: =INDEX('LIVE SOURCE'!$H$3:$H$232,$P74) -> WR2/FLEX; dependable lineup option with matchup-driven ceiling. | O74: =INDEX('LIVE SOURCE'!$J$3:$J$232,$P74) -> NFL translation and exact weekly role are the main variables; preseason first-team usage can move this rating quickly. | P74: =MATCH($A74,'Draft Engine'!$Q$3:$Q$232,0) -> 119
A75: =73 -> 73 | B75: =INDEX('Draft Engine'!$A$3:$A$232,$P75) -> RB | C75: =INDEX('Draft Engine'!$F$3:$F$232,$P75) -> 26 | D75: =INDEX('Draft Engine'!$B$3:$B$232,$P75) -> Jaylen Warren | E75: =INDEX('Draft Engine'!$E$3:$E$232,$P75) -> 76.0918 | F75: =IF($E75>=95,"ELITE",IF($E75>=90,"TIER 1",IF($E75>=85,"TIER 2",IF($E75>=80,"TIER 3",IF($E75>=75,"TIER 4",IF($E75>=70,"TIER 5",IF($E75>=65,"TIER 6","TIER 7"))))))) -> TIER 4 | G75: =INDEX('Draft Engine'!$G$3:$G$232,$P75) -> 249.6 | H75: =INDEX('Draft Engine'!$J$3:$J$232,$P75) -> 10.6 | I75: =INDEX('Draft Engine'!$N$3:$N$232,$P75) -> 67.024115 | J75: =INDEX('Draft Engine'!$R$3:$R$232,$P75) -> 68.8 | K75: =INDEX('Draft Engine'!$S$3:$S$232,$P75) -> -4.2 | L75: =INDEX('Draft Engine'!$T$3:$T$232,$P75) -> A | M75: =INDEX('Draft Engine'!$X$3:$X$232,$P75) -> RATE-ADJUSTED VETERAN | N75: =INDEX('LIVE SOURCE'!$H$3:$H$232,$P75) -> RB2/FLEX; useful weekly but role and receiving volume matter. | O75: =INDEX('LIVE SOURCE'!$J$3:$J$232,$P75) -> Touchdown variance, receiving-role changes and backfield competition are the main downside paths. | P75: =MATCH($A75,'Draft Engine'!$Q$3:$Q$232,0) -> 58
A76: =74 -> 74 | B76: =INDEX('Draft Engine'!$A$3:$A$232,$P76) -> TE | C76: =INDEX('Draft Engine'!$F$3:$F$232,$P76) -> 12 | D76: =INDEX('Draft Engine'!$B$3:$B$232,$P76) -> Travis Kelce | E76: =INDEX('Draft Engine'!$E$3:$E$232,$P76) -> 81.7478 | F76: =IF($E76>=95,"ELITE",IF($E76>=90,"TIER 1",IF($E76>=85,"TIER 2",IF($E76>=80,"TIER 3",IF($E76>=75,"TIER 4",IF($E76>=70,"TIER 5",IF($E76>=65,"TIER 6","TIER 7"))))))) -> TIER 3 | G76: =INDEX('Draft Engine'!$G$3:$G$232,$P76) -> 186.1 | H76: =INDEX('Draft Engine'!$J$3:$J$232,$P76) -> 6.4 | I76: =INDEX('Draft Engine'!$N$3:$N$232,$P76) -> 66.997905 | J76: =INDEX('Draft Engine'!$R$3:$R$232,$P76) -> 108.7 | K76: =INDEX('Draft Engine'!$S$3:$S$232,$P76) -> 34.7 | L76: =INDEX('Draft Engine'!$T$3:$T$232,$P76) -> A | M76: =INDEX('Draft Engine'!$X$3:$X$232,$P76) -> RATE-ADJUSTED VETERAN | N76: =INDEX('LIVE SOURCE'!$H$3:$H$232,$P76) -> Low-end TE1; startable but replacement options remain close. | O76: =INDEX('LIVE SOURCE'!$J$3:$J$232,$P76) -> Route share, target volume and touchdown volatility are the main swing factors. | P76: =MATCH($A76,'Draft Engine'!$Q$3:$Q$232,0) -> 170
A77: =75 -> 75 | B77: =INDEX('Draft Engine'!$A$3:$A$232,$P77) -> QB | C77: =INDEX('Draft Engine'!$F$3:$F$232,$P77) -> 11 | D77: =INDEX('Draft Engine'!$B$3:$B$232,$P77) -> Bo Nix | E77: =INDEX('Draft Engine'!$E$3:$E$232,$P77) -> 85.2485 | F77: =IF($E77>=95,"ELITE",IF($E77>=90,"TIER 1",IF($E77>=85,"TIER 2",IF($E77>=80,"TIER 3",IF($E77>=75,"TIER 4",IF($E77>=70,"TIER 5",IF($E77>=65,"TIER 6","TIER 7"))))))) -> TIER 2 | G77: =INDEX('Draft Engine'!$G$3:$G$232,$P77) -> 353.6 | H77: =INDEX('Draft Engine'!$J$3:$J$232,$P77) -> 2.5 | I77: =INDEX('Draft Engine'!$N$3:$N$232,$P77) -> 66.644367 | J77: =INDEX('Draft Engine'!$R$3:$R$232,$P77) -> 121.5 | K77: =INDEX('Draft Engine'!$S$3:$S$232,$P77) -> 46.5 | L77: =INDEX('Draft Engine'!$T$3:$T$232,$P77) -> A | M77: =INDEX('Draft Engine'!$X$3:$X$232,$P77) -> RATE-ADJUSTED VETERAN | N77: =INDEX('LIVE SOURCE'!$H$3:$H$232,$P77) -> Low-end QB1/high-end QB2 in a 10-team league; startable most weeks. | O77: =INDEX('LIVE SOURCE'!$J$3:$J$232,$P77) -> Passing-TD efficiency, rushing volume and supporting-cast health are the main swing factors. | P77: =MATCH($A77,'Draft Engine'!$Q$3:$Q$232,0) -> 11
A78: =76 -> 76 | B78: =INDEX('Draft Engine'!$A$3:$A$232,$P78) -> WR | C78: =INDEX('Draft Engine'!$F$3:$F$232,$P78) -> 27 | D78: =INDEX('Draft Engine'!$B$3:$B$232,$P78) -> Jameson Williams | E78: =INDEX('Draft Engine'!$E$3:$E$232,$P78) -> 76.0625 | F78: =IF($E78>=95,"ELITE",IF($E78>=90,"TIER 1",IF($E78>=85,"TIER 2",IF($E78>=80,"TIER 3",IF($E78>=75,"TIER 4",IF($E78>=70,"TIER 5",IF($E78>=65,"TIER 6","TIER 7"))))))) -> TIER 4 | G78: =INDEX('Draft Engine'!$G$3:$G$232,$P78) -> 249.5 | H78: =INDEX('Draft Engine'!$J$3:$J$232,$P78) -> 10.2 | I78: =INDEX('Draft Engine'!$N$3:$N$232,$P78) -> 66.503708 | J78: =INDEX('Draft Engine'!$R$3:$R$232,$P78) -> 45.8 | K78: =INDEX('Draft Engine'!$S$3:$S$232,$P78) -> -30.2 | L78: =INDEX('Draft Engine'!$T$3:$T$232,$P78) -> C | M78: =INDEX('Draft Engine'!$X$3:$X$232,$P78) -> HISTORY FALLBACK | N78: =INDEX('LIVE SOURCE'!$H$3:$H$232,$P78) -> WR2/FLEX; dependable lineup option with matchup-driven ceiling. | O78: =INDEX('LIVE SOURCE'!$J$3:$J$232,$P78) -> Target competition, quarterback efficiency and touchdown regression are the main downside paths. | P78: =MATCH($A78,'Draft Engine'!$Q$3:$Q$232,0) -> 110
A79: =77 -> 77 | B79: =INDEX('Draft Engine'!$A$3:$A$232,$P79) -> RB | C79: =INDEX('Draft Engine'!$F$3:$F$232,$P79) -> 27 | D79: =INDEX('Draft Engine'!$B$3:$B$232,$P79) -> Rico Dowdle | E79: =INDEX('Draft Engine'!$E$3:$E$232,$P79) -> 75.7858 | F79: =IF($E79>=95,"ELITE",IF($E79>=90,"TIER 1",IF($E79>=85,"TIER 2",IF($E79>=80,"TIER 3",IF($E79>=75,"TIER 4",IF($E79>=70,"TIER 5",IF($E79>=65,"TIER 6","TIER 7"))))))) -> TIER 4 | G79: =INDEX('Draft Engine'!$G$3:$G$232,$P79) -> 248.3 | H79: =INDEX('Draft Engine'!$J$3:$J$232,$P79) -> 9.3 | I79: =INDEX('Draft Engine'!$N$3:$N$232,$P79) -> 66.26244 | J79: =INDEX('Draft Engine'!$R$3:$R$232,$P79) -> 64.8 | K79: =INDEX('Draft Engine'!$S$3:$S$232,$P79) -> -12.2 | L79: =INDEX('Draft Engine'!$T$3:$T$232,$P79) -> A | M79: =INDEX('Draft Engine'!$X$3:$X$232,$P79) -> RATE-ADJUSTED VETERAN | N79: =INDEX('LIVE SOURCE'!$H$3:$H$232,$P79) -> RB2/FLEX; useful weekly but role and receiving volume matter. | O79: =INDEX('LIVE SOURCE'!$J$3:$J$232,$P79) -> Touchdown variance, receiving-role changes and backfield competition are the main downside paths. | P79: =MATCH($A79,'Draft Engine'!$Q$3:$Q$232,0) -> 59
A80: =78 -> 78 | B80: =INDEX('Draft Engine'!$A$3:$A$232,$P80) -> QB | C80: =INDEX('Draft Engine'!$F$3:$F$232,$P80) -> 12 | D80: =INDEX('Draft Engine'!$B$3:$B$232,$P80) -> Dak Prescott | E80: =INDEX('Draft Engine'!$E$3:$E$232,$P80) -> 85.1156 | F80: =IF($E80>=95,"ELITE",IF($E80>=90,"TIER 1",IF($E80>=85,"TIER 2",IF($E80>=80,"TIER 3",IF($E80>=75,"TIER 4",IF($E80>=70,"TIER 5",IF($E80>=65,"TIER 6","TIER 7"))))))) -> TIER 2 | G80: =INDEX('Draft Engine'!$G$3:$G$232,$P80) -> 353 | H80: =INDEX('Draft Engine'!$J$3:$J$232,$P80) -> 1.9 | I80: =INDEX('Draft Engine'!$N$3:$N$232,$P80) -> 65.694042 | J80: =INDEX('Draft Engine'!$R$3:$R$232,$P80) -> 65.4 | K80: =INDEX('Draft Engine'!$S$3:$S$232,$P80) -> -12.6 | L80: =INDEX('Draft Engine'!$T$3:$T$232,$P80) -> A | M80: =INDEX('Draft Engine'!$X$3:$X$232,$P80) -> RATE-ADJUSTED VETERAN | N80: =INDEX('LIVE SOURCE'!$H$3:$H$232,$P80) -> Low-end QB1/high-end QB2 in a 10-team league; startable most weeks. | O80: =INDEX('LIVE SOURCE'!$J$3:$J$232,$P80) -> Passing-TD efficiency, rushing volume and supporting-cast health are the main swing factors. | P80: =MATCH($A80,'Draft Engine'!$Q$3:$Q$232,0) -> 12
A81: =79 -> 79 | B81: =INDEX('Draft Engine'!$A$3:$A$232,$P81) -> WR | C81: =INDEX('Draft Engine'!$F$3:$F$232,$P81) -> 28 | D81: =INDEX('Draft Engine'!$B$3:$B$232,$P81) -> Michael Pittman Jr. | E81: =INDEX('Draft Engine'!$E$3:$E$232,$P81) -> 75.55 | F81: =IF($E81>=95,"ELITE",IF($E81>=90,"TIER 1",IF($E81>=85,"TIER 2",IF($E81>=80,"TIER 3",IF($E81>=75,"TIER 4",IF($E81>=70,"TIER 5",IF($E81>=65,"TIER 6","TIER 7"))))))) -> TIER 4 | G81: =INDEX('Draft Engine'!$G$3:$G$232,$P81) -> 247.3 | H81: =INDEX('Draft Engine'!$J$3:$J$232,$P81) -> 8 | I81: =INDEX('Draft Engine'!$N$3:$N$232,$P81) -> 65.4925 | J81: =INDEX('Draft Engine'!$R$3:$R$232,$P81) -> 72.2 | K81: =INDEX('Draft Engine'!$S$3:$S$232,$P81) -> -6.8 | L81: =INDEX('Draft Engine'!$T$3:$T$232,$P81) -> C | M81: =INDEX('Draft Engine'!$X$3:$X$232,$P81) -> HISTORY FALLBACK | N81: =INDEX('LIVE SOURCE'!$H$3:$H$232,$P81) -> WR2/FLEX; dependable lineup option with matchup-driven ceiling. | O81: =INDEX('LIVE SOURCE'!$J$3:$J$232,$P81) -> Target competition, quarterback efficiency and touchdown regression are the main downside paths. | P81: =MATCH($A81,'Draft Engine'!$Q$3:$Q$232,0) -> 120
A82: =80 -> 80 | B82: =INDEX('Draft Engine'!$A$3:$A$232,$P82) -> WR | C82: =INDEX('Draft Engine'!$F$3:$F$232,$P82) -> 29 | D82: =INDEX('Draft Engine'!$B$3:$B$232,$P82) -> DJ Moore | E82: =INDEX('Draft Engine'!$E$3:$E$232,$P82) -> 75.48 | F82: =IF($E82>=95,"ELITE",IF($E82>=90,"TIER 1",IF($E82>=85,"TIER 2",IF($E82>=80,"TIER 3",IF($E82>=75,"TIER 4",IF($E82>=70,"TIER 5",IF($E82>=65,"TIER 6","TIER 7"))))))) -> TIER 4 | G82: =INDEX('Draft Engine'!$G$3:$G$232,$P82) -> 247 | H82: =INDEX('Draft Engine'!$J$3:$J$232,$P82) -> 7.7 | I82: =INDEX('Draft Engine'!$N$3:$N$232,$P82) -> 65.066667 | J82: =INDEX('Draft Engine'!$R$3:$R$232,$P82) -> 52.9 | K82: =INDEX('Draft Engine'!$S$3:$S$232,$P82) -> -27.1 | L82: =INDEX('Draft Engine'!$T$3:$T$232,$P82) -> C | M82: =INDEX('Draft Engine'!$X$3:$X$232,$P82) -> HISTORY FALLBACK | N82: =INDEX('LIVE SOURCE'!$H$3:$H$232,$P82) -> WR2/FLEX; dependable lineup option with matchup-driven ceiling. | O82: =INDEX('LIVE SOURCE'!$J$3:$J$232,$P82) -> Target competition, quarterback efficiency and touchdown regression are the main downside paths. | P82: =MATCH($A82,'Draft Engine'!$Q$3:$Q$232,0) -> 109
A83: =81 -> 81 | B83: =INDEX('Draft Engine'!$A$3:$A$232,$P83) -> RB | C83: =INDEX('Draft Engine'!$F$3:$F$232,$P83) -> 28 | D83: =INDEX('Draft Engine'!$B$3:$B$232,$P83) -> Tony Pollard | E83: =INDEX('Draft Engine'!$E$3:$E$232,$P83) -> 75.0986 | F83: =IF($E83>=95,"ELITE",IF($E83>=90,"TIER 1",IF($E83>=85,"TIER 2",IF($E83>=80,"TIER 3",IF($E83>=75,"TIER 4",IF($E83>=70,"TIER 5",IF($E83>=65,"TIER 6","TIER 7"))))))) -> TIER 4 | G83: =INDEX('Draft Engine'!$G$3:$G$232,$P83) -> 245.4 | H83: =INDEX('Draft Engine'!$J$3:$J$232,$P83) -> 6.4 | I83: =INDEX('Draft Engine'!$N$3:$N$232,$P83) -> 65.003105 | J83: =INDEX('Draft Engine'!$R$3:$R$232,$P83) -> 65.5 | K83: =INDEX('Draft Engine'!$S$3:$S$232,$P83) -> -15.5 | L83: =INDEX('Draft Engine'!$T$3:$T$232,$P83) -> A | M83: =INDEX('Draft Engine'!$X$3:$X$232,$P83) -> RATE-ADJUSTED VETERAN | N83: =INDEX('LIVE SOURCE'!$H$3:$H$232,$P83) -> RB2/FLEX; useful weekly but role and receiving volume matter. | O83: =INDEX('LIVE SOURCE'!$J$3:$J$232,$P83) -> Touchdown variance, receiving-role changes and backfield competition are the main downside paths. | P83: =MATCH($A83,'Draft Engine'!$Q$3:$Q$232,0) -> 60
A84: =82 -> 82 | B84: =INDEX('Draft Engine'!$A$3:$A$232,$P84) -> QB | C84: =INDEX('Draft Engine'!$F$3:$F$232,$P84) -> 13 | D84: =INDEX('Draft Engine'!$B$3:$B$232,$P84) -> Trevor Lawrence | E84: =INDEX('Draft Engine'!$E$3:$E$232,$P84) -> 84.6921 | F84: =IF($E84>=95,"ELITE",IF($E84>=90,"TIER 1",IF($E84>=85,"TIER 2",IF($E84>=80,"TIER 3",IF($E84>=75,"TIER 4",IF($E84>=70,"TIER 5",IF($E84>=65,"TIER 6","TIER 7"))))))) -> TIER 3 | G84: =INDEX('Draft Engine'!$G$3:$G$232,$P84) -> 351.1 | H84: =INDEX('Draft Engine'!$J$3:$J$232,$P84) -> 0 | I84: =INDEX('Draft Engine'!$N$3:$N$232,$P84) -> 64.349886 | J84: =INDEX('Draft Engine'!$R$3:$R$232,$P84) -> 89.6 | K84: =INDEX('Draft Engine'!$S$3:$S$232,$P84) -> 7.6 | L84: =INDEX('Draft Engine'!$T$3:$T$232,$P84) -> A | M84: =INDEX('Draft Engine'!$X$3:$X$232,$P84) -> RATE-ADJUSTED VETERAN | N84: =INDEX('LIVE SOURCE'!$H$3:$H$232,$P84) -> QB2/streaming tier; useful when matchup and supporting cast line up. | O84: =INDEX('LIVE SOURCE'!$J$3:$J$232,$P84) -> Passing-TD efficiency, rushing volume and supporting-cast health are the main swing factors. | P84: =MATCH($A84,'Draft Engine'!$Q$3:$Q$232,0) -> 13
A85: =83 -> 83 | B85: =INDEX('Draft Engine'!$A$3:$A$232,$P85) -> TE | C85: =INDEX('Draft Engine'!$F$3:$F$232,$P85) -> 13 | D85: =INDEX('Draft Engine'!$B$3:$B$232,$P85) -> Dallas Goedert | E85: =INDEX('Draft Engine'!$E$3:$E$232,$P85) -> 79.9181 | F85: =IF($E85>=95,"ELITE",IF($E85>=90,"TIER 1",IF($E85>=85,"TIER 2",IF($E85>=80,"TIER 3",IF($E85>=75,"TIER 4",IF($E85>=70,"TIER 5",IF($E85>=65,"TIER 6","TIER 7"))))))) -> TIER 4 | G85: =INDEX('Draft Engine'!$G$3:$G$232,$P85) -> 179.7 | H85: =INDEX('Draft Engine'!$J$3:$J$232,$P85) -> 0 | I85: =INDEX('Draft Engine'!$N$3:$N$232,$P85) -> 64.147263 | J85: =INDEX('Draft Engine'!$R$3:$R$232,$P85) -> 103.9 | K85: =INDEX('Draft Engine'!$S$3:$S$232,$P85) -> 20.9 | L85: =INDEX('Draft Engine'!$T$3:$T$232,$P85) -> A | M85: =INDEX('Draft Engine'!$X$3:$X$232,$P85) -> RATE-ADJUSTED VETERAN | N85: =INDEX('LIVE SOURCE'!$H$3:$H$232,$P85) -> Streaming/TE2 range; touchdown and route volume drive usefulness. | O85: =INDEX('LIVE SOURCE'!$J$3:$J$232,$P85) -> Route share, target volume and touchdown volatility are the main swing factors. | P85: =MATCH($A85,'Draft Engine'!$Q$3:$Q$232,0) -> 171
A86: =84 -> 84 | B86: =INDEX('Draft Engine'!$A$3:$A$232,$P86) -> RB | C86: =INDEX('Draft Engine'!$F$3:$F$232,$P86) -> 29 | D86: =INDEX('Draft Engine'!$B$3:$B$232,$P86) -> Rhamondre Stevenson | E86: =INDEX('Draft Engine'!$E$3:$E$232,$P86) -> 74.5881 | F86: =IF($E86>=95,"ELITE",IF($E86>=90,"TIER 1",IF($E86>=85,"TIER 2",IF($E86>=80,"TIER 3",IF($E86>=75,"TIER 4",IF($E86>=70,"TIER 5",IF($E86>=65,"TIER 6","TIER 7"))))))) -> TIER 5 | G86: =INDEX('Draft Engine'!$G$3:$G$232,$P86) -> 243.3 | H86: =INDEX('Draft Engine'!$J$3:$J$232,$P86) -> 4.3 | I86: =INDEX('Draft Engine'!$N$3:$N$232,$P86) -> 63.984955 | J86: =INDEX('Draft Engine'!$R$3:$R$232,$P86) -> 72.3 | K86: =INDEX('Draft Engine'!$S$3:$S$232,$P86) -> -11.7 | L86: =INDEX('Draft Engine'!$T$3:$T$232,$P86) -> A | M86: =INDEX('Draft Engine'!$X$3:$X$232,$P86) -> RATE-ADJUSTED VETERAN | N86: =INDEX('LIVE SOURCE'!$H$3:$H$232,$P86) -> RB2/FLEX; useful weekly but role and receiving volume matter. | O86: =INDEX('LIVE SOURCE'!$J$3:$J$232,$P86) -> Touchdown variance, receiving-role changes and backfield competition are the main downside paths. | P86: =MATCH($A86,'Draft Engine'!$Q$3:$Q$232,0) -> 61
A87: =85 -> 85 | B87: =INDEX('Draft Engine'!$A$3:$A$232,$P87) -> WR | C87: =INDEX('Draft Engine'!$F$3:$F$232,$P87) -> 30 | D87: =INDEX('Draft Engine'!$B$3:$B$232,$P87) -> Jakobi Meyers | E87: =INDEX('Draft Engine'!$E$3:$E$232,$P87) -> 74.88 | F87: =IF($E87>=95,"ELITE",IF($E87>=90,"TIER 1",IF($E87>=85,"TIER 2",IF($E87>=80,"TIER 3",IF($E87>=75,"TIER 4",IF($E87>=70,"TIER 5",IF($E87>=65,"TIER 6","TIER 7"))))))) -> TIER 5 | G87: =INDEX('Draft Engine'!$G$3:$G$232,$P87) -> 244.5 | H87: =INDEX('Draft Engine'!$J$3:$J$232,$P87) -> 5.2 | I87: =INDEX('Draft Engine'!$N$3:$N$232,$P87) -> 63.953333 | J87: =INDEX('Draft Engine'!$R$3:$R$232,$P87) -> 75.6 | K87: =INDEX('Draft Engine'!$S$3:$S$232,$P87) -> -9.4 | L87: =INDEX('Draft Engine'!$T$3:$T$232,$P87) -> C | M87: =INDEX('Draft Engine'!$X$3:$X$232,$P87) -> HISTORY FALLBACK | N87: =INDEX('LIVE SOURCE'!$H$3:$H$232,$P87) -> WR2/FLEX; dependable lineup option with matchup-driven ceiling. | O87: =INDEX('LIVE SOURCE'!$J$3:$J$232,$P87) -> Target competition, quarterback efficiency and touchdown regression are the main downside paths. | P87: =MATCH($A87,'Draft Engine'!$Q$3:$Q$232,0) -> 121
A88: =86 -> 86 | B88: =INDEX('Draft Engine'!$A$3:$A$232,$P88) -> RB | C88: =INDEX('Draft Engine'!$F$3:$F$232,$P88) -> 30 | D88: =INDEX('Draft Engine'!$B$3:$B$232,$P88) -> Kenneth Gainwell | E88: =INDEX('Draft Engine'!$E$3:$E$232,$P88) -> 74.5049 | F88: =IF($E88>=95,"ELITE",IF($E88>=90,"TIER 1",IF($E88>=85,"TIER 2",IF($E88>=80,"TIER 3",IF($E88>=75,"TIER 4",IF($E88>=70,"TIER 5",IF($E88>=65,"TIER 6","TIER 7"))))))) -> TIER 5 | G88: =INDEX('Draft Engine'!$G$3:$G$232,$P88) -> 242.9 | H88: =INDEX('Draft Engine'!$J$3:$J$232,$P88) -> 3.9 | I88: =INDEX('Draft Engine'!$N$3:$N$232,$P88) -> 63.50782 | J88: =INDEX('Draft Engine'!$R$3:$R$232,$P88) -> 123.8 | K88: =INDEX('Draft Engine'!$S$3:$S$232,$P88) -> 37.8 | L88: =INDEX('Draft Engine'!$T$3:$T$232,$P88) -> A | M88: =INDEX('Draft Engine'!$X$3:$X$232,$P88) -> RATE-ADJUSTED VETERAN | N88: =INDEX('LIVE SOURCE'!$H$3:$H$232,$P88) -> RB2/FLEX; useful weekly but role and receiving volume matter. | O88: =INDEX('LIVE SOURCE'!$J$3:$J$232,$P88) -> Touchdown variance, receiving-role changes and backfield competition are the main downside paths. | P88: =MATCH($A88,'Draft Engine'!$Q$3:$Q$232,0) -> 62
A89: =87 -> 87 | B89: =INDEX('Draft Engine'!$A$3:$A$232,$P89) -> RB | C89: =INDEX('Draft Engine'!$F$3:$F$232,$P89) -> 31 | D89: =INDEX('Draft Engine'!$B$3:$B$232,$P89) -> Bhayshul Tuten | E89: =INDEX('Draft Engine'!$E$3:$E$232,$P89) -> 74.4677 | F89: =IF($E89>=95,"ELITE",IF($E89>=90,"TIER 1",IF($E89>=85,"TIER 2",IF($E89>=80,"TIER 3",IF($E89>=75,"TIER 4",IF($E89>=70,"TIER 5",IF($E89>=65,"TIER 6","TIER 7"))))))) -> TIER 5 | G89: =INDEX('Draft Engine'!$G$3:$G$232,$P89) -> 242.8 | H89: =INDEX('Draft Engine'!$J$3:$J$232,$P89) -> 3.8 | I89: =INDEX('Draft Engine'!$N$3:$N$232,$P89) -> 63.109985 | J89: =INDEX('Draft Engine'!$R$3:$R$232,$P89) -> 52.3 | K89: =INDEX('Draft Engine'!$S$3:$S$232,$P89) -> -34.7 | L89: =INDEX('Draft Engine'!$T$3:$T$232,$P89) -> A | M89: =INDEX('Draft Engine'!$X$3:$X$232,$P89) -> RATE-ADJUSTED VETERAN | N89: =INDEX('LIVE SOURCE'!$H$3:$H$232,$P89) -> FLEX/bench depth with upside if workload grows. | O89: =INDEX('LIVE SOURCE'!$J$3:$J$232,$P89) -> Touchdown variance, receiving-role changes and backfield competition are the main downside paths. | P89: =MATCH($A89,'Draft Engine'!$Q$3:$Q$232,0) -> 63
A90: =88 -> 88 | B90: =INDEX('Draft Engine'!$A$3:$A$232,$P90) -> WR | C90: =INDEX('Draft Engine'!$F$3:$F$232,$P90) -> 31 | D90: =INDEX('Draft Engine'!$B$3:$B$232,$P90) -> Jordan Addison | E90: =INDEX('Draft Engine'!$E$3:$E$232,$P90) -> 74.21 | F90: =IF($E90>=95,"ELITE",IF($E90>=90,"TIER 1",IF($E90>=85,"TIER 2",IF($E90>=80,"TIER 3",IF($E90>=75,"TIER 4",IF($E90>=70,"TIER 5",IF($E90>=65,"TIER 6","TIER 7"))))))) -> TIER 5 | G90: =INDEX('Draft Engine'!$G$3:$G$232,$P90) -> 241.7 | H90: =INDEX('Draft Engine'!$J$3:$J$232,$P90) -> 2.4 | I90: =INDEX('Draft Engine'!$N$3:$N$232,$P90) -> 62.7475 | J90: =INDEX('Draft Engine'!$R$3:$R$232,$P90) -> 103.3 | K90: =INDEX('Draft Engine'!$S$3:$S$232,$P90) -> 15.3 | L90: =INDEX('Draft Engine'!$T$3:$T$232,$P90) -> C | M90: =INDEX('Draft Engine'!$X$3:$X$232,$P90) -> HISTORY FALLBACK | N90: =INDEX('LIVE SOURCE'!$H$3:$H$232,$P90) -> WR2/FLEX; dependable lineup option with matchup-driven ceiling. | O90: =INDEX('LIVE SOURCE'!$J$3:$J$232,$P90) -> Target competition, quarterback efficiency and touchdown regression are the main downside paths. | P90: =MATCH($A90,'Draft Engine'!$Q$3:$Q$232,0) -> 122
A91: =89 -> 89 | B91: =INDEX('Draft Engine'!$A$3:$A$232,$P91) -> TE | C91: =INDEX('Draft Engine'!$F$3:$F$232,$P91) -> 14 | D91: =INDEX('Draft Engine'!$B$3:$B$232,$P91) -> Mark Andrews | E91: =INDEX('Draft Engine'!$E$3:$E$232,$P91) -> 79.0654 | F91: =IF($E91>=95,"ELITE",IF($E91>=90,"TIER 1",IF($E91>=85,"TIER 2",IF($E91>=80,"TIER 3",IF($E91>=75,"TIER 4",IF($E91>=70,"TIER 5",IF($E91>=65,"TIER 6","TIER 7"))))))) -> TIER 4 | G91: =INDEX('Draft Engine'!$G$3:$G$232,$P91) -> 176.7 | H91: =INDEX('Draft Engine'!$J$3:$J$232,$P91) -> -3 | I91: =INDEX('Draft Engine'!$N$3:$N$232,$P91) -> 62.44597 | J91: =INDEX('Draft Engine'!$R$3:$R$232,$P91) -> 145 | K91: =INDEX('Draft Engine'!$S$3:$S$232,$P91) -> 56 | L91: =INDEX('Draft Engine'!$T$3:$T$232,$P91) -> A | M91: =INDEX('Draft Engine'!$X$3:$X$232,$P91) -> RATE-ADJUSTED VETERAN | N91: =INDEX('LIVE SOURCE'!$H$3:$H$232,$P91) -> Streaming/TE2 range; touchdown and route volume drive usefulness. | O91: =INDEX('LIVE SOURCE'!$J$3:$J$232,$P91) -> Route share, target volume and touchdown volatility are the main swing factors. | P91: =MATCH($A91,'Draft Engine'!$Q$3:$Q$232,0) -> 172
A92: =90 -> 90 | B92: =INDEX('Draft Engine'!$A$3:$A$232,$P92) -> QB | C92: =INDEX('Draft Engine'!$F$3:$F$232,$P92) -> 14 | D92: =INDEX('Draft Engine'!$B$3:$B$232,$P92) -> Brock Purdy | E92: =INDEX('Draft Engine'!$E$3:$E$232,$P92) -> 83.8386 | F92: =IF($E92>=95,"ELITE",IF($E92>=90,"TIER 1",IF($E92>=85,"TIER 2",IF($E92>=80,"TIER 3",IF($E92>=75,"TIER 4",IF($E92>=70,"TIER 5",IF($E92>=65,"TIER 6","TIER 7"))))))) -> TIER 3 | G92: =INDEX('Draft Engine'!$G$3:$G$232,$P92) -> 347.3 | H92: =INDEX('Draft Engine'!$J$3:$J$232,$P92) -> -3.8 | I92: =INDEX('Draft Engine'!$N$3:$N$232,$P92) -> 62.42723 | J92: =INDEX('Draft Engine'!$R$3:$R$232,$P92) -> 75.7 | K92: =INDEX('Draft Engine'!$S$3:$S$232,$P92) -> -14.3 | L92: =INDEX('Draft Engine'!$T$3:$T$232,$P92) -> B | M92: =INDEX('Draft Engine'!$X$3:$X$232,$P92) -> RATE-ADJUSTED VETERAN | N92: =INDEX('LIVE SOURCE'!$H$3:$H$232,$P92) -> QB2/streaming tier; useful when matchup and supporting cast line up. | O92: =INDEX('LIVE SOURCE'!$J$3:$J$232,$P92) -> Availability/sample risk is elevated after only 9 games; talent is not being punished as heavily as durability. | P92: =MATCH($A92,'Draft Engine'!$Q$3:$Q$232,0) -> 14
A93: =91 -> 91 | B93: =INDEX('Draft Engine'!$A$3:$A$232,$P93) -> WR | C93: =INDEX('Draft Engine'!$F$3:$F$232,$P93) -> 32 | D93: =INDEX('Draft Engine'!$B$3:$B$232,$P93) -> Christian Watson | E93: =INDEX('Draft Engine'!$E$3:$E$232,$P93) -> 73.8925 | F93: =IF($E93>=95,"ELITE",IF($E93>=90,"TIER 1",IF($E93>=85,"TIER 2",IF($E93>=80,"TIER 3",IF($E93>=75,"TIER 4",IF($E93>=70,"TIER 5",IF($E93>=65,"TIER 6","TIER 7"))))))) -> TIER 5 | G93: =INDEX('Draft Engine'!$G$3:$G$232,$P93) -> 240.3 | H93: =INDEX('Draft Engine'!$J$3:$J$232,$P93) -> 1 | I93: =INDEX('Draft Engine'!$N$3:$N$232,$P93) -> 61.987542 | J93: =INDEX('Draft Engine'!$R$3:$R$232,$P93) -> 70.9 | K93: =INDEX('Draft Engine'!$S$3:$S$232,$P93) -> -20.1 | L93: =INDEX('Draft Engine'!$T$3:$T$232,$P93) -> C | M93: =INDEX('Draft Engine'!$X$3:$X$232,$P93) -> HISTORY FALLBACK | N93: =INDEX('LIVE SOURCE'!$H$3:$H$232,$P93) -> WR2/FLEX; dependable lineup option with matchup-driven ceiling. | O93: =INDEX('LIVE SOURCE'!$J$3:$J$232,$P93) -> Target competition, quarterback efficiency and touchdown regression are the main downside paths. | P93: =MATCH($A93,'Draft Engine'!$Q$3:$Q$232,0) -> 114
A94: =92 -> 92 | B94: =INDEX('Draft Engine'!$A$3:$A$232,$P94) -> RB | C94: =INDEX('Draft Engine'!$F$3:$F$232,$P94) -> 32 | D94: =INDEX('Draft Engine'!$B$3:$B$232,$P94) -> RJ Harvey | E94: =INDEX('Draft Engine'!$E$3:$E$232,$P94) -> 73.5678 | F94: =IF($E94>=95,"ELITE",IF($E94>=90,"TIER 1",IF($E94>=85,"TIER 2",IF($E94>=80,"TIER 3",IF($E94>=75,"TIER 4",IF($E94>=70,"TIER 5",IF($E94>=65,"TIER 6","TIER 7"))))))) -> TIER 5 | G94: =INDEX('Draft Engine'!$G$3:$G$232,$P94) -> 239 | H94: =INDEX('Draft Engine'!$J$3:$J$232,$P94) -> 0 | I94: =INDEX('Draft Engine'!$N$3:$N$232,$P94) -> 61.571665 | J94: =INDEX('Draft Engine'!$R$3:$R$232,$P94) -> 82.6 | K94: =INDEX('Draft Engine'!$S$3:$S$232,$P94) -> -9.4 | L94: =INDEX('Draft Engine'!$T$3:$T$232,$P94) -> A | M94: =INDEX('Draft Engine'!$X$3:$X$232,$P94) -> RATE-ADJUSTED VETERAN | N94: =INDEX('LIVE SOURCE'!$H$3:$H$232,$P94) -> FLEX/bench depth with upside if workload grows. | O94: =INDEX('LIVE SOURCE'!$J$3:$J$232,$P94) -> Touchdown variance, receiving-role changes and backfield competition are the main downside paths. | P94: =MATCH($A94,'Draft Engine'!$Q$3:$Q$232,0) -> 64
A95: =93 -> 93 | B95: =INDEX('Draft Engine'!$A$3:$A$232,$P95) -> WR | C95: =INDEX('Draft Engine'!$F$3:$F$232,$P95) -> 33 | D95: =INDEX('Draft Engine'!$B$3:$B$232,$P95) -> Rome Odunze | E95: =INDEX('Draft Engine'!$E$3:$E$232,$P95) -> 73.645 | F95: =IF($E95>=95,"ELITE",IF($E95>=90,"TIER 1",IF($E95>=85,"TIER 2",IF($E95>=80,"TIER 3",IF($E95>=75,"TIER 4",IF($E95>=70,"TIER 5",IF($E95>=65,"TIER 6","TIER 7"))))))) -> TIER 5 | G95: =INDEX('Draft Engine'!$G$3:$G$232,$P95) -> 239.3 | H95: =INDEX('Draft Engine'!$J$3:$J$232,$P95) -> 0 | I95: =INDEX('Draft Engine'!$N$3:$N$232,$P95) -> 61.338083 | J95: =INDEX('Draft Engine'!$R$3:$R$232,$P95) -> 49.3 | K95: =INDEX('Draft Engine'!$S$3:$S$232,$P95) -> -43.7 | L95: =INDEX('Draft Engine'!$T$3:$T$232,$P95) -> C | M95: =INDEX('Draft Engine'!$X$3:$X$232,$P95) -> HISTORY FALLBACK | N95: =INDEX('LIVE SOURCE'!$H$3:$H$232,$P95) -> WR2/FLEX; dependable lineup option with matchup-driven ceiling. | O95: =INDEX('LIVE SOURCE'!$J$3:$J$232,$P95) -> Target competition, quarterback efficiency and touchdown regression are the main downside paths. | P95: =MATCH($A95,'Draft Engine'!$Q$3:$Q$232,0) -> 111
A96: =94 -> 94 | B96: =INDEX('Draft Engine'!$A$3:$A$232,$P96) -> TE | C96: =INDEX('Draft Engine'!$F$3:$F$232,$P96) -> 15 | D96: =INDEX('Draft Engine'!$B$3:$B$232,$P96) -> Isaiah Likely | E96: =INDEX('Draft Engine'!$E$3:$E$232,$P96) -> 78.5795 | F96: =IF($E96>=95,"ELITE",IF($E96>=90,"TIER 1",IF($E96>=85,"TIER 2",IF($E96>=80,"TIER 3",IF($E96>=75,"TIER 4",IF($E96>=70,"TIER 5",IF($E96>=65,"TIER 6","TIER 7"))))))) -> TIER 4 | G96: =INDEX('Draft Engine'!$G$3:$G$232,$P96) -> 175 | H96: =INDEX('Draft Engine'!$J$3:$J$232,$P96) -> -4.7 | I96: =INDEX('Draft Engine'!$N$3:$N$232,$P96) -> 61.180417 | J96: =INDEX('Draft Engine'!$R$3:$R$232,$P96) -> 133.1 | K96: =INDEX('Draft Engine'!$S$3:$S$232,$P96) -> 39.1 | L96: =INDEX('Draft Engine'!$T$3:$T$232,$P96) -> A | M96: =INDEX('Draft Engine'!$X$3:$X$232,$P96) -> RATE-ADJUSTED VETERAN | N96: =INDEX('LIVE SOURCE'!$H$3:$H$232,$P96) -> Streaming/TE2 range; touchdown and route volume drive usefulness. | O96: =INDEX('LIVE SOURCE'!$J$3:$J$232,$P96) -> Route share, target volume and touchdown volatility are the main swing factors. | P96: =MATCH($A96,'Draft Engine'!$Q$3:$Q$232,0) -> 173
A97: =95 -> 95 | B97: =INDEX('Draft Engine'!$A$3:$A$232,$P97) -> WR | C97: =INDEX('Draft Engine'!$F$3:$F$232,$P97) -> 34 | D97: =INDEX('Draft Engine'!$B$3:$B$232,$P97) -> Wan'Dale Robinson | E97: =INDEX('Draft Engine'!$E$3:$E$232,$P97) -> 73.54 | F97: =IF($E97>=95,"ELITE",IF($E97>=90,"TIER 1",IF($E97>=85,"TIER 2",IF($E97>=80,"TIER 3",IF($E97>=75,"TIER 4",IF($E97>=70,"TIER 5",IF($E97>=65,"TIER 6","TIER 7"))))))) -> TIER 5 | G97: =INDEX('Draft Engine'!$G$3:$G$232,$P97) -> 238.9 | H97: =INDEX('Draft Engine'!$J$3:$J$232,$P97) -> -0.4 | I97: =INDEX('Draft Engine'!$N$3:$N$232,$P97) -> 60.875 | J97: =INDEX('Draft Engine'!$R$3:$R$232,$P97) -> 71 | K97: =INDEX('Draft Engine'!$S$3:$S$232,$P97) -> -24 | L97: =INDEX('Draft Engine'!$T$3:$T$232,$P97) -> C | M97: =INDEX('Draft Engine'!$X$3:$X$232,$P97) -> HISTORY FALLBACK | N97: =INDEX('LIVE SOURCE'!$H$3:$H$232,$P97) -> WR2/FLEX; dependable lineup option with matchup-driven ceiling. | O97: =INDEX('LIVE SOURCE'!$J$3:$J$232,$P97) -> Target competition, quarterback efficiency and touchdown regression are the main downside paths. | P97: =MATCH($A97,'Draft Engine'!$Q$3:$Q$232,0) -> 123
A98: =96 -> 96 | B98: =INDEX('Draft Engine'!$A$3:$A$232,$P98) -> QB | C98: =INDEX('Draft Engine'!$F$3:$F$232,$P98) -> 15 | D98: =INDEX('Draft Engine'!$B$3:$B$232,$P98) -> Jaxson Dart | E98: =INDEX('Draft Engine'!$E$3:$E$232,$P98) -> 83.0607 | F98: =IF($E98>=95,"ELITE",IF($E98>=90,"TIER 1",IF($E98>=85,"TIER 2",IF($E98>=80,"TIER 3",IF($E98>=75,"TIER 4",IF($E98>=70,"TIER 5",IF($E98>=65,"TIER 6","TIER 7"))))))) -> TIER 3 | G98: =INDEX('Draft Engine'!$G$3:$G$232,$P98) -> 343.8 | H98: =INDEX('Draft Engine'!$J$3:$J$232,$P98) -> -7.3 | I98: =INDEX('Draft Engine'!$N$3:$N$232,$P98) -> 60.600154 | J98: =INDEX('Draft Engine'!$R$3:$R$232,$P98) -> 100.4 | K98: =INDEX('Draft Engine'!$S$3:$S$232,$P98) -> 4.4 | L98: =INDEX('Draft Engine'!$T$3:$T$232,$P98) -> A | M98: =INDEX('Draft Engine'!$X$3:$X$232,$P98) -> RATE-ADJUSTED VETERAN | N98: =INDEX('LIVE SOURCE'!$H$3:$H$232,$P98) -> QB2/streaming tier; useful when matchup and supporting cast line up. | O98: =INDEX('LIVE SOURCE'!$J$3:$J$232,$P98) -> Passing-TD efficiency, rushing volume and supporting-cast health are the main swing factors. | P98: =MATCH($A98,'Draft Engine'!$Q$3:$Q$232,0) -> 15
A99: =97 -> 97 | B99: =INDEX('Draft Engine'!$A$3:$A$232,$P99) -> TE | C99: =INDEX('Draft Engine'!$F$3:$F$232,$P99) -> 16 | D99: =INDEX('Draft Engine'!$B$3:$B$232,$P99) -> Juwan Johnson | E99: =INDEX('Draft Engine'!$E$3:$E$232,$P99) -> 78.3203 | F99: =IF($E99>=95,"ELITE",IF($E99>=90,"TIER 1",IF($E99>=85,"TIER 2",IF($E99>=80,"TIER 3",IF($E99>=75,"TIER 4",IF($E99>=70,"TIER 5",IF($E99>=65,"TIER 6","TIER 7"))))))) -> TIER 4 | G99: =INDEX('Draft Engine'!$G$3:$G$232,$P99) -> 174.1 | H99: =INDEX('Draft Engine'!$J$3:$J$232,$P99) -> -5.6 | I99: =INDEX('Draft Engine'!$N$3:$N$232,$P99) -> 60.18355 | J99: =INDEX('Draft Engine'!$R$3:$R$232,$P99) -> 159.2 | K99: =INDEX('Draft Engine'!$S$3:$S$232,$P99) -> 62.2 | L99: =INDEX('Draft Engine'!$T$3:$T$232,$P99) -> A | M99: =INDEX('Draft Engine'!$X$3:$X$232,$P99) -> RATE-ADJUSTED VETERAN | N99: =INDEX('LIVE SOURCE'!$H$3:$H$232,$P99) -> Streaming/TE2 range; touchdown and route volume drive usefulness. | O99: =INDEX('LIVE SOURCE'!$J$3:$J$232,$P99) -> Route share, target volume and touchdown volatility are the main swing factors. | P99: =MATCH($A99,'Draft Engine'!$Q$3:$Q$232,0) -> 174
A100: =98 -> 98 | B100: =INDEX('Draft Engine'!$A$3:$A$232,$P100) -> RB | C100: =INDEX('Draft Engine'!$F$3:$F$232,$P100) -> 33 | D100: =INDEX('Draft Engine'!$B$3:$B$232,$P100) -> Kyle Monangai | E100: =INDEX('Draft Engine'!$E$3:$E$232,$P100) -> 72.6102 | F100: =IF($E100>=95,"ELITE",IF($E100>=90,"TIER 1",IF($E100>=85,"TIER 2",IF($E100>=80,"TIER 3",IF($E100>=75,"TIER 4",IF($E100>=70,"TIER 5",IF($E100>=65,"TIER 6","TIER 7"))))))) -> TIER 5 | G100: =INDEX('Draft Engine'!$G$3:$G$232,$P100) -> 235 | H100: =INDEX('Draft Engine'!$J$3:$J$232,$P100) -> -4 | I100: =INDEX('Draft Engine'!$N$3:$N$232,$P100) -> 59.96561 | J100: =INDEX('Draft Engine'!$R$3:$R$232,$P100) -> 100.3 | K100: =INDEX('Draft Engine'!$S$3:$S$232,$P100) -> 2.3 | L100: =INDEX('Draft Engine'!$T$3:$T$232,$P100) -> A | M100: =INDEX('Draft Engine'!$X$3:$X$232,$P100) -> RATE-ADJUSTED VETERAN | N100: =INDEX('LIVE SOURCE'!$H$3:$H$232,$P100) -> FLEX/bench depth with upside if workload grows. | O100: =INDEX('LIVE SOURCE'!$J$3:$J$232,$P100) -> Touchdown variance, receiving-role changes and backfield competition are the main downside paths. | P100: =MATCH($A100,'Draft Engine'!$Q$3:$Q$232,0) -> 65
...

Sheet Top 200
A1: 2026 Overall Top 200: pure formula view, updates with every adjustment.
A2: Overall | B2: Pos | C2: Pos Rank | D2: Player | E2: Draft Score | F2: Adj Rating | G2: Proj Points | H2: VORP | I2: Scarcity | J2: Market ADP | K2: Draft Edge | L2: Floor | M2: Ceiling | N2: Confidence | O2: Src
A3: =1 -> 1 | B3: =INDEX('Draft Engine'!$A$3:$A$232,$O3) -> WR | C3: =INDEX('Draft Engine'!$F$3:$F$232,$O3) -> 1 | D3: =INDEX('Draft Engine'!$B$3:$B$232,$O3) -> Puka Nacua | E3: =INDEX('Draft Engine'!$N$3:$N$232,$O3) -> 99.167245 | F3: =INDEX('Draft Engine'!$E$3:$E$232,$O3) -> 98.4859 | G3: =INDEX('Draft Engine'!$G$3:$G$232,$O3) -> 343.6 | H3: =INDEX('Draft Engine'!$J$3:$J$232,$O3) -> 104.3 | I3: =INDEX('Draft Engine'!$L$3:$L$232,$O3) -> 100 | J3: =INDEX('Draft Engine'!$R$3:$R$232,$O3) -> 2.9 | K3: =INDEX('Draft Engine'!$S$3:$S$232,$O3) -> 1.9 | L3: =INDEX('Draft Engine'!$U$3:$U$232,$O3) -> 92.4859 | M3: =INDEX('Draft Engine'!$W$3:$W$232,$O3) -> 100 | N3: =INDEX('Draft Engine'!$T$3:$T$232,$O3) -> A | O3: =MATCH($A3,'Draft Engine'!$Q$3:$Q$232,0) -> 86
A4: =2 -> 2 | B4: =INDEX('Draft Engine'!$A$3:$A$232,$O4) -> RB | C4: =INDEX('Draft Engine'!$F$3:$F$232,$O4) -> 1 | D4: =INDEX('Draft Engine'!$B$3:$B$232,$O4) -> Bijan Robinson | E4: =INDEX('Draft Engine'!$N$3:$N$232,$O4) -> 98.552015 | F4: =INDEX('Draft Engine'!$E$3:$E$232,$O4) -> 97.3673 | G4: =INDEX('Draft Engine'!$G$3:$G$232,$O4) -> 338.9 | H4: =INDEX('Draft Engine'!$J$3:$J$232,$O4) -> 99.9 | I4: =INDEX('Draft Engine'!$L$3:$L$232,$O4) -> 100 | J4: =INDEX('Draft Engine'!$R$3:$R$232,$O4) -> 1.8 | K4: =INDEX('Draft Engine'!$S$3:$S$232,$O4) -> -0.2 | L4: =INDEX('Draft Engine'!$U$3:$U$232,$O4) -> 91.3673 | M4: =INDEX('Draft Engine'!$W$3:$W$232,$O4) -> 100 | N4: =INDEX('Draft Engine'!$T$3:$T$232,$O4) -> A | O4: =MATCH($A4,'Draft Engine'!$Q$3:$Q$232,0) -> 33
A5: =3 -> 3 | B5: =INDEX('Draft Engine'!$A$3:$A$232,$O5) -> WR | C5: =INDEX('Draft Engine'!$F$3:$F$232,$O5) -> 2 | D5: =INDEX('Draft Engine'!$B$3:$B$232,$O5) -> Ja'Marr Chase | E5: =INDEX('Draft Engine'!$N$3:$N$232,$O5) -> 98.202765 | F5: =INDEX('Draft Engine'!$E$3:$E$232,$O5) -> 96.7323 | G5: =INDEX('Draft Engine'!$G$3:$G$232,$O5) -> 336.3 | H5: =INDEX('Draft Engine'!$J$3:$J$232,$O5) -> 97 | I5: =INDEX('Draft Engine'!$L$3:$L$232,$O5) -> 100 | J5: =INDEX('Draft Engine'!$R$3:$R$232,$O5) -> 3.9 | K5: =INDEX('Draft Engine'!$S$3:$S$232,$O5) -> 0.9 | L5: =INDEX('Draft Engine'!$U$3:$U$232,$O5) -> 90.7323 | M5: =INDEX('Draft Engine'!$W$3:$W$232,$O5) -> 100 | N5: =INDEX('Draft Engine'!$T$3:$T$232,$O5) -> A | O5: =MATCH($A5,'Draft Engine'!$Q$3:$Q$232,0) -> 85
A6: =4 -> 4 | B6: =INDEX('Draft Engine'!$A$3:$A$232,$O6) -> RB | C6: =INDEX('Draft Engine'!$F$3:$F$232,$O6) -> 2 | D6: =INDEX('Draft Engine'!$B$3:$B$232,$O6) -> Jahmyr Gibbs | E6: =INDEX('Draft Engine'!$N$3:$N$232,$O6) -> 97.982765 | F6: =INDEX('Draft Engine'!$E$3:$E$232,$O6) -> 96.3323 | G6: =INDEX('Draft Engine'!$G$3:$G$232,$O6) -> 334.6 | H6: =INDEX('Draft Engine'!$J$3:$J$232,$O6) -> 95.6 | I6: =INDEX('Draft Engine'!$L$3:$L$232,$O6) -> 100 | J6: =INDEX('Draft Engine'!$R$3:$R$232,$O6) -> 1.8 | K6: =INDEX('Draft Engine'!$S$3:$S$232,$O6) -> -2.2 | L6: =INDEX('Draft Engine'!$U$3:$U$232,$O6) -> 90.3323 | M6: =INDEX('Draft Engine'!$W$3:$W$232,$O6) -> 100 | N6: =INDEX('Draft Engine'!$T$3:$T$232,$O6) -> A | O6: =MATCH($A6,'Draft Engine'!$Q$3:$Q$232,0) -> 34
A7: =5 -> 5 | B7: =INDEX('Draft Engine'!$A$3:$A$232,$O7) -> RB | C7: =INDEX('Draft Engine'!$F$3:$F$232,$O7) -> 3 | D7: =INDEX('Draft Engine'!$B$3:$B$232,$O7) -> Christian McCaffrey | E7: =INDEX('Draft Engine'!$N$3:$N$232,$O7) -> 96.834585 | F7: =INDEX('Draft Engine'!$E$3:$E$232,$O7) -> 94.2447 | G7: =INDEX('Draft Engine'!$G$3:$G$232,$O7) -> 325.8 | H7: =INDEX('Draft Engine'!$J$3:$J$232,$O7) -> 86.8 | I7: =INDEX('Draft Engine'!$L$3:$L$232,$O7) -> 100 | J7: =INDEX('Draft Engine'!$R$3:$R$232,$O7) -> 5.8 | K7: =INDEX('Draft Engine'!$S$3:$S$232,$O7) -> 0.8 | L7: =INDEX('Draft Engine'!$U$3:$U$232,$O7) -> 88.2447 | M7: =INDEX('Draft Engine'!$W$3:$W$232,$O7) -> 100 | N7: =INDEX('Draft Engine'!$T$3:$T$232,$O7) -> A | O7: =MATCH($A7,'Draft Engine'!$Q$3:$Q$232,0) -> 35
A8: =6 -> 6 | B8: =INDEX('Draft Engine'!$A$3:$A$232,$O8) -> WR | C8: =INDEX('Draft Engine'!$F$3:$F$232,$O8) -> 3 | D8: =INDEX('Draft Engine'!$B$3:$B$232,$O8) -> Jaxon Smith-Njigba | E8: =INDEX('Draft Engine'!$N$3:$N$232,$O8) -> 96.743945 | F8: =INDEX('Draft Engine'!$E$3:$E$232,$O8) -> 94.0799 | G8: =INDEX('Draft Engine'!$G$3:$G$232,$O8) -> 325.1 | H8: =INDEX('Draft Engine'!$J$3:$J$232,$O8) -> 85.8 | I8: =INDEX('Draft Engine'!$L$3:$L$232,$O8) -> 100 | J8: =INDEX('Draft Engine'!$R$3:$R$232,$O8) -> 5.7 | K8: =INDEX('Draft Engine'!$S$3:$S$232,$O8) -> -0.3 | L8: =INDEX('Draft Engine'!$U$3:$U$232,$O8) -> 88.0799 | M8: =INDEX('Draft Engine'!$W$3:$W$232,$O8) -> 100 | N8: =INDEX('Draft Engine'!$T$3:$T$232,$O8) -> A | O8: =MATCH($A8,'Draft Engine'!$Q$3:$Q$232,0) -> 87
A9: =7 -> 7 | B9: =INDEX('Draft Engine'!$A$3:$A$232,$O9) -> WR | C9: =INDEX('Draft Engine'!$F$3:$F$232,$O9) -> 4 | D9: =INDEX('Draft Engine'!$B$3:$B$232,$O9) -> Amon-Ra St. Brown | E9: =INDEX('Draft Engine'!$N$3:$N$232,$O9) -> 96.127145 | F9: =INDEX('Draft Engine'!$E$3:$E$232,$O9) -> 93.2639 | G9: =INDEX('Draft Engine'!$G$3:$G$232,$O9) -> 321.7 | H9: =INDEX('Draft Engine'!$J$3:$J$232,$O9) -> 82.4 | I9: =INDEX('Draft Engine'!$L$3:$L$232,$O9) -> 100 | J9: =INDEX('Draft Engine'!$R$3:$R$232,$O9) -> 7 | K9: =INDEX('Draft Engine'!$S$3:$S$232,$O9) -> 0 | L9: =INDEX('Draft Engine'!$U$3:$U$232,$O9) -> 87.2639 | M9: =INDEX('Draft Engine'!$W$3:$W$232,$O9) -> 99.2639 | N9: =INDEX('Draft Engine'!$T$3:$T$232,$O9) -> A | O9: =MATCH($A9,'Draft Engine'!$Q$3:$Q$232,0) -> 88
A10: =8 -> 8 | B10: =INDEX('Draft Engine'!$A$3:$A$232,$O10) -> RB | C10: =INDEX('Draft Engine'!$F$3:$F$232,$O10) -> 4 | D10: =INDEX('Draft Engine'!$B$3:$B$232,$O10) -> Jonathan Taylor | E10: =INDEX('Draft Engine'!$N$3:$N$232,$O10) -> 94.72085 | F10: =INDEX('Draft Engine'!$E$3:$E$232,$O10) -> 92.147 | G10: =INDEX('Draft Engine'!$G$3:$G$232,$O10) -> 317 | H10: =INDEX('Draft Engine'!$J$3:$J$232,$O10) -> 78 | I10: =INDEX('Draft Engine'!$L$3:$L$232,$O10) -> 100 | J10: =INDEX('Draft Engine'!$R$3:$R$232,$O10) -> 7.4 | K10: =INDEX('Draft Engine'!$S$3:$S$232,$O10) -> -0.6 | L10: =INDEX('Draft Engine'!$U$3:$U$232,$O10) -> 86.147 | M10: =INDEX('Draft Engine'!$W$3:$W$232,$O10) -> 98.147 | N10: =INDEX('Draft Engine'!$T$3:$T$232,$O10) -> A | O10: =MATCH($A10,'Draft Engine'!$Q$3:$Q$232,0) -> 36
A11: =9 -> 9 | B11: =INDEX('Draft Engine'!$A$3:$A$232,$O11) -> WR | C11: =INDEX('Draft Engine'!$F$3:$F$232,$O11) -> 5 | D11: =INDEX('Draft Engine'!$B$3:$B$232,$O11) -> Nico Collins | E11: =INDEX('Draft Engine'!$N$3:$N$232,$O11) -> 93.820875 | F11: =INDEX('Draft Engine'!$E$3:$E$232,$O11) -> 91.4925 | G11: =INDEX('Draft Engine'!$G$3:$G$232,$O11) -> 314.3 | H11: =INDEX('Draft Engine'!$J$3:$J$232,$O11) -> 75 | I11: =INDEX('Draft Engine'!$L$3:$L$232,$O11) -> 100 | J11: =INDEX('Draft Engine'!$R$3:$R$232,$O11) -> 23.8 | K11: =INDEX('Draft Engine'!$S$3:$S$232,$O11) -> 14.8 | L11: =INDEX('Draft Engine'!$U$3:$U$232,$O11) -> 82.4925 | M11: =INDEX('Draft Engine'!$W$3:$W$232,$O11) -> 100 | N11: =INDEX('Draft Engine'!$T$3:$T$232,$O11) -> B | O11: =MATCH($A11,'Draft Engine'!$Q$3:$Q$232,0) -> 94
A12: =10 -> 10 | B12: =INDEX('Draft Engine'!$A$3:$A$232,$O12) -> TE | C12: =INDEX('Draft Engine'!$F$3:$F$232,$O12) -> 1 | D12: =INDEX('Draft Engine'!$B$3:$B$232,$O12) -> Trey McBride | E12: =INDEX('Draft Engine'!$N$3:$N$232,$O12) -> 93.487405 | F12: =INDEX('Draft Engine'!$E$3:$E$232,$O12) -> 97.7371 | G12: =INDEX('Draft Engine'!$G$3:$G$232,$O12) -> 242.1 | H12: =INDEX('Draft Engine'!$J$3:$J$232,$O12) -> 62.4 | I12: =INDEX('Draft Engine'!$L$3:$L$232,$O12) -> 90 | J12: =INDEX('Draft Engine'!$R$3:$R$232,$O12) -> 35.7 | K12: =INDEX('Draft Engine'!$S$3:$S$232,$O12) -> 25.7 | L12: =INDEX('Draft Engine'!$U$3:$U$232,$O12) -> 91.7371 | M12: =INDEX('Draft Engine'!$W$3:$W$232,$O12) -> 100 | N12: =INDEX('Draft Engine'!$T$3:$T$232,$O12) -> A | O12: =MATCH($A12,'Draft Engine'!$Q$3:$Q$232,0) -> 159
A13: =11 -> 11 | B13: =INDEX('Draft Engine'!$A$3:$A$232,$O13) -> RB | C13: =INDEX('Draft Engine'!$F$3:$F$232,$O13) -> 5 | D13: =INDEX('Draft Engine'!$B$3:$B$232,$O13) -> Jeremiyah Love | E13: =INDEX('Draft Engine'!$N$3:$N$232,$O13) -> 93.044245 | F13: =INDEX('Draft Engine'!$E$3:$E$232,$O13) -> 90.8659 | G13: =INDEX('Draft Engine'!$G$3:$G$232,$O13) -> 311.6 | H13: =INDEX('Draft Engine'!$J$3:$J$232,$O13) -> 72.6 | I13: =INDEX('Draft Engine'!$L$3:$L$232,$O13) -> 100 | J13: =INDEX('Draft Engine'!$R$3:$R$232,$O13) -> 26.2 | K13: =INDEX('Draft Engine'!$S$3:$S$232,$O13) -> 15.2 | L13: =INDEX('Draft Engine'!$U$3:$U$232,$O13) -> 81.8659 | M13: =INDEX('Draft Engine'!$W$3:$W$232,$O13) -> 99.8659 | N13: =INDEX('Draft Engine'!$T$3:$T$232,$O13) -> B | O13: =MATCH($A13,'Draft Engine'!$Q$3:$Q$232,0) -> 37
A14: =12 -> 12 | B14: =INDEX('Draft Engine'!$A$3:$A$232,$O14) -> QB | C14: =INDEX('Draft Engine'!$F$3:$F$232,$O14) -> 1 | D14: =INDEX('Draft Engine'!$B$3:$B$232,$O14) -> Josh Allen | E14: =INDEX('Draft Engine'!$N$3:$N$232,$O14) -> 90.744445 | F14: =INDEX('Draft Engine'!$E$3:$E$232,$O14) -> 97.3099 | G14: =INDEX('Draft Engine'!$G$3:$G$232,$O14) -> 407.9 | H14: =INDEX('Draft Engine'!$J$3:$J$232,$O14) -> 56.8 | I14: =INDEX('Draft Engine'!$L$3:$L$232,$O14) -> 100 | J14: =INDEX('Draft Engine'!$R$3:$R$232,$O14) -> 26.6 | K14: =INDEX('Draft Engine'!$S$3:$S$232,$O14) -> 14.6 | L14: =INDEX('Draft Engine'!$U$3:$U$232,$O14) -> 91.3099 | M14: =INDEX('Draft Engine'!$W$3:$W$232,$O14) -> 100 | N14: =INDEX('Draft Engine'!$T$3:$T$232,$O14) -> A | O14: =MATCH($A14,'Draft Engine'!$Q$3:$Q$232,0) -> 1
A15: =13 -> 13 | B15: =INDEX('Draft Engine'!$A$3:$A$232,$O15) -> WR | C15: =INDEX('Draft Engine'!$F$3:$F$232,$O15) -> 6 | D15: =INDEX('Draft Engine'!$B$3:$B$232,$O15) -> Chris Olave | E15: =INDEX('Draft Engine'!$N$3:$N$232,$O15) -> 90.270458 | F15: =INDEX('Draft Engine'!$E$3:$E$232,$O15) -> 88.9075 | G15: =INDEX('Draft Engine'!$G$3:$G$232,$O15) -> 303.4 | H15: =INDEX('Draft Engine'!$J$3:$J$232,$O15) -> 64.1 | I15: =INDEX('Draft Engine'!$L$3:$L$232,$O15) -> 98.888889 | J15: =INDEX('Draft Engine'!$R$3:$R$232,$O15) -> 20.4 | K15: =INDEX('Draft Engine'!$S$3:$S$232,$O15) -> 7.4 | L15: =INDEX('Draft Engine'!$U$3:$U$232,$O15) -> 79.9075 | M15: =INDEX('Draft Engine'!$W$3:$W$232,$O15) -> 97.9075 | N15: =INDEX('Draft Engine'!$T$3:$T$232,$O15) -> B | O15: =MATCH($A15,'Draft Engine'!$Q$3:$Q$232,0) -> 96
A16: =14 -> 14 | B16: =INDEX('Draft Engine'!$A$3:$A$232,$O16) -> RB | C16: =INDEX('Draft Engine'!$F$3:$F$232,$O16) -> 6 | D16: =INDEX('Draft Engine'!$B$3:$B$232,$O16) -> Omarion Hampton | E16: =INDEX('Draft Engine'!$N$3:$N$232,$O16) -> 90.147155 | F16: =INDEX('Draft Engine'!$E$3:$E$232,$O16) -> 88.6421 | G16: =INDEX('Draft Engine'!$G$3:$G$232,$O16) -> 302.3 | H16: =INDEX('Draft Engine'!$J$3:$J$232,$O16) -> 63.3 | I16: =INDEX('Draft Engine'!$L$3:$L$232,$O16) -> 100 | J16: =INDEX('Draft Engine'!$R$3:$R$232,$O16) -> 19.6 | K16: =INDEX('Draft Engine'!$S$3:$S$232,$O16) -> 5.6 | L16: =INDEX('Draft Engine'!$U$3:$U$232,$O16) -> 79.6421 | M16: =INDEX('Draft Engine'!$W$3:$W$232,$O16) -> 97.6421 | N16: =INDEX('Draft Engine'!$T$3:$T$232,$O16) -> B | O16: =MATCH($A16,'Draft Engine'!$Q$3:$Q$232,0) -> 38
A17: =15 -> 15 | B17: =INDEX('Draft Engine'!$A$3:$A$232,$O17) -> TE | C17: =INDEX('Draft Engine'!$F$3:$F$232,$O17) -> 2 | D17: =INDEX('Draft Engine'!$B$3:$B$232,$O17) -> Brock Bowers | E17: =INDEX('Draft Engine'!$N$3:$N$232,$O17) -> 89.426222 | F17: =INDEX('Draft Engine'!$E$3:$E$232,$O17) -> 94.8846 | G17: =INDEX('Draft Engine'!$G$3:$G$232,$O17) -> 232.1 | H17: =INDEX('Draft Engine'!$J$3:$J$232,$O17) -> 52.4 | I17: =INDEX('Draft Engine'!$L$3:$L$232,$O17) -> 85.384615 | J17: =INDEX('Draft Engine'!$R$3:$R$232,$O17) -> 41.1 | K17: =INDEX('Draft Engine'!$S$3:$S$232,$O17) -> 26.1 | L17: =INDEX('Draft Engine'!$U$3:$U$232,$O17) -> 88.8846 | M17: =INDEX('Draft Engine'!$W$3:$W$232,$O17) -> 100 | N17: =INDEX('Draft Engine'!$T$3:$T$232,$O17) -> A | O17: =MATCH($A17,'Draft Engine'!$Q$3:$Q$232,0) -> 160
A18: =16 -> 16 | B18: =INDEX('Draft Engine'!$A$3:$A$232,$O18) -> RB | C18: =INDEX('Draft Engine'!$F$3:$F$232,$O18) -> 7 | D18: =INDEX('Draft Engine'!$B$3:$B$232,$O18) -> De'Von Achane | E18: =INDEX('Draft Engine'!$N$3:$N$232,$O18) -> 89.2412 | F18: =INDEX('Draft Engine'!$E$3:$E$232,$O18) -> 87.944 | G18: =INDEX('Draft Engine'!$G$3:$G$232,$O18) -> 299.4 | H18: =INDEX('Draft Engine'!$J$3:$J$232,$O18) -> 60.4 | I18: =INDEX('Draft Engine'!$L$3:$L$232,$O18) -> 100 | J18: =INDEX('Draft Engine'!$R$3:$R$232,$O18) -> 10.1 | K18: =INDEX('Draft Engine'!$S$3:$S$232,$O18) -> -5.9 | L18: =INDEX('Draft Engine'!$U$3:$U$232,$O18) -> 81.944 | M18: =INDEX('Draft Engine'!$W$3:$W$232,$O18) -> 93.944 | N18: =INDEX('Draft Engine'!$T$3:$T$232,$O18) -> A | O18: =MATCH($A18,'Draft Engine'!$Q$3:$Q$232,0) -> 39
A19: =17 -> 17 | B19: =INDEX('Draft Engine'!$A$3:$A$232,$O19) -> RB | C19: =INDEX('Draft Engine'!$F$3:$F$232,$O19) -> 8 | D19: =INDEX('Draft Engine'!$B$3:$B$232,$O19) -> Kenneth Walker III | E19: =INDEX('Draft Engine'!$N$3:$N$232,$O19) -> 88.113305 | F19: =INDEX('Draft Engine'!$E$3:$E$232,$O19) -> 87.2926 | G19: =INDEX('Draft Engine'!$G$3:$G$232,$O19) -> 296.6 | H19: =INDEX('Draft Engine'!$J$3:$J$232,$O19) -> 57.6 | I19: =INDEX('Draft Engine'!$L$3:$L$232,$O19) -> 98.229167 | J19: =INDEX('Draft Engine'!$R$3:$R$232,$O19) -> 26.2 | K19: =INDEX('Draft Engine'!$S$3:$S$232,$O19) -> 9.2 | L19: =INDEX('Draft Engine'!$U$3:$U$232,$O19) -> 81.2926 | M19: =INDEX('Draft Engine'!$W$3:$W$232,$O19) -> 93.2926 | N19: =INDEX('Draft Engine'!$T$3:$T$232,$O19) -> A | O19: =MATCH($A19,'Draft Engine'!$Q$3:$Q$232,0) -> 40
A20: =18 -> 18 | B20: =INDEX('Draft Engine'!$A$3:$A$232,$O20) -> WR | C20: =INDEX('Draft Engine'!$F$3:$F$232,$O20) -> 7 | D20: =INDEX('Draft Engine'!$B$3:$B$232,$O20) -> Drake London | E20: =INDEX('Draft Engine'!$N$3:$N$232,$O20) -> 88.10683 | F20: =INDEX('Draft Engine'!$E$3:$E$232,$O20) -> 87.5106 | G20: =INDEX('Draft Engine'!$G$3:$G$232,$O20) -> 297.5 | H20: =INDEX('Draft Engine'!$J$3:$J$232,$O20) -> 58.2 | I20: =INDEX('Draft Engine'!$L$3:$L$232,$O20) -> 96.666667 | J20: =INDEX('Draft Engine'!$R$3:$R$232,$O20) -> 10.2 | K20: =INDEX('Draft Engine'!$S$3:$S$232,$O20) -> -7.8 | L20: =INDEX('Draft Engine'!$U$3:$U$232,$O20) -> 81.5106 | M20: =INDEX('Draft Engine'!$W$3:$W$232,$O20) -> 93.5106 | N20: =INDEX('Draft Engine'!$T$3:$T$232,$O20) -> A | O20: =MATCH($A20,'Draft Engine'!$Q$3:$Q$232,0) -> 93
A21: =19 -> 19 | B21: =INDEX('Draft Engine'!$A$3:$A$232,$O21) -> WR | C21: =INDEX('Draft Engine'!$F$3:$F$232,$O21) -> 8 | D21: =INDEX('Draft Engine'!$B$3:$B$232,$O21) -> DeVonta Smith | E21: =INDEX('Draft Engine'!$N$3:$N$232,$O21) -> 87.742792 | F21: =INDEX('Draft Engine'!$E$3:$E$232,$O21) -> 87.4875 | G21: =INDEX('Draft Engine'!$G$3:$G$232,$O21) -> 297.4 | H21: =INDEX('Draft Engine'!$J$3:$J$232,$O21) -> 58.1 | I21: =INDEX('Draft Engine'!$L$3:$L$232,$O21) -> 94.444444 | J21: =INDEX('Draft Engine'!$R$3:$R$232,$O21) -> 29.5 | K21: =INDEX('Draft Engine'!$S$3:$S$232,$O21) -> 10.5 | L21: =INDEX('Draft Engine'!$U$3:$U$232,$O21) -> 78.4875 | M21: =INDEX('Draft Engine'!$W$3:$W$232,$O21) -> 96.4875 | N21: =INDEX('Draft Engine'!$T$3:$T$232,$O21) -> B | O21: =MATCH($A21,'Draft Engine'!$Q$3:$Q$232,0) -> 100
A22: =20 -> 20 | B22: =INDEX('Draft Engine'!$A$3:$A$232,$O22) -> RB | C22: =INDEX('Draft Engine'!$F$3:$F$232,$O22) -> 9 | D22: =INDEX('Draft Engine'!$B$3:$B$232,$O22) -> James Cook III | E22: =INDEX('Draft Engine'!$N$3:$N$232,$O22) -> 87.4449 | F22: =INDEX('Draft Engine'!$E$3:$E$232,$O22) -> 87.058 | G22: =INDEX('Draft Engine'!$G$3:$G$232,$O22) -> 295.6 | H22: =INDEX('Draft Engine'!$J$3:$J$232,$O22) -> 56.6 | I22: =INDEX('Draft Engine'!$L$3:$L$232,$O22) -> 95.833333 | J22: =INDEX('Draft Engine'!$R$3:$R$232,$O22) -> 14.9 | K22: =INDEX('Draft Engine'!$S$3:$S$232,$O22) -> -5.1 | L22: =INDEX('Draft Engine'!$U$3:$U$232,$O22) -> 81.058 | M22: =INDEX('Draft Engine'!$W$3:$W$232,$O22) -> 93.058 | N22: =INDEX('Draft Engine'!$T$3:$T$232,$O22) -> A | O22: =MATCH($A22,'Draft Engine'!$Q$3:$Q$232,0) -> 41
A23: =21 -> 21 | B23: =INDEX('Draft Engine'!$A$3:$A$232,$O23) -> WR | C23: =INDEX('Draft Engine'!$F$3:$F$232,$O23) -> 9 | D23: =INDEX('Draft Engine'!$B$3:$B$232,$O23) -> Zay Flowers | E23: =INDEX('Draft Engine'!$N$3:$N$232,$O23) -> 86.220833 | F23: =INDEX('Draft Engine'!$E$3:$E$232,$O23) -> 86.57 | G23: =INDEX('Draft Engine'!$G$3:$G$232,$O23) -> 293.6 | H23: =INDEX('Draft Engine'!$J$3:$J$232,$O23) -> 54.3 | I23: =INDEX('Draft Engine'!$L$3:$L$232,$O23) -> 92.222222 | J23: =INDEX('Draft Engine'!$R$3:$R$232,$O23) -> 26.4 | K23: =INDEX('Draft Engine'!$S$3:$S$232,$O23) -> 5.4 | L23: =INDEX('Draft Engine'!$U$3:$U$232,$O23) -> 77.57 | M23: =INDEX('Draft Engine'!$W$3:$W$232,$O23) -> 95.57 | N23: =INDEX('Draft Engine'!$T$3:$T$232,$O23) -> B | O23: =MATCH($A23,'Draft Engine'!$Q$3:$Q$232,0) -> 101
A24: =22 -> 22 | B24: =INDEX('Draft Engine'!$A$3:$A$232,$O24) -> RB | C24: =INDEX('Draft Engine'!$F$3:$F$232,$O24) -> 10 | D24: =INDEX('Draft Engine'!$B$3:$B$232,$O24) -> Kyren Williams | E24: =INDEX('Draft Engine'!$N$3:$N$232,$O24) -> 85.647355 | F24: =INDEX('Draft Engine'!$E$3:$E$232,$O24) -> 85.9486 | G24: =INDEX('Draft Engine'!$G$3:$G$232,$O24) -> 291 | H24: =INDEX('Draft Engine'!$J$3:$J$232,$O24) -> 52 | I24: =INDEX('Draft Engine'!$L$3:$L$232,$O24) -> 93.4375 | J24: =INDEX('Draft Engine'!$R$3:$R$232,$O24) -> 33.1 | K24: =INDEX('Draft Engine'!$S$3:$S$232,$O24) -> 11.1 | L24: =INDEX('Draft Engine'!$U$3:$U$232,$O24) -> 79.9486 | M24: =INDEX('Draft Engine'!$W$3:$W$232,$O24) -> 91.9486 | N24: =INDEX('Draft Engine'!$T$3:$T$232,$O24) -> A | O24: =MATCH($A24,'Draft Engine'!$Q$3:$Q$232,0) -> 42
A25: =23 -> 23 | B25: =INDEX('Draft Engine'!$A$3:$A$232,$O25) -> WR | C25: =INDEX('Draft Engine'!$F$3:$F$232,$O25) -> 10 | D25: =INDEX('Draft Engine'!$B$3:$B$232,$O25) -> Garrett Wilson | E25: =INDEX('Draft Engine'!$N$3:$N$232,$O25) -> 85.35325 | F25: =INDEX('Draft Engine'!$E$3:$E$232,$O25) -> 86.155 | G25: =INDEX('Draft Engine'!$G$3:$G$232,$O25) -> 291.9 | H25: =INDEX('Draft Engine'!$J$3:$J$232,$O25) -> 52.6 | I25: =INDEX('Draft Engine'!$L$3:$L$232,$O25) -> 90 | J25: =INDEX('Draft Engine'!$R$3:$R$232,$O25) -> 29 | K25: =INDEX('Draft Engine'!$S$3:$S$232,$O25) -> 6 | L25: =INDEX('Draft Engine'!$U$3:$U$232,$O25) -> 77.155 | M25: =INDEX('Draft Engine'!$W$3:$W$232,$O25) -> 95.155 | N25: =INDEX('Draft Engine'!$T$3:$T$232,$O25) -> B | O25: =MATCH($A25,'Draft Engine'!$Q$3:$Q$232,0) -> 99
A26: =24 -> 24 | B26: =INDEX('Draft Engine'!$A$3:$A$232,$O26) -> RB | C26: =INDEX('Draft Engine'!$F$3:$F$232,$O26) -> 11 | D26: =INDEX('Draft Engine'!$B$3:$B$232,$O26) -> Breece Hall | E26: =INDEX('Draft Engine'!$N$3:$N$232,$O26) -> 85.22261 | F26: =INDEX('Draft Engine'!$E$3:$E$232,$O26) -> 85.8952 | G26: =INDEX('Draft Engine'!$G$3:$G$232,$O26) -> 290.8 | H26: =INDEX('Draft Engine'!$J$3:$J$232,$O26) -> 51.8 | I26: =INDEX('Draft Engine'!$L$3:$L$232,$O26) -> 91.041667 | J26: =INDEX('Draft Engine'!$R$3:$R$232,$O26) -> 27 | K26: =INDEX('Draft Engine'!$S$3:$S$232,$O26) -> 3 | L26: =INDEX('Draft Engine'!$U$3:$U$232,$O26) -> 79.8952 | M26: =INDEX('Draft Engine'!$W$3:$W$232,$O26) -> 91.8952 | N26: =INDEX('Draft Engine'!$T$3:$T$232,$O26) -> A | O26: =MATCH($A26,'Draft Engine'!$Q$3:$Q$232,0) -> 43
A27: =25 -> 25 | B27: =INDEX('Draft Engine'!$A$3:$A$232,$O27) -> RB | C27: =INDEX('Draft Engine'!$F$3:$F$232,$O27) -> 12 | D27: =INDEX('Draft Engine'!$B$3:$B$232,$O27) -> Ashton Jeanty | E27: =INDEX('Draft Engine'!$N$3:$N$232,$O27) -> 84.78069 | F27: =INDEX('Draft Engine'!$E$3:$E$232,$O27) -> 85.8433 | G27: =INDEX('Draft Engine'!$G$3:$G$232,$O27) -> 290.5 | H27: =INDEX('Draft Engine'!$J$3:$J$232,$O27) -> 51.5 | I27: =INDEX('Draft Engine'!$L$3:$L$232,$O27) -> 88.645833 | J27: =INDEX('Draft Engine'!$R$3:$R$232,$O27) -> 13.8 | K27: =INDEX('Draft Engine'!$S$3:$S$232,$O27) -> -11.2 | L27: =INDEX('Draft Engine'!$U$3:$U$232,$O27) -> 79.8433 | M27: =INDEX('Draft Engine'!$W$3:$W$232,$O27) -> 91.8433 | N27: =INDEX('Draft Engine'!$T$3:$T$232,$O27) -> A | O27: =MATCH($A27,'Draft Engine'!$Q$3:$Q$232,0) -> 44
A28: =26 -> 26 | B28: =INDEX('Draft Engine'!$A$3:$A$232,$O28) -> WR | C28: =INDEX('Draft Engine'!$F$3:$F$232,$O28) -> 11 | D28: =INDEX('Draft Engine'!$B$3:$B$232,$O28) -> CeeDee Lamb | E28: =INDEX('Draft Engine'!$N$3:$N$232,$O28) -> 84.469097 | F28: =INDEX('Draft Engine'!$E$3:$E$232,$O28) -> 85.7426 | G28: =INDEX('Draft Engine'!$G$3:$G$232,$O28) -> 290.1 | H28: =INDEX('Draft Engine'!$J$3:$J$232,$O28) -> 50.8 | I28: =INDEX('Draft Engine'!$L$3:$L$232,$O28) -> 87.777778 | J28: =INDEX('Draft Engine'!$R$3:$R$232,$O28) -> 11.2 | K28: =INDEX('Draft Engine'!$S$3:$S$232,$O28) -> -14.8 | L28: =INDEX('Draft Engine'!$U$3:$U$232,$O28) -> 79.7426 | M28: =INDEX('Draft Engine'!$W$3:$W$232,$O28) -> 91.7426 | N28: =INDEX('Draft Engine'!$T$3:$T$232,$O28) -> A | O28: =MATCH($A28,'Draft Engine'!$Q$3:$Q$232,0) -> 90
A29: =27 -> 27 | B29: =INDEX('Draft Engine'!$A$3:$A$232,$O29) -> RB | C29: =INDEX('Draft Engine'!$F$3:$F$232,$O29) -> 13 | D29: =INDEX('Draft Engine'!$B$3:$B$232,$O29) -> Derrick Henry | E29: =INDEX('Draft Engine'!$N$3:$N$232,$O29) -> 84.19857 | F29: =INDEX('Draft Engine'!$E$3:$E$232,$O29) -> 85.6674 | G29: =INDEX('Draft Engine'!$G$3:$G$232,$O29) -> 289.8 | H29: =INDEX('Draft Engine'!$J$3:$J$232,$O29) -> 50.8 | I29: =INDEX('Draft Engine'!$L$3:$L$232,$O29) -> 86.25 | J29: =INDEX('Draft Engine'!$R$3:$R$232,$O29) -> 15.4 | K29: =INDEX('Draft Engine'!$S$3:$S$232,$O29) -> -11.6 | L29: =INDEX('Draft Engine'!$U$3:$U$232,$O29) -> 79.6674 | M29: =INDEX('Draft Engine'!$W$3:$W$232,$O29) -> 91.6674 | N29: =INDEX('Draft Engine'!$T$3:$T$232,$O29) -> A | O29: =MATCH($A29,'Draft Engine'!$Q$3:$Q$232,0) -> 45
A30: =28 -> 28 | B30: =INDEX('Draft Engine'!$A$3:$A$232,$O30) -> WR | C30: =INDEX('Draft Engine'!$F$3:$F$232,$O30) -> 12 | D30: =INDEX('Draft Engine'!$B$3:$B$232,$O30) -> Tetairoa McMillan | E30: =INDEX('Draft Engine'!$N$3:$N$232,$O30) -> 84.134333 | F30: =INDEX('Draft Engine'!$E$3:$E$232,$O30) -> 85.74 | G30: =INDEX('Draft Engine'!$G$3:$G$232,$O30) -> 290.1 | H30: =INDEX('Draft Engine'!$J$3:$J$232,$O30) -> 50.8 | I30: =INDEX('Draft Engine'!$L$3:$L$232,$O30) -> 85.555556 | J30: =INDEX('Draft Engine'!$R$3:$R$232,$O30) -> 34.4 | K30: =INDEX('Draft Engine'!$S$3:$S$232,$O30) -> 6.4 | L30: =INDEX('Draft Engine'!$U$3:$U$232,$O30) -> 76.74 | M30: =INDEX('Draft Engine'!$W$3:$W$232,$O30) -> 94.74 | N30: =INDEX('Draft Engine'!$T$3:$T$232,$O30) -> B | O30: =MATCH($A30,'Draft Engine'!$Q$3:$Q$232,0) -> 97
A31: =29 -> 29 | B31: =INDEX('Draft Engine'!$A$3:$A$232,$O31) -> RB | C31: =INDEX('Draft Engine'!$F$3:$F$232,$O31) -> 14 | D31: =INDEX('Draft Engine'!$B$3:$B$232,$O31) -> Chase Brown | E31: =INDEX('Draft Engine'!$N$3:$N$232,$O31) -> 83.837545 | F31: =INDEX('Draft Engine'!$E$3:$E$232,$O31) -> 85.6644 | G31: =INDEX('Draft Engine'!$G$3:$G$232,$O31) -> 289.8 | H31: =INDEX('Draft Engine'!$J$3:$J$232,$O31) -> 50.8 | I31: =INDEX('Draft Engine'!$L$3:$L$232,$O31) -> 83.854167 | J31: =INDEX('Draft Engine'!$R$3:$R$232,$O31) -> 12.1 | K31: =INDEX('Draft Engine'!$S$3:$S$232,$O31) -> -16.9 | L31: =INDEX('Draft Engine'!$U$3:$U$232,$O31) -> 79.6644 | M31: =INDEX('Draft Engine'!$W$3:$W$232,$O31) -> 91.6644 | N31: =INDEX('Draft Engine'!$T$3:$T$232,$O31) -> A | O31: =MATCH($A31,'Draft Engine'!$Q$3:$Q$232,0) -> 46
A32: =30 -> 30 | B32: =INDEX('Draft Engine'!$A$3:$A$232,$O32) -> QB | C32: =INDEX('Draft Engine'!$F$3:$F$232,$O32) -> 2 | D32: =INDEX('Draft Engine'!$B$3:$B$232,$O32) -> Caleb Williams | E32: =INDEX('Draft Engine'!$N$3:$N$232,$O32) -> 83.020754 | F32: =INDEX('Draft Engine'!$E$3:$E$232,$O32) -> 92.1927 | G32: =INDEX('Draft Engine'!$G$3:$G$232,$O32) -> 384.9 | H32: =INDEX('Draft Engine'!$J$3:$J$232,$O32) -> 33.8 | I32: =INDEX('Draft Engine'!$L$3:$L$232,$O32) -> 94.871795 | J32: =INDEX('Draft Engine'!$R$3:$R$232,$O32) -> 107.5 | K32: =INDEX('Draft Engine'!$S$3:$S$232,$O32) -> 77.5 | L32: =INDEX('Draft Engine'!$U$3:$U$232,$O32) -> 86.1927 | M32: =INDEX('Draft Engine'!$W$3:$W$232,$O32) -> 98.1927 | N32: =INDEX('Draft Engine'!$T$3:$T$232,$O32) -> A | O32: =MATCH($A32,'Draft Engine'!$Q$3:$Q$232,0) -> 2
A33: =31 -> 31 | B33: =INDEX('Draft Engine'!$A$3:$A$232,$O33) -> WR | C33: =INDEX('Draft Engine'!$F$3:$F$232,$O33) -> 13 | D33: =INDEX('Draft Engine'!$B$3:$B$232,$O33) -> Tee Higgins | E33: =INDEX('Draft Engine'!$N$3:$N$232,$O33) -> 82.612375 | F33: =INDEX('Draft Engine'!$E$3:$E$232,$O33) -> 84.8225 | G33: =INDEX('Draft Engine'!$G$3:$G$232,$O33) -> 286.3 | H33: =INDEX('Draft Engine'!$J$3:$J$232,$O33) -> 47 | I33: =INDEX('Draft Engine'!$L$3:$L$232,$O33) -> 83.333333 | J33: =INDEX('Draft Engine'!$R$3:$R$232,$O33) -> 38.6 | K33: =INDEX('Draft Engine'!$S$3:$S$232,$O33) -> 7.6 | L33: =INDEX('Draft Engine'!$U$3:$U$232,$O33) -> 75.8225 | M33: =INDEX('Draft Engine'!$W$3:$W$232,$O33) -> 93.8225 | N33: =INDEX('Draft Engine'!$T$3:$T$232,$O33) -> B | O33: =MATCH($A33,'Draft Engine'!$Q$3:$Q$232,0) -> 98
A34: =32 -> 32 | B34: =INDEX('Draft Engine'!$A$3:$A$232,$O34) -> WR | C34: =INDEX('Draft Engine'!$F$3:$F$232,$O34) -> 14 | D34: =INDEX('Draft Engine'!$B$3:$B$232,$O34) -> Justin Jefferson | E34: =INDEX('Draft Engine'!$N$3:$N$232,$O34) -> 82.227147 | F34: =INDEX('Draft Engine'!$E$3:$E$232,$O34) -> 84.7936 | G34: =INDEX('Draft Engine'!$G$3:$G$232,$O34) -> 286.1 | H34: =INDEX('Draft Engine'!$J$3:$J$232,$O34) -> 46.8 | I34: =INDEX('Draft Engine'!$L$3:$L$232,$O34) -> 81.111111 | J34: =INDEX('Draft Engine'!$R$3:$R$232,$O34) -> 14.6 | K34: =INDEX('Draft Engine'!$S$3:$S$232,$O34) -> -17.4 | L34: =INDEX('Draft Engine'!$U$3:$U$232,$O34) -> 78.7936 | M34: =INDEX('Draft Engine'!$W$3:$W$232,$O34) -> 90.7936 | N34: =INDEX('Draft Engine'!$T$3:$T$232,$O34) -> A | O34: =MATCH($A34,'Draft Engine'!$Q$3:$Q$232,0) -> 91
A35: =33 -> 33 | B35: =INDEX('Draft Engine'!$A$3:$A$232,$O35) -> RB | C35: =INDEX('Draft Engine'!$F$3:$F$232,$O35) -> 15 | D35: =INDEX('Draft Engine'!$B$3:$B$232,$O35) -> Josh Jacobs | E35: =INDEX('Draft Engine'!$N$3:$N$232,$O35) -> 81.86127 | F35: =INDEX('Draft Engine'!$E$3:$E$232,$O35) -> 84.4264 | G35: =INDEX('Draft Engine'!$G$3:$G$232,$O35) -> 284.6 | H35: =INDEX('Draft Engine'!$J$3:$J$232,$O35) -> 45.6 | I35: =INDEX('Draft Engine'!$L$3:$L$232,$O35) -> 81.458333 | J35: =INDEX('Draft Engine'!$R$3:$R$232,$O35) -> 24.2 | K35: =INDEX('Draft Engine'!$S$3:$S$232,$O35) -> -8.8 | L35: =INDEX('Draft Engine'!$U$3:$U$232,$O35) -> 78.4264 | M35: =INDEX('Draft Engine'!$W$3:$W$232,$O35) -> 90.4264 | N35: =INDEX('Draft Engine'!$T$3:$T$232,$O35) -> A | O35: =MATCH($A35,'Draft Engine'!$Q$3:$Q$232,0) -> 47
A36: =34 -> 34 | B36: =INDEX('Draft Engine'!$A$3:$A$232,$O36) -> TE | C36: =INDEX('Draft Engine'!$F$3:$F$232,$O36) -> 3 | D36: =INDEX('Draft Engine'!$B$3:$B$232,$O36) -> Colston Loveland | E36: =INDEX('Draft Engine'!$N$3:$N$232,$O36) -> 81.49159 | F36: =INDEX('Draft Engine'!$E$3:$E$232,$O36) -> 88.7531 | G36: =INDEX('Draft Engine'!$G$3:$G$232,$O36) -> 210.6 | H36: =INDEX('Draft Engine'!$J$3:$J$232,$O36) -> 30.9 | I36: =INDEX('Draft Engine'!$L$3:$L$232,$O36) -> 80.769231 | J36: =INDEX('Draft Engine'!$R$3:$R$232,$O36) -> 60.8 | K36: =INDEX('Draft Engine'!$S$3:$S$232,$O36) -> 26.8 | L36: =INDEX('Draft Engine'!$U$3:$U$232,$O36) -> 82.7531 | M36: =INDEX('Draft Engine'!$W$3:$W$232,$O36) -> 94.7531 | N36: =INDEX('Draft Engine'!$T$3:$T$232,$O36) -> A | O36: =MATCH($A36,'Draft Engine'!$Q$3:$Q$232,0) -> 161
A37: =35 -> 35 | B37: =INDEX('Draft Engine'!$A$3:$A$232,$O37) -> WR | C37: =INDEX('Draft Engine'!$F$3:$F$232,$O37) -> 15 | D37: =INDEX('Draft Engine'!$B$3:$B$232,$O37) -> Rashee Rice | E37: =INDEX('Draft Engine'!$N$3:$N$232,$O37) -> 80.987418 | F37: =INDEX('Draft Engine'!$E$3:$E$232,$O37) -> 84.0947 | G37: =INDEX('Draft Engine'!$G$3:$G$232,$O37) -> 283.2 | H37: =INDEX('Draft Engine'!$J$3:$J$232,$O37) -> 43.9 | I37: =INDEX('Draft Engine'!$L$3:$L$232,$O37) -> 78.888889 | J37: =INDEX('Draft Engine'!$R$3:$R$232,$O37) -> 11.5 | K37: =INDEX('Draft Engine'!$S$3:$S$232,$O37) -> -23.5 | L37: =INDEX('Draft Engine'!$U$3:$U$232,$O37) -> 78.0947 | M37: =INDEX('Draft Engine'!$W$3:$W$232,$O37) -> 90.0947 | N37: =INDEX('Draft Engine'!$T$3:$T$232,$O37) -> A | O37: =MATCH($A37,'Draft Engine'!$Q$3:$Q$232,0) -> 95
A38: =36 -> 36 | B38: =INDEX('Draft Engine'!$A$3:$A$232,$O38) -> RB | C38: =INDEX('Draft Engine'!$F$3:$F$232,$O38) -> 16 | D38: =INDEX('Draft Engine'!$B$3:$B$232,$O38) -> Saquon Barkley | E38: =INDEX('Draft Engine'!$N$3:$N$232,$O38) -> 80.980075 | F38: =INDEX('Draft Engine'!$E$3:$E$232,$O38) -> 84.034 | G38: =INDEX('Draft Engine'!$G$3:$G$232,$O38) -> 282.9 | H38: =INDEX('Draft Engine'!$J$3:$J$232,$O38) -> 43.9 | I38: =INDEX('Draft Engine'!$L$3:$L$232,$O38) -> 79.0625 | J38: =INDEX('Draft Engine'!$R$3:$R$232,$O38) -> 19 | K38: =INDEX('Draft Engine'!$S$3:$S$232,$O38) -> -17 | L38: =INDEX('Draft Engine'!$U$3:$U$232,$O38) -> 78.034 | M38: =INDEX('Draft Engine'!$W$3:$W$232,$O38) -> 90.034 | N38: =INDEX('Draft Engine'!$T$3:$T$232,$O38) -> A | O38: =MATCH($A38,'Draft Engine'!$Q$3:$Q$232,0) -> 48
A39: =37 -> 37 | B39: =INDEX('Draft Engine'!$A$3:$A$232,$O39) -> QB | C39: =INDEX('Draft Engine'!$F$3:$F$232,$O39) -> 3 | D39: =INDEX('Draft Engine'!$B$3:$B$232,$O39) -> Drake Maye | E39: =INDEX('Draft Engine'!$N$3:$N$232,$O39) -> 80.683188 | F39: =INDEX('Draft Engine'!$E$3:$E$232,$O39) -> 91.043 | G39: =INDEX('Draft Engine'!$G$3:$G$232,$O39) -> 379.7 | H39: =INDEX('Draft Engine'!$J$3:$J$232,$O39) -> 28.6 | I39: =INDEX('Draft Engine'!$L$3:$L$232,$O39) -> 89.74359 | J39: =INDEX('Draft Engine'!$R$3:$R$232,$O39) -> 49.8 | K39: =INDEX('Draft Engine'!$S$3:$S$232,$O39) -> 12.8 | L39: =INDEX('Draft Engine'!$U$3:$U$232,$O39) -> 85.043 | M39: =INDEX('Draft Engine'!$W$3:$W$232,$O39) -> 97.043 | N39: =INDEX('Draft Engine'!$T$3:$T$232,$O39) -> A | O39: =MATCH($A39,'Draft Engine'!$Q$3:$Q$232,0) -> 3
A40: =38 -> 38 | B40: =INDEX('Draft Engine'!$A$3:$A$232,$O40) -> RB | C40: =INDEX('Draft Engine'!$F$3:$F$232,$O40) -> 17 | D40: =INDEX('Draft Engine'!$B$3:$B$232,$O40) -> Javonte Williams | E40: =INDEX('Draft Engine'!$N$3:$N$232,$O40) -> 80.33176 | F40: =INDEX('Draft Engine'!$E$3:$E$232,$O40) -> 83.8032 | G40: =INDEX('Draft Engine'!$G$3:$G$232,$O40) -> 282 | H40: =INDEX('Draft Engine'!$J$3:$J$232,$O40) -> 43 | I40: =INDEX('Draft Engine'!$L$3:$L$232,$O40) -> 76.666667 | J40: =INDEX('Draft Engine'!$R$3:$R$232,$O40) -> 35.8 | K40: =INDEX('Draft Engine'!$S$3:$S$232,$O40) -> -2.2 | L40: =INDEX('Draft Engine'!$U$3:$U$232,$O40) -> 77.8032 | M40: =INDEX('Draft Engine'!$W$3:$W$232,$O40) -> 89.8032 | N40: =INDEX('Draft Engine'!$T$3:$T$232,$O40) -> A | O40: =MATCH($A40,'Draft Engine'!$Q$3:$Q$232,0) -> 49
A41: =39 -> 39 | B41: =INDEX('Draft Engine'!$A$3:$A$232,$O41) -> WR | C41: =INDEX('Draft Engine'!$F$3:$F$232,$O41) -> 16 | D41: =INDEX('Draft Engine'!$B$3:$B$232,$O41) -> A.J. Brown | E41: =INDEX('Draft Engine'!$N$3:$N$232,$O41) -> 79.533635 | F41: =INDEX('Draft Engine'!$E$3:$E$232,$O41) -> 83.2357 | G41: =INDEX('Draft Engine'!$G$3:$G$232,$O41) -> 279.6 | H41: =INDEX('Draft Engine'!$J$3:$J$232,$O41) -> 40.3 | I41: =INDEX('Draft Engine'!$L$3:$L$232,$O41) -> 76.666667 | J41: =INDEX('Draft Engine'!$R$3:$R$232,$O41) -> 17.8 | K41: =INDEX('Draft Engine'!$S$3:$S$232,$O41) -> -21.2 | L41: =INDEX('Draft Engine'!$U$3:$U$232,$O41) -> 77.2357 | M41: =INDEX('Draft Engine'!$W$3:$W$232,$O41) -> 89.2357 | N41: =INDEX('Draft Engine'!$T$3:$T$232,$O41) -> A | O41: =MATCH($A41,'Draft Engine'!$Q$3:$Q$232,0) -> 89
A42: =40 -> 40 | B42: =INDEX('Draft Engine'!$A$3:$A$232,$O42) -> RB | C42: =INDEX('Draft Engine'!$F$3:$F$232,$O42) -> 18 | D42: =INDEX('Draft Engine'!$B$3:$B$232,$O42) -> Travis Etienne Jr. | E42: =INDEX('Draft Engine'!$N$3:$N$232,$O42) -> 78.978605 | F42: =INDEX('Draft Engine'!$E$3:$E$232,$O42) -> 83.0436 | G42: =INDEX('Draft Engine'!$G$3:$G$232,$O42) -> 278.8 | H42: =INDEX('Draft Engine'!$J$3:$J$232,$O42) -> 39.8 | I42: =INDEX('Draft Engine'!$L$3:$L$232,$O42) -> 74.270833 | J42: =INDEX('Draft Engine'!$R$3:$R$232,$O42) -> 38.4 | K42: =INDEX('Draft Engine'!$S$3:$S$232,$O42) -> -1.6 | L42: =INDEX('Draft Engine'!$U$3:$U$232,$O42) -> 77.0436 | M42: =INDEX('Draft Engine'!$W$3:$W$232,$O42) -> 89.0436 | N42: =INDEX('Draft Engine'!$T$3:$T$232,$O42) -> A | O42: =MATCH($A42,'Draft Engine'!$Q$3:$Q$232,0) -> 50
A43: =41 -> 41 | B43: =INDEX('Draft Engine'!$A$3:$A$232,$O43) -> TE | C43: =INDEX('Draft Engine'!$F$3:$F$232,$O43) -> 4 | D43: =INDEX('Draft Engine'!$B$3:$B$232,$O43) -> Tyler Warren | E43: =INDEX('Draft Engine'!$N$3:$N$232,$O43) -> 78.974397 | F43: =INDEX('Draft Engine'!$E$3:$E$232,$O43) -> 87.2024 | G43: =INDEX('Draft Engine'!$G$3:$G$232,$O43) -> 205.2 | H43: =INDEX('Draft Engine'!$J$3:$J$232,$O43) -> 25.5 | I43: =INDEX('Draft Engine'!$L$3:$L$232,$O43) -> 76.153846 | J43: =INDEX('Draft Engine'!$R$3:$R$232,$O43) -> 65.4 | K43: =INDEX('Draft Engine'!$S$3:$S$232,$O43) -> 24.4 | L43: =INDEX('Draft Engine'!$U$3:$U$232,$O43) -> 81.2024 | M43: =INDEX('Draft Engine'!$W$3:$W$232,$O43) -> 93.2024 | N43: =INDEX('Draft Engine'!$T$3:$T$232,$O43) -> A | O43: =MATCH($A43,'Draft Engine'!$Q$3:$Q$232,0) -> 162
A44: =42 -> 42 | B44: =INDEX('Draft Engine'!$A$3:$A$232,$O44) -> QB | C44: =INDEX('Draft Engine'!$F$3:$F$232,$O44) -> 4 | D44: =INDEX('Draft Engine'!$B$3:$B$232,$O44) -> Justin Herbert | E44: =INDEX('Draft Engine'!$N$3:$N$232,$O44) -> 78.648603 | F44: =INDEX('Draft Engine'!$E$3:$E$232,$O44) -> 90.1169 | G44: =INDEX('Draft Engine'!$G$3:$G$232,$O44) -> 375.5 | H44: =INDEX('Draft Engine'!$J$3:$J$232,$O44) -> 24.4 | I44: =INDEX('Draft Engine'!$L$3:$L$232,$O44) -> 84.615385 | J44: =INDEX('Draft Engine'!$R$3:$R$232,$O44) -> 104.2 | K44: =INDEX('Draft Engine'!$S$3:$S$232,$O44) -> 62.2 | L44: =INDEX('Draft Engine'!$U$3:$U$232,$O44) -> 84.1169 | M44: =INDEX('Draft Engine'!$W$3:$W$232,$O44) -> 96.1169 | N44: =INDEX('Draft Engine'!$T$3:$T$232,$O44) -> A | O44: =MATCH($A44,'Draft Engine'!$Q$3:$Q$232,0) -> 4
A45: =43 -> 43 | B45: =INDEX('Draft Engine'!$A$3:$A$232,$O45) -> WR | C45: =INDEX('Draft Engine'!$F$3:$F$232,$O45) -> 17 | D45: =INDEX('Draft Engine'!$B$3:$B$232,$O45) -> Ladd McConkey | E45: =INDEX('Draft Engine'!$N$3:$N$232,$O45) -> 78.545542 | F45: =INDEX('Draft Engine'!$E$3:$E$232,$O45) -> 82.7325 | G45: =INDEX('Draft Engine'!$G$3:$G$232,$O45) -> 277.5 | H45: =INDEX('Draft Engine'!$J$3:$J$232,$O45) -> 38.2 | I45: =INDEX('Draft Engine'!$L$3:$L$232,$O45) -> 74.444444 | J45: =INDEX('Draft Engine'!$R$3:$R$232,$O45) -> 44.3 | K45: =INDEX('Draft Engine'!$S$3:$S$232,$O45) -> 1.3 | L45: =INDEX('Draft Engine'!$U$3:$U$232,$O45) -> 73.7325 | M45: =INDEX('Draft Engine'!$W$3:$W$232,$O45) -> 91.7325 | N45: =INDEX('Draft Engine'!$T$3:$T$232,$O45) -> B | O45: =MATCH($A45,'Draft Engine'!$Q$3:$Q$232,0) -> 106
A46: =44 -> 44 | B46: =INDEX('Draft Engine'!$A$3:$A$232,$O46) -> WR | C46: =INDEX('Draft Engine'!$F$3:$F$232,$O46) -> 18 | D46: =INDEX('Draft Engine'!$B$3:$B$232,$O46) -> Jaylen Waddle | E46: =INDEX('Draft Engine'!$N$3:$N$232,$O46) -> 77.659958 | F46: =INDEX('Draft Engine'!$E$3:$E$232,$O46) -> 82.3175 | G46: =INDEX('Draft Engine'!$G$3:$G$232,$O46) -> 275.7 | H46: =INDEX('Draft Engine'!$J$3:$J$232,$O46) -> 36.4 | I46: =INDEX('Draft Engine'!$L$3:$L$232,$O46) -> 72.222222 | J46: =INDEX('Draft Engine'!$R$3:$R$232,$O46) -> 48.9 | K46: =INDEX('Draft Engine'!$S$3:$S$232,$O46) -> 4.9 | L46: =INDEX('Draft Engine'!$U$3:$U$232,$O46) -> 70.3175 | M46: =INDEX('Draft Engine'!$W$3:$W$232,$O46) -> 94.3175 | N46: =INDEX('Draft Engine'!$T$3:$T$232,$O46) -> C | O46: =MATCH($A46,'Draft Engine'!$Q$3:$Q$232,0) -> 104
A47: =45 -> 45 | B47: =INDEX('Draft Engine'!$A$3:$A$232,$O47) -> TE | C47: =INDEX('Draft Engine'!$F$3:$F$232,$O47) -> 5 | D47: =INDEX('Draft Engine'!$B$3:$B$232,$O47) -> George Kittle | E47: =INDEX('Draft Engine'!$N$3:$N$232,$O47) -> 77.173289 | F47: =INDEX('Draft Engine'!$E$3:$E$232,$O47) -> 86.2664 | G47: =INDEX('Draft Engine'!$G$3:$G$232,$O47) -> 201.9 | H47: =INDEX('Draft Engine'!$J$3:$J$232,$O47) -> 22.2 | I47: =INDEX('Draft Engine'!$L$3:$L$232,$O47) -> 71.538462 | J47: =INDEX('Draft Engine'!$R$3:$R$232,$O47) -> 115.1 | K47: =INDEX('Draft Engine'!$S$3:$S$232,$O47) -> 70.1 | L47: =INDEX('Draft Engine'!$U$3:$U$232,$O47) -> 77.2664 | M47: =INDEX('Draft Engine'!$W$3:$W$232,$O47) -> 95.2664 | N47: =INDEX('Draft Engine'!$T$3:$T$232,$O47) -> B | O47: =MATCH($A47,'Draft Engine'!$Q$3:$Q$232,0) -> 163
A48: =46 -> 46 | B48: =INDEX('Draft Engine'!$A$3:$A$232,$O48) -> RB | C48: =INDEX('Draft Engine'!$F$3:$F$232,$O48) -> 19 | D48: =INDEX('Draft Engine'!$B$3:$B$232,$O48) -> Cam Skattebo | E48: =INDEX('Draft Engine'!$N$3:$N$232,$O48) -> 77.10187 | F48: =INDEX('Draft Engine'!$E$3:$E$232,$O48) -> 81.8884 | G48: =INDEX('Draft Engine'!$G$3:$G$232,$O48) -> 273.9 | H48: =INDEX('Draft Engine'!$J$3:$J$232,$O48) -> 34.9 | I48: =INDEX('Draft Engine'!$L$3:$L$232,$O48) -> 71.875 | J48: =INDEX('Draft Engine'!$R$3:$R$232,$O48) -> 30.8 | K48: =INDEX('Draft Engine'!$S$3:$S$232,$O48) -> -15.2 | L48: =INDEX('Draft Engine'!$U$3:$U$232,$O48) -> 72.8884 | M48: =INDEX('Draft Engine'!$W$3:$W$232,$O48) -> 90.8884 | N48: =INDEX('Draft Engine'!$T$3:$T$232,$O48) -> B | O48: =MATCH($A48,'Draft Engine'!$Q$3:$Q$232,0) -> 51
A49: =47 -> 47 | B49: =INDEX('Draft Engine'!$A$3:$A$232,$O49) -> WR | C49: =INDEX('Draft Engine'!$F$3:$F$232,$O49) -> 19 | D49: =INDEX('Draft Engine'!$B$3:$B$232,$O49) -> George Pickens | E49: =INDEX('Draft Engine'!$N$3:$N$232,$O49) -> 76.70213 | F49: =INDEX('Draft Engine'!$E$3:$E$232,$O49) -> 81.8366 | G49: =INDEX('Draft Engine'!$G$3:$G$232,$O49) -> 273.7 | H49: =INDEX('Draft Engine'!$J$3:$J$232,$O49) -> 34.4 | I49: =INDEX('Draft Engine'!$L$3:$L$232,$O49) -> 70 | J49: =INDEX('Draft Engine'!$R$3:$R$232,$O49) -> 21.1 | K49: =INDEX('Draft Engine'!$S$3:$S$232,$O49) -> -25.9 | L49: =INDEX('Draft Engine'!$U$3:$U$232,$O49) -> 75.8366 | M49: =INDEX('Draft Engine'!$W$3:$W$232,$O49) -> 87.8366 | N49: =INDEX('Draft Engine'!$T$3:$T$232,$O49) -> A | O49: =MATCH($A49,'Draft Engine'!$Q$3:$Q$232,0) -> 92
A50: =48 -> 48 | B50: =INDEX('Draft Engine'!$A$3:$A$232,$O50) -> WR | C50: =INDEX('Draft Engine'!$F$3:$F$232,$O50) -> 20 | D50: =INDEX('Draft Engine'!$B$3:$B$232,$O50) -> Emeka Egbuka | E50: =INDEX('Draft Engine'!$N$3:$N$232,$O50) -> 76.240917 | F50: =INDEX('Draft Engine'!$E$3:$E$232,$O50) -> 81.735 | G50: =INDEX('Draft Engine'!$G$3:$G$232,$O50) -> 273.3 | H50: =INDEX('Draft Engine'!$J$3:$J$232,$O50) -> 34 | I50: =INDEX('Draft Engine'!$L$3:$L$232,$O50) -> 67.777778 | J50: =INDEX('Draft Engine'!$R$3:$R$232,$O50) -> 34.4 | K50: =INDEX('Draft Engine'!$S$3:$S$232,$O50) -> -13.6 | L50: =INDEX('Draft Engine'!$U$3:$U$232,$O50) -> 69.735 | M50: =INDEX('Draft Engine'!$W$3:$W$232,$O50) -> 93.735 | N50: =INDEX('Draft Engine'!$T$3:$T$232,$O50) -> C | O50: =MATCH($A50,'Draft Engine'!$Q$3:$Q$232,0) -> 103
A51: =49 -> 49 | B51: =INDEX('Draft Engine'!$A$3:$A$232,$O51) -> QB | C51: =INDEX('Draft Engine'!$F$3:$F$232,$O51) -> 5 | D51: =INDEX('Draft Engine'!$B$3:$B$232,$O51) -> Lamar Jackson | E51: =INDEX('Draft Engine'!$N$3:$N$232,$O51) -> 75.972237 | F51: =INDEX('Draft Engine'!$E$3:$E$232,$O51) -> 88.7112 | G51: =INDEX('Draft Engine'!$G$3:$G$232,$O51) -> 369.2 | H51: =INDEX('Draft Engine'!$J$3:$J$232,$O51) -> 18.1 | I51: =INDEX('Draft Engine'!$L$3:$L$232,$O51) -> 79.487179 | J51: =INDEX('Draft Engine'!$R$3:$R$232,$O51) -> 52.6 | K51: =INDEX('Draft Engine'!$S$3:$S$232,$O51) -> 3.6 | L51: =INDEX('Draft Engine'!$U$3:$U$232,$O51) -> 82.7112 | M51: =INDEX('Draft Engine'!$W$3:$W$232,$O51) -> 94.7112 | N51: =INDEX('Draft Engine'!$T$3:$T$232,$O51) -> A | O51: =MATCH($A51,'Draft Engine'!$Q$3:$Q$232,0) -> 5
A52: =50 -> 50 | B52: =INDEX('Draft Engine'!$A$3:$A$232,$O52) -> TE | C52: =INDEX('Draft Engine'!$F$3:$F$232,$O52) -> 6 | D52: =INDEX('Draft Engine'!$B$3:$B$232,$O52) -> Kyle Pitts Sr. | E52: =INDEX('Draft Engine'!$N$3:$N$232,$O52) -> 75.357937 | F52: =INDEX('Draft Engine'!$E$3:$E$232,$O52) -> 85.3045 | G52: =INDEX('Draft Engine'!$G$3:$G$232,$O52) -> 198.6 | H52: =INDEX('Draft Engine'!$J$3:$J$232,$O52) -> 18.9 | I52: =INDEX('Draft Engine'!$L$3:$L$232,$O52) -> 66.923077 | J52: =INDEX('Draft Engine'!$R$3:$R$232,$O52) -> 78.3 | K52: =INDEX('Draft Engine'!$S$3:$S$232,$O52) -> 28.3 | L52: =INDEX('Draft Engine'!$U$3:$U$232,$O52) -> 79.3045 | M52: =INDEX('Draft Engine'!$W$3:$W$232,$O52) -> 91.3045 | N52: =INDEX('Draft Engine'!$T$3:$T$232,$O52) -> A | O52: =MATCH($A52,'Draft Engine'!$Q$3:$Q$232,0) -> 164
A53: =51 -> 51 | B53: =INDEX('Draft Engine'!$A$3:$A$232,$O53) -> WR | C53: =INDEX('Draft Engine'!$F$3:$F$232,$O53) -> 21 | D53: =INDEX('Draft Engine'!$B$3:$B$232,$O53) -> Malik Nabers | E53: =INDEX('Draft Engine'!$N$3:$N$232,$O53) -> 75.137208 | F53: =INDEX('Draft Engine'!$E$3:$E$232,$O53) -> 81.1525 | G53: =INDEX('Draft Engine'!$G$3:$G$232,$O53) -> 270.8 | H53: =INDEX('Draft Engine'!$J$3:$J$232,$O53) -> 31.5 | I53: =INDEX('Draft Engine'!$L$3:$L$232,$O53) -> 65.555556 | J53: =INDEX('Draft Engine'!$R$3:$R$232,$O53) -> 31.9 | K53: =INDEX('Draft Engine'!$S$3:$S$232,$O53) -> -19.1 | L53: =INDEX('Draft Engine'!$U$3:$U$232,$O53) -> 69.1525 | M53: =INDEX('Draft Engine'!$W$3:$W$232,$O53) -> 93.1525 | N53: =INDEX('Draft Engine'!$T$3:$T$232,$O53) -> C | O53: =MATCH($A53,'Draft Engine'!$Q$3:$Q$232,0) -> 102
A54: =52 -> 52 | B54: =INDEX('Draft Engine'!$A$3:$A$232,$O54) -> QB | C54: =INDEX('Draft Engine'!$F$3:$F$232,$O54) -> 6 | D54: =INDEX('Draft Engine'!$B$3:$B$232,$O54) -> Jalen Hurts | E54: =INDEX('Draft Engine'!$N$3:$N$232,$O54) -> 74.843291 | F54: =INDEX('Draft Engine'!$E$3:$E$232,$O54) -> 88.4499 | G54: =INDEX('Draft Engine'!$G$3:$G$232,$O54) -> 368 | H54: =INDEX('Draft Engine'!$J$3:$J$232,$O54) -> 16.9 | I54: =INDEX('Draft Engine'!$L$3:$L$232,$O54) -> 74.358974 | J54: =INDEX('Draft Engine'!$R$3:$R$232,$O54) -> 73.7 | K54: =INDEX('Draft Engine'!$S$3:$S$232,$O54) -> 21.7 | L54: =INDEX('Draft Engine'!$U$3:$U$232,$O54) -> 82.4499 | M54: =INDEX('Draft Engine'!$W$3:$W$232,$O54) -> 94.4499 | N54: =INDEX('Draft Engine'!$T$3:$T$232,$O54) -> A | O54: =MATCH($A54,'Draft Engine'!$Q$3:$Q$232,0) -> 6
A55: =53 -> 53 | B55: =INDEX('Draft Engine'!$A$3:$A$232,$O55) -> RB | C55: =INDEX('Draft Engine'!$F$3:$F$232,$O55) -> 20 | D55: =INDEX('Draft Engine'!$B$3:$B$232,$O55) -> D'Andre Swift | E55: =INDEX('Draft Engine'!$N$3:$N$232,$O55) -> 74.255955 | F55: =INDEX('Draft Engine'!$E$3:$E$232,$O55) -> 79.9856 | G55: =INDEX('Draft Engine'!$G$3:$G$232,$O55) -> 265.9 | H55: =INDEX('Draft Engine'!$J$3:$J$232,$O55) -> 26.9 | I55: =INDEX('Draft Engine'!$L$3:$L$232,$O55) -> 69.479167 | J55: =INDEX('Draft Engine'!$R$3:$R$232,$O55) -> 43.9 | K55: =INDEX('Draft Engine'!$S$3:$S$232,$O55) -> -9.1 | L55: =INDEX('Draft Engine'!$U$3:$U$232,$O55) -> 73.9856 | M55: =INDEX('Draft Engine'!$W$3:$W$232,$O55) -> 85.9856 | N55: =INDEX('Draft Engine'!$T$3:$T$232,$O55) -> A | O55: =MATCH($A55,'Draft Engine'!$Q$3:$Q$232,0) -> 52
A56: =54 -> 54 | B56: =INDEX('Draft Engine'!$A$3:$A$232,$O56) -> RB | C56: =INDEX('Draft Engine'!$F$3:$F$232,$O56) -> 21 | D56: =INDEX('Draft Engine'!$B$3:$B$232,$O56) -> Bucky Irving | E56: =INDEX('Draft Engine'!$N$3:$N$232,$O56) -> 73.833025 | F56: =INDEX('Draft Engine'!$E$3:$E$232,$O56) -> 79.9355 | G56: =INDEX('Draft Engine'!$G$3:$G$232,$O56) -> 265.7 | H56: =INDEX('Draft Engine'!$J$3:$J$232,$O56) -> 26.7 | I56: =INDEX('Draft Engine'!$L$3:$L$232,$O56) -> 67.083333 | J56: =INDEX('Draft Engine'!$R$3:$R$232,$O56) -> 43 | K56: =INDEX('Draft Engine'!$S$3:$S$232,$O56) -> -11 | L56: =INDEX('Draft Engine'!$U$3:$U$232,$O56) -> 70.9355 | M56: =INDEX('Draft Engine'!$W$3:$W$232,$O56) -> 88.9355 | N56: =INDEX('Draft Engine'!$T$3:$T$232,$O56) -> B | O56: =MATCH($A56,'Draft Engine'!$Q$3:$Q$232,0) -> 53
A57: =55 -> 55 | B57: =INDEX('Draft Engine'!$A$3:$A$232,$O57) -> TE | C57: =INDEX('Draft Engine'!$F$3:$F$232,$O57) -> 7 | D57: =INDEX('Draft Engine'!$B$3:$B$232,$O57) -> Harold Fannin Jr. | E57: =INDEX('Draft Engine'!$N$3:$N$232,$O57) -> 73.561889 | F57: =INDEX('Draft Engine'!$E$3:$E$232,$O57) -> 84.3777 | G57: =INDEX('Draft Engine'!$G$3:$G$232,$O57) -> 195.3 | H57: =INDEX('Draft Engine'!$J$3:$J$232,$O57) -> 15.6 | I57: =INDEX('Draft Engine'!$L$3:$L$232,$O57) -> 62.307692 | J57: =INDEX('Draft Engine'!$R$3:$R$232,$O57) -> 82.8 | K57: =INDEX('Draft Engine'!$S$3:$S$232,$O57) -> 27.8 | L57: =INDEX('Draft Engine'!$U$3:$U$232,$O57) -> 78.3777 | M57: =INDEX('Draft Engine'!$W$3:$W$232,$O57) -> 90.3777 | N57: =INDEX('Draft Engine'!$T$3:$T$232,$O57) -> A | O57: =MATCH($A57,'Draft Engine'!$Q$3:$Q$232,0) -> 165
A58: =56 -> 56 | B58: =INDEX('Draft Engine'!$A$3:$A$232,$O58) -> RB | C58: =INDEX('Draft Engine'!$F$3:$F$232,$O58) -> 22 | D58: =INDEX('Draft Engine'!$B$3:$B$232,$O58) -> Quinshon Judkins | E58: =INDEX('Draft Engine'!$N$3:$N$232,$O58) -> 73.47079 | F58: =INDEX('Draft Engine'!$E$3:$E$232,$O58) -> 79.9303 | G58: =INDEX('Draft Engine'!$G$3:$G$232,$O58) -> 265.7 | H58: =INDEX('Draft Engine'!$J$3:$J$232,$O58) -> 26.7 | I58: =INDEX('Draft Engine'!$L$3:$L$232,$O58) -> 64.6875 | J58: =INDEX('Draft Engine'!$R$3:$R$232,$O58) -> 49.9 | K58: =INDEX('Draft Engine'!$S$3:$S$232,$O58) -> -6.1 | L58: =INDEX('Draft Engine'!$U$3:$U$232,$O58) -> 73.9303 | M58: =INDEX('Draft Engine'!$W$3:$W$232,$O58) -> 85.9303 | N58: =INDEX('Draft Engine'!$T$3:$T$232,$O58) -> A | O58: =MATCH($A58,'Draft Engine'!$Q$3:$Q$232,0) -> 54
A59: =57 -> 57 | B59: =INDEX('Draft Engine'!$A$3:$A$232,$O59) -> WR | C59: =INDEX('Draft Engine'!$F$3:$F$232,$O59) -> 22 | D59: =INDEX('Draft Engine'!$B$3:$B$232,$O59) -> Terry McLaurin | E59: =INDEX('Draft Engine'!$N$3:$N$232,$O59) -> 73.179 | F59: =INDEX('Draft Engine'!$E$3:$E$232,$O59) -> 79.9 | G59: =INDEX('Draft Engine'!$G$3:$G$232,$O59) -> 265.6 | H59: =INDEX('Draft Engine'!$J$3:$J$232,$O59) -> 26.3 | I59: =INDEX('Draft Engine'!$L$3:$L$232,$O59) -> 63.333333 | J59: =INDEX('Draft Engine'!$R$3:$R$232,$O59) -> 43 | K59: =INDEX('Draft Engine'!$S$3:$S$232,$O59) -> -14 | L59: =INDEX('Draft Engine'!$U$3:$U$232,$O59) -> 67.9 | M59: =INDEX('Draft Engine'!$W$3:$W$232,$O59) -> 91.9 | N59: =INDEX('Draft Engine'!$T$3:$T$232,$O59) -> C | O59: =MATCH($A59,'Draft Engine'!$Q$3:$Q$232,0) -> 105
A60: =58 -> 58 | B60: =INDEX('Draft Engine'!$A$3:$A$232,$O60) -> TE | C60: =INDEX('Draft Engine'!$F$3:$F$232,$O60) -> 8 | D60: =INDEX('Draft Engine'!$B$3:$B$232,$O60) -> Jake Ferguson | E60: =INDEX('Draft Engine'!$N$3:$N$232,$O60) -> 72.521996 | F60: =INDEX('Draft Engine'!$E$3:$E$232,$O60) -> 84.073 | G60: =INDEX('Draft Engine'!$G$3:$G$232,$O60) -> 194.3 | H60: =INDEX('Draft Engine'!$J$3:$J$232,$O60) -> 14.6 | I60: =INDEX('Draft Engine'!$L$3:$L$232,$O60) -> 57.692308 | J60: =INDEX('Draft Engine'!$R$3:$R$232,$O60) -> 140.8 | K60: =INDEX('Draft Engine'!$S$3:$S$232,$O60) -> 82.8 | L60: =INDEX('Draft Engine'!$U$3:$U$232,$O60) -> 78.073 | M60: =INDEX('Draft Engine'!$W$3:$W$232,$O60) -> 90.073 | N60: =INDEX('Draft Engine'!$T$3:$T$232,$O60) -> A | O60: =MATCH($A60,'Draft Engine'!$Q$3:$Q$232,0) -> 166
A61: =59 -> 59 | B61: =INDEX('Draft Engine'!$A$3:$A$232,$O61) -> QB | C61: =INDEX('Draft Engine'!$F$3:$F$232,$O61) -> 7 | D61: =INDEX('Draft Engine'!$B$3:$B$232,$O61) -> Patrick Mahomes II | E61: =INDEX('Draft Engine'!$N$3:$N$232,$O61) -> 72.11008 | F61: =INDEX('Draft Engine'!$E$3:$E$232,$O61) -> 87.0063 | G61: =INDEX('Draft Engine'!$G$3:$G$232,$O61) -> 361.5 | H61: =INDEX('Draft Engine'!$J$3:$J$232,$O61) -> 10.4 | I61: =INDEX('Draft Engine'!$L$3:$L$232,$O61) -> 69.230769 | J61: =INDEX('Draft Engine'!$R$3:$R$232,$O61) -> 97.4 | K61: =INDEX('Draft Engine'!$S$3:$S$232,$O61) -> 38.4 | L61: =INDEX('Draft Engine'!$U$3:$U$232,$O61) -> 81.0063 | M61: =INDEX('Draft Engine'!$W$3:$W$232,$O61) -> 93.0063 | N61: =INDEX('Draft Engine'!$T$3:$T$232,$O61) -> A | O61: =MATCH($A61,'Draft Engine'!$Q$3:$Q$232,0) -> 7
A62: =60 -> 60 | B62: =INDEX('Draft Engine'!$A$3:$A$232,$O62) -> TE | C62: =INDEX('Draft Engine'!$F$3:$F$232,$O62) -> 9 | D62: =INDEX('Draft Engine'!$B$3:$B$232,$O62) -> Tucker Kraft | E62: =INDEX('Draft Engine'!$N$3:$N$232,$O62) -> 71.504268 | F62: =INDEX('Draft Engine'!$E$3:$E$232,$O62) -> 83.8086 | G62: =INDEX('Draft Engine'!$G$3:$G$232,$O62) -> 193.3 | H62: =INDEX('Draft Engine'!$J$3:$J$232,$O62) -> 13.6 | I62: =INDEX('Draft Engine'!$L$3:$L$232,$O62) -> 53.076923 | J62: =INDEX('Draft Engine'!$R$3:$R$232,$O62) -> 108.3 | K62: =INDEX('Draft Engine'!$S$3:$S$232,$O62) -> 48.3 | L62: =INDEX('Draft Engine'!$U$3:$U$232,$O62) -> 74.8086 | M62: =INDEX('Draft Engine'!$W$3:$W$232,$O62) -> 92.8086 | N62: =INDEX('Draft Engine'!$T$3:$T$232,$O62) -> B | O62: =MATCH($A62,'Draft Engine'!$Q$3:$Q$232,0) -> 167
A63: =61 -> 61 | B63: =INDEX('Draft Engine'!$A$3:$A$232,$O63) -> WR | C63: =INDEX('Draft Engine'!$F$3:$F$232,$O63) -> 23 | D63: =INDEX('Draft Engine'!$B$3:$B$232,$O63) -> Luther Burden III | E63: =INDEX('Draft Engine'!$N$3:$N$232,$O63) -> 71.202792 | F63: =INDEX('Draft Engine'!$E$3:$E$232,$O63) -> 78.6475 | G63: =INDEX('Draft Engine'!$G$3:$G$232,$O63) -> 260.3 | H63: =INDEX('Draft Engine'!$J$3:$J$232,$O63) -> 21 | I63: =INDEX('Draft Engine'!$L$3:$L$232,$O63) -> 61.111111 | J63: =INDEX('Draft Engine'!$R$3:$R$232,$O63) -> 53.1 | K63: =INDEX('Draft Engine'!$S$3:$S$232,$O63) -> -7.9 | L63: =INDEX('Draft Engine'!$U$3:$U$232,$O63) -> 66.6475 | M63: =INDEX('Draft Engine'!$W$3:$W$232,$O63) -> 90.6475 | N63: =INDEX('Draft Engine'!$T$3:$T$232,$O63) -> C | O63: =MATCH($A63,'Draft Engine'!$Q$3:$Q$232,0) -> 108
A64: =62 -> 62 | B64: =INDEX('Draft Engine'!$A$3:$A$232,$O64) -> QB | C64: =INDEX('Draft Engine'!$F$3:$F$232,$O64) -> 8 | D64: =INDEX('Draft Engine'!$B$3:$B$232,$O64) -> Jayden Daniels | E64: =INDEX('Draft Engine'!$N$3:$N$232,$O64) -> 70.93855 | F64: =INDEX('Draft Engine'!$E$3:$E$232,$O64) -> 86.7003 | G64: =INDEX('Draft Engine'!$G$3:$G$232,$O64) -> 360.2 | H64: =INDEX('Draft Engine'!$J$3:$J$232,$O64) -> 9.1 | I64: =INDEX('Draft Engine'!$L$3:$L$232,$O64) -> 64.102564 | J64: =INDEX('Draft Engine'!$R$3:$R$232,$O64) -> 67 | K64: =INDEX('Draft Engine'!$S$3:$S$232,$O64) -> 5 | L64: =INDEX('Draft Engine'!$U$3:$U$232,$O64) -> 77.7003 | M64: =INDEX('Draft Engine'!$W$3:$W$232,$O64) -> 95.7003 | N64: =INDEX('Draft Engine'!$T$3:$T$232,$O64) -> B | O64: =MATCH($A64,'Draft Engine'!$Q$3:$Q$232,0) -> 8
A65: =63 -> 63 | B65: =INDEX('Draft Engine'!$A$3:$A$232,$O65) -> RB | C65: =INDEX('Draft Engine'!$F$3:$F$232,$O65) -> 23 | D65: =INDEX('Draft Engine'!$B$3:$B$232,$O65) -> David Montgomery | E65: =INDEX('Draft Engine'!$N$3:$N$232,$O65) -> 70.47036 | F65: =INDEX('Draft Engine'!$E$3:$E$232,$O65) -> 77.9102 | G65: =INDEX('Draft Engine'!$G$3:$G$232,$O65) -> 257.2 | H65: =INDEX('Draft Engine'!$J$3:$J$232,$O65) -> 18.2 | I65: =INDEX('Draft Engine'!$L$3:$L$232,$O65) -> 62.291667 | J65: =INDEX('Draft Engine'!$R$3:$R$232,$O65) -> 66.4 | K65: =INDEX('Draft Engine'!$S$3:$S$232,$O65) -> 3.4 | L65: =INDEX('Draft Engine'!$U$3:$U$232,$O65) -> 71.9102 | M65: =INDEX('Draft Engine'!$W$3:$W$232,$O65) -> 83.9102 | N65: =INDEX('Draft Engine'!$T$3:$T$232,$O65) -> A | O65: =MATCH($A65,'Draft Engine'!$Q$3:$Q$232,0) -> 55
A66: =64 -> 64 | B66: =INDEX('Draft Engine'!$A$3:$A$232,$O66) -> WR | C66: =INDEX('Draft Engine'!$F$3:$F$232,$O66) -> 24 | D66: =INDEX('Draft Engine'!$B$3:$B$232,$O66) -> Davante Adams | E66: =INDEX('Draft Engine'!$N$3:$N$232,$O66) -> 70.117083 | F66: =INDEX('Draft Engine'!$E$3:$E$232,$O66) -> 78.065 | G66: =INDEX('Draft Engine'!$G$3:$G$232,$O66) -> 257.9 | H66: =INDEX('Draft Engine'!$J$3:$J$232,$O66) -> 18.6 | I66: =INDEX('Draft Engine'!$L$3:$L$232,$O66) -> 58.888889 | J66: =INDEX('Draft Engine'!$R$3:$R$232,$O66) -> 41.5 | K66: =INDEX('Draft Engine'!$S$3:$S$232,$O66) -> -22.5 | L66: =INDEX('Draft Engine'!$U$3:$U$232,$O66) -> 66.065 | M66: =INDEX('Draft Engine'!$W$3:$W$232,$O66) -> 90.065 | N66: =INDEX('Draft Engine'!$T$3:$T$232,$O66) -> C | O66: =MATCH($A66,'Draft Engine'!$Q$3:$Q$232,0) -> 107
A67: =65 -> 65 | B67: =INDEX('Draft Engine'!$A$3:$A$232,$O67) -> RB | C67: =INDEX('Draft Engine'!$F$3:$F$232,$O67) -> 24 | D67: =INDEX('Draft Engine'!$B$3:$B$232,$O67) -> TreVeyon Henderson | E67: =INDEX('Draft Engine'!$N$3:$N$232,$O67) -> 70.01425 | F67: =INDEX('Draft Engine'!$E$3:$E$232,$O67) -> 77.8325 | G67: =INDEX('Draft Engine'!$G$3:$G$232,$O67) -> 256.9 | H67: =INDEX('Draft Engine'!$J$3:$J$232,$O67) -> 17.9 | I67: =INDEX('Draft Engine'!$L$3:$L$232,$O67) -> 59.895833 | J67: =INDEX('Draft Engine'!$R$3:$R$232,$O67) -> 55.4 | K67: =INDEX('Draft Engine'!$S$3:$S$232,$O67) -> -9.6 | L67: =INDEX('Draft Engine'!$U$3:$U$232,$O67) -> 71.8325 | M67: =INDEX('Draft Engine'!$W$3:$W$232,$O67) -> 83.8325 | N67: =INDEX('Draft Engine'!$T$3:$T$232,$O67) -> A | O67: =MATCH($A67,'Draft Engine'!$Q$3:$Q$232,0) -> 56
A68: =66 -> 66 | B68: =INDEX('Draft Engine'!$A$3:$A$232,$O68) -> TE | C68: =INDEX('Draft Engine'!$F$3:$F$232,$O68) -> 10 | D68: =INDEX('Draft Engine'!$B$3:$B$232,$O68) -> Sam LaPorta | E68: =INDEX('Draft Engine'!$N$3:$N$232,$O68) -> 69.699146 | F68: =INDEX('Draft Engine'!$E$3:$E$232,$O68) -> 82.8653 | G68: =INDEX('Draft Engine'!$G$3:$G$232,$O68) -> 190 | H68: =INDEX('Draft Engine'!$J$3:$J$232,$O68) -> 10.3 | I68: =INDEX('Draft Engine'!$L$3:$L$232,$O68) -> 48.461538 | J68: =INDEX('Draft Engine'!$R$3:$R$232,$O68) -> 88.7 | K68: =INDEX('Draft Engine'!$S$3:$S$232,$O68) -> 22.7 | L68: =INDEX('Draft Engine'!$U$3:$U$232,$O68) -> 73.8653 | M68: =INDEX('Draft Engine'!$W$3:$W$232,$O68) -> 91.8653 | N68: =INDEX('Draft Engine'!$T$3:$T$232,$O68) -> B | O68: =MATCH($A68,'Draft Engine'!$Q$3:$Q$232,0) -> 168
A69: =67 -> 67 | B69: =INDEX('Draft Engine'!$A$3:$A$232,$O69) -> QB | C69: =INDEX('Draft Engine'!$F$3:$F$232,$O69) -> 9 | D69: =INDEX('Draft Engine'!$B$3:$B$232,$O69) -> Joe Burrow | E69: =INDEX('Draft Engine'!$N$3:$N$232,$O69) -> 68.659369 | F69: =INDEX('Draft Engine'!$E$3:$E$232,$O69) -> 85.5913 | G69: =INDEX('Draft Engine'!$G$3:$G$232,$O69) -> 355.2 | H69: =INDEX('Draft Engine'!$J$3:$J$232,$O69) -> 4.1 | I69: =INDEX('Draft Engine'!$L$3:$L$232,$O69) -> 58.974359 | J69: =INDEX('Draft Engine'!$R$3:$R$232,$O69) -> 57.3 | K69: =INDEX('Draft Engine'!$S$3:$S$232,$O69) -> -9.7 | L69: =INDEX('Draft Engine'!$U$3:$U$232,$O69) -> 76.5913 | M69: =INDEX('Draft Engine'!$W$3:$W$232,$O69) -> 94.5913 | N69: =INDEX('Draft Engine'!$T$3:$T$232,$O69) -> B | O69: =MATCH($A69,'Draft Engine'!$Q$3:$Q$232,0) -> 9
A70: =68 -> 68 | B70: =INDEX('Draft Engine'!$A$3:$A$232,$O70) -> RB | C70: =INDEX('Draft Engine'!$F$3:$F$232,$O70) -> 25 | D70: =INDEX('Draft Engine'!$B$3:$B$232,$O70) -> Jadarian Price | E70: =INDEX('Draft Engine'!$N$3:$N$232,$O70) -> 68.12921 | F70: =INDEX('Draft Engine'!$E$3:$E$232,$O70) -> 76.6622 | G70: =INDEX('Draft Engine'!$G$3:$G$232,$O70) -> 252 | H70: =INDEX('Draft Engine'!$J$3:$J$232,$O70) -> 13 | I70: =INDEX('Draft Engine'!$L$3:$L$232,$O70) -> 57.5 | J70: =INDEX('Draft Engine'!$R$3:$R$232,$O70) -> 63 | K70: =INDEX('Draft Engine'!$S$3:$S$232,$O70) -> -5 | L70: =INDEX('Draft Engine'!$U$3:$U$232,$O70) -> 67.6622 | M70: =INDEX('Draft Engine'!$W$3:$W$232,$O70) -> 85.6622 | N70: =INDEX('Draft Engine'!$T$3:$T$232,$O70) -> B | O70: =MATCH($A70,'Draft Engine'!$Q$3:$Q$232,0) -> 57
A71: =69 -> 69 | B71: =INDEX('Draft Engine'!$A$3:$A$232,$O71) -> TE | C71: =INDEX('Draft Engine'!$F$3:$F$232,$O71) -> 11 | D71: =INDEX('Draft Engine'!$B$3:$B$232,$O71) -> Dalton Kincaid | E71: =INDEX('Draft Engine'!$N$3:$N$232,$O71) -> 67.889678 | F71: =INDEX('Draft Engine'!$E$3:$E$232,$O71) -> 81.9141 | G71: =INDEX('Draft Engine'!$G$3:$G$232,$O71) -> 186.7 | H71: =INDEX('Draft Engine'!$J$3:$J$232,$O71) -> 7 | I71: =INDEX('Draft Engine'!$L$3:$L$232,$O71) -> 43.846154 | J71: =INDEX('Draft Engine'!$R$3:$R$232,$O71) -> 152 | K71: =INDEX('Draft Engine'!$S$3:$S$232,$O71) -> 83 | L71: =INDEX('Draft Engine'!$U$3:$U$232,$O71) -> 75.9141 | M71: =INDEX('Draft Engine'!$W$3:$W$232,$O71) -> 87.9141 | N71: =INDEX('Draft Engine'!$T$3:$T$232,$O71) -> A | O71: =MATCH($A71,'Draft Engine'!$Q$3:$Q$232,0) -> 169
A72: =70 -> 70 | B72: =INDEX('Draft Engine'!$A$3:$A$232,$O72) -> WR | C72: =INDEX('Draft Engine'!$F$3:$F$232,$O72) -> 25 | D72: =INDEX('Draft Engine'!$B$3:$B$232,$O72) -> Mike Evans | E72: =INDEX('Draft Engine'!$N$3:$N$232,$O72) -> 67.704625 | F72: =INDEX('Draft Engine'!$E$3:$E$232,$O72) -> 76.4775 | G72: =INDEX('Draft Engine'!$G$3:$G$232,$O72) -> 251.2 | H72: =INDEX('Draft Engine'!$J$3:$J$232,$O72) -> 11.9 | I72: =INDEX('Draft Engine'!$L$3:$L$232,$O72) -> 56.666667 | J72: =INDEX('Draft Engine'!$R$3:$R$232,$O72) -> 59.4 | K72: =INDEX('Draft Engine'!$S$3:$S$232,$O72) -> -10.6 | L72: =INDEX('Draft Engine'!$U$3:$U$232,$O72) -> 64.4775 | M72: =INDEX('Draft Engine'!$W$3:$W$232,$O72) -> 88.4775 | N72: =INDEX('Draft Engine'!$T$3:$T$232,$O72) -> C | O72: =MATCH($A72,'Draft Engine'!$Q$3:$Q$232,0) -> 112
A73: =71 -> 71 | B73: =INDEX('Draft Engine'!$A$3:$A$232,$O73) -> QB | C73: =INDEX('Draft Engine'!$F$3:$F$232,$O73) -> 10 | D73: =INDEX('Draft Engine'!$B$3:$B$232,$O73) -> Matthew Stafford | E73: =INDEX('Draft Engine'!$N$3:$N$232,$O73) -> 67.651758 | F73: =INDEX('Draft Engine'!$E$3:$E$232,$O73) -> 85.4197 | G73: =INDEX('Draft Engine'!$G$3:$G$232,$O73) -> 354.4 | H73: =INDEX('Draft Engine'!$J$3:$J$232,$O73) -> 3.3 | I73: =INDEX('Draft Engine'!$L$3:$L$232,$O73) -> 53.846154 | J73: =INDEX('Draft Engine'!$R$3:$R$232,$O73) -> 83.7 | K73: =INDEX('Draft Engine'!$S$3:$S$232,$O73) -> 12.7 | L73: =INDEX('Draft Engine'!$U$3:$U$232,$O73) -> 79.4197 | M73: =INDEX('Draft Engine'!$W$3:$W$232,$O73) -> 91.4197 | N73: =INDEX('Draft Engine'!$T$3:$T$232,$O73) -> A | O73: =MATCH($A73,'Draft Engine'!$Q$3:$Q$232,0) -> 10
A74: =72 -> 72 | B74: =INDEX('Draft Engine'!$A$3:$A$232,$O74) -> WR | C74: =INDEX('Draft Engine'!$F$3:$F$232,$O74) -> 26 | D74: =INDEX('Draft Engine'!$B$3:$B$232,$O74) -> Jordyn Tyson | E74: =INDEX('Draft Engine'!$N$3:$N$232,$O74) -> 67.031667 | F74: =INDEX('Draft Engine'!$E$3:$E$232,$O74) -> 76.22 | G74: =INDEX('Draft Engine'!$G$3:$G$232,$O74) -> 250.1 | H74: =INDEX('Draft Engine'!$J$3:$J$232,$O74) -> 10.8 | I74: =INDEX('Draft Engine'!$L$3:$L$232,$O74) -> 54.444444 | J74: =INDEX('Draft Engine'!$R$3:$R$232,$O74) -> 87.1 | K74: =INDEX('Draft Engine'!$S$3:$S$232,$O74) -> 15.1 | L74: =INDEX('Draft Engine'!$U$3:$U$232,$O74) -> 64.22 | M74: =INDEX('Draft Engine'!$W$3:$W$232,$O74) -> 88.22 | N74: =INDEX('Draft Engine'!$T$3:$T$232,$O74) -> C | O74: =MATCH($A74,'Draft Engine'!$Q$3:$Q$232,0) -> 119
A75: =73 -> 73 | B75: =INDEX('Draft Engine'!$A$3:$A$232,$O75) -> RB | C75: =INDEX('Draft Engine'!$F$3:$F$232,$O75) -> 26 | D75: =INDEX('Draft Engine'!$B$3:$B$232,$O75) -> Jaylen Warren | E75: =INDEX('Draft Engine'!$N$3:$N$232,$O75) -> 67.024115 | F75: =INDEX('Draft Engine'!$E$3:$E$232,$O75) -> 76.0918 | G75: =INDEX('Draft Engine'!$G$3:$G$232,$O75) -> 249.6 | H75: =INDEX('Draft Engine'!$J$3:$J$232,$O75) -> 10.6 | I75: =INDEX('Draft Engine'!$L$3:$L$232,$O75) -> 55.104167 | J75: =INDEX('Draft Engine'!$R$3:$R$232,$O75) -> 68.8 | K75: =INDEX('Draft Engine'!$S$3:$S$232,$O75) -> -4.2 | L75: =INDEX('Draft Engine'!$U$3:$U$232,$O75) -> 70.0918 | M75: =INDEX('Draft Engine'!$W$3:$W$232,$O75) -> 82.0918 | N75: =INDEX('Draft Engine'!$T$3:$T$232,$O75) -> A | O75: =MATCH($A75,'Draft Engine'!$Q$3:$Q$232,0) -> 58
